Workbook
Name index: 'Hypothèses'!$B$11
Name apport: 'Hypothèses'!$B$14
Name durée: 'Hypothèses'!$B$18

Sheet Hypothèses
A1: HYPOTHÈSES D'INVESTISSEMENT — Dispositif Jeanbrun
A2: ✏ SAISIE CONSEILLER — cellule modifiable | E2: 🔒 CALCULÉ AUTOMATIQUEMENT — cellule verrouillée
A3: 🏠 BIEN IMMOBILIER
A4: Prix d'acquisition | B4: 260000 | C4: € | E4: 📐 SURFACE PONDÉRÉE (Annexes)
A5: Frais d'acquisition ("frais de notaire") | B5: 0.03 | C5: % | E5: RDC (OUI / NON) | F5: NON
A6: Coût total acquisition (frais inclus) | B6: =B4*(1+B5) -> 267800 | C6: € | E6: Surface terrasse (m²) | F6: 0
E7: Surface balcon (m²) | F7: 15
A8: Surface habitable | B8: 40 | C8: m²
A9: Zone d'acquisition | B9: A | E9: Surface pondérée (m²) | F9: =B8+MIN(N(F7)+IF(F5="OUI",0,MIN(N(F6),9)),16)/2 -> 47.5
E10: Coefficient multiplicateur | F10: =TRUNC(MIN(0.7+19/F9,1.2),2) -> 1.1
A11: Indexation revenus du client et valeur du bien | B11: 0 | C11: %/an | E11: ▸ RDC=OUI → terrasse exclue ; cap 9/16 m²
E12: Loyer MAX légal (€/mois) | F12: =B24*F9*F10 -> 757.1025
A13: 💳 FINANCEMENT
A14: Apport personnel | B14: 15000 | C14: €
A15: Montant emprunté | B15: =B6-B14 -> 252800 | C15: €
A16: Taux d'intérêt annuel | B16: 0.033 | C16: %
A17: Taux assurance emprunteur | B17: 0.0035 | C17: %
A18: Durée du financement | B18: 25 | C18: ans
A19: Assurance mensuelle | B19: ='Tableau dAMT financier'!F16/12 -> 73.733333 | C19: €/mois
A20: Mensualité crédit (hors assurance) | B20: =('Tableau dAMT financier'!D16+'Tableau dAMT financier'!E16)/12 -> 1238.6228 | C20: €/mois
A21: Frais garantie + dossier + courtage | B21: 4000 | C21: €
A22: 🏘 REVENUS LOCATIFS | E22: 📋 PLAFONDS AMORTISSEMENT
A23: Type de loyer | B23: Loyer intermédiaire | E23: Loyer intermédiaire | F23: 8000
A24: Plafond loyer légal (€/m²/mois) | B24: =VLOOKUP(B9,'Plafonds loyers'!A:D,IF(B23="Loyer intermédiaire",2,IF(B23="Loyer social",3,4)),FALSE()) -> 14.49 | C24: €/m² | E24: Loyer social | F24: 10000
A25: Loyer mensuel retenu ⚠ ≤ MAX légal | B25: =MIN(F26,F12) -> 750 | C25: ≤ MAX légal | E25: Loyer très social | F25: 12000
A26: Loyer annuel | B26: =B25*12 -> 9000 | C26: €/an | E26: Loyer souhaité (conseiller) | F26: 750
A27: Indexation loyers (%/an) | B27: 0.015
A28: Charges exploit. + taxe foncière | B28: 0.3 | C28: % loyers
A30: 📊 DISPOSITIF JEANBRUN
A31: Base amortissement (80% coût total) | B31: =B4*0.8 -> 208000 | C31: €
A32: Taux d'amortissement (selon type) | B32: =IF(B23="Loyer intermédiaire",0.035,IF(B23="Loyer social",0.045,0.055)) -> 0.035 | C32: %
A33: Plafond annuel (taux × base) | B33: =VLOOKUP(B23,E23:F26,2,FALSE()) -> 8000 | C33: €/an
A34: Amortissement annuel | B34: =MIN(B33,B31*B32) -> 7280 | C34: €/an
A35: 👤 SITUATION FISCALE DU CLIENT
A36: Type de revenus | B36: Salaires (abatt. 10%)
A37: Revenus annuels déclarés | B37: 95000 | C37: €/an
A38: Revenus fonciers — autres biens | B38: 5000 | C38: €/an
A39: Nombre de parts fiscales | B39: 2.5 | C39: parts
A40: Taux prélèvements sociaux | B40: 0.172 | C40: %
A41: Nombre de déclarants | B41: 2 | C41: pers.
A42: 💹 PLUS-VALUE À LA REVENTE
A43: Forfait frais d'acquisition PV | B43: 0.075 | C43: %
A44: Forfait travaux (> 5 ans détenus) | B44: 0.15 | C44: %
A45: Taux IR plus-value | B45: 0.19 | C45: %
A46: Taux PS plus-value | B46: 0.172 | C46: %
A48: ⚙ CALCULS INTERMÉDIAIRES
A49: Abattement applicable (calculé) | B49: =IF(B36="Salaires (abatt. 10%)",MAX('Barème fiscal'!B30*B41,MIN(B37*0.1,'Barème fiscal'!B29*B41)),IF(B36="Pensions / Retraites (abatt. 10%)",MAX('Barème fiscal'!B32*B41,MIN(B37*0.1,'Barème fiscal'!B31*B41)),0)) -> 9500 | C49: €
A50: Revenus nets après abattement | B50: =B37-B49 -> 85500 | C50: €

Sheet Synthèse Visuelle
B2: médicis IMMOBILIER NEUF | I2: ▸ DISPOSITIF JEANBRUN — Projection simplifiée · Simulation personnalisée
B4: REVENUS DÉCLARÉS | E4: TRANCHE MARGINALE | H4: PRIX D'ACQUISITION | K4: LOYER INITIAL | N4: SURFACE / ZONE | Q4: ÉCONOMIE FISCALE AN 1
B5: ='Hypothèses'!B37 -> 95000 | E5: ='Synthèse client - simplifiée'!C6 -> 0.3 | H5: ='Hypothèses'!B4 -> 260000 | K5: ='Hypothèses'!B25 -> 750 | N5: ='Hypothèses'!F9&" m² · Zone "&'Hypothèses'!B9 -> 47,5 m² · Zone A | Q5: ='Synthèse client - simplifiée'!E6 -> 5092.2977
B7: ='Hypothèses'!B39&" parts fiscales" -> 2,5 parts fiscales | H7: ='Hypothèses'!B23 -> Loyer intermédiaire
B9: COMPTE EN T · Moyennes mensuelles calculées sur chaque horizon
B11: 9 | C11: ans | H11: 15 | I11: ans | N11: 25 | O11: ans
B12: Fin durée d'engagement | H12: ★ Horizon de référence | N12: Financement soldé · Pleine propriété
B13: ✚ CE QUI RENTRE | E13: − CE QUI SORT | H13: ✚ CE QUI RENTRE | K13: − CE QUI SORT | N13: ✚ CE QUI RENTRE | Q13: − CE QUI SORT
B14: Loyers moy. | C14: ='Synthèse client - simplifiée'!D14 -> 796.61097 | E14: Crédit | F14: ='Synthèse client - simplifiée'!I14 -> 1312.3562 | H14: Loyers moy. | I14: ='Synthèse client - simplifiée'!D22 -> 834.10689 | K14: Crédit | L14: ='Synthèse client - simplifiée'!I22 -> 1312.3562 | N14: Loyers moy. | O14: ='Synthèse client - simplifiée'!D30 -> 901.89071 | Q14: Crédit | R14: ='Synthèse client - simplifiée'!I30 -> 1312.3562
B15: Gain fiscal | C15: ='Synthèse client - simplifiée'!D15 -> 294.11968 | E15: Charges | F15: ='Synthèse client - simplifiée'!I15 -> 238.98329 | H15: Gain fiscal | I15: ='Synthèse client - simplifiée'!D23 -> 260.14178 | K15: Charges | L15: ='Synthèse client - simplifiée'!I23 -> 250.23207 | N15: Gain fiscal | O15: ='Synthèse client - simplifiée'!D31 -> 185.12192 | Q15: Charges | R15: ='Synthèse client - simplifiée'!I31 -> 270.56721
B16: Total | C16: ='Synthèse client - simplifiée'!D16 -> 1090.7307 | E16: Total | F16: ='Synthèse client - simplifiée'!I16 -> 1551.3395 | H16: Total | I16: ='Synthèse client - simplifiée'!D24 -> 1094.2487 | K16: Total | L16: ='Synthèse client - simplifiée'!I24 -> 1562.5882 | N16: Total | O16: ='Synthèse client - simplifiée'!D32 -> 1087.0126 | Q16: Total | R16: ='Synthèse client - simplifiée'!I32 -> 1582.9234
B18: Effort d'épargne mensuel moyen | E18: =ABS('Synthèse client - simplifiée'!G17) -> 460.60881 | H18: Effort d'épargne mensuel moyen | K18: =ABS('Synthèse client - simplifiée'!G25) -> 468.33957 | N18: Effort d'épargne mensuel moyen | Q18: =ABS('Synthèse client - simplifiée'!G33) -> 495.91076
B19: ← Reste à charge mensuel réel après loyers et économie fiscale | H19: ← Reste à charge mensuel réel après loyers et économie fiscale | N19: ← Reste à charge mensuel réel après loyers et économie fiscale
B20: ="Capital net si prix de vente = prix d'achat · dont "&TEXT(ABS('Synthèse client - simplifiée'!M17),"#,##0")&" € via Jeanbrun" -> Capital net si prix de vente = prix d'achat · dont 24 236 € via Jeanbrun | H20: ="Capital net si prix de vente = prix d'achat · dont "&TEXT(ABS('Synthèse client - simplifiée'!M25),"#,##0")&" € via Jeanbrun" -> Capital net si prix de vente = prix d'achat · dont 43 189 € via Jeanbrun | N20: ="Capital net si prix de vente = prix d'achat · dont "&TEXT(ABS('Synthèse client - simplifiée'!M33),"#,##0")&" € via Jeanbrun" -> Capital net si prix de vente = prix d'achat · dont 76 066 € via Jeanbrun
B21: ='Synthèse client - simplifiée'!M14 -> 73286.154 | H21: ='Synthèse client - simplifiée'!M22 -> 122412.87 | N21: ='Synthèse client - simplifiée'!M30 -> 250441.1
B23: Capital net constitué par année de détention (Valeur revente - CRD - impôt PV) · Hypothèses de revalorisation du bien à 0% et 1,5%
B39: 💶 | C39: Le côté vert (+) | H39: 🏦 | I39: Le côté rouge (−) | N39: 📊 | O39: Le gain fiscal — 2 composantes
C40: Ce que vous percevez : loyers encaissés + économie d'impôt grâce au dispositif Jeanbrun. | I40: Ce que vous déboursez : mensualité de crédit + charges d'exploitation annuelles (gestion / GLI / taxe foncière / assurance PNO / provisions menus travaux :;ces charges sont estimées)) | O40: Déficit naturel (acquis sans Jeanbrun) + avantage lié à l'amortissement Jeanbrun. Les deux s'additionnent.
B45: www.medicis-immobilier-neuf.fr · Simulation personnalisée non contractuelle · Hypothèses d'indexation et fiscalité constantes - Tout investissementlocatif comporte des risques (location / impayés / travbaux / baisse de valeur)

Sheet Synthèse client - simplifiée
A1: PROJECTION SIMPLIFIÉE — DISPOSITIF JEANBRUN
A2: Compte en T • Moyennes mensuelles • Document non contractuel
A4: SITUATION DU FOYER | F4: OPÉRATION IMMOBILIÈRE
A5: Revenus déclarés | C5: ='Synthèse Client - détaillée'!C5 -> 95000 | D5: Parts | E5: ='Synthèse Client - détaillée'!F5 -> 2.5 | F5: Prix d'acquisition | H5: ='Synthèse Client - détaillée'!J5 -> 260000 | I5: ='Synthèse Client - détaillée'!M5 -> A
A6: TMI | C6: ='Synthèse Client - détaillée'!F6 -> 0.3 | D6: Éco. fiscale an 1 | E6: ='Synthèse Client - détaillée'!F7 -> 5092.2977 | F6: Surface pondérée | H6: ='Synthèse Client - détaillée'!J6 -> 47.5 | I6: ='Synthèse Client - détaillée'!M7
A7: Mensualité crédit | C7: ='Synthèse Client - détaillée'!F12 -> 1312.3562 | D7: Apport | E7: ='Synthèse Client - détaillée'!C10 -> 15000 | F7: Loyer mensuel initial estimé | H7: ='Synthèse Client - détaillée'!J7 -> 750 | I7: ='Synthèse Client - détaillée'!M6 -> Loyer intermédiaire
A11: 🔹 HORIZON 9 ANS - COMPTE EN T
A12: Moyennes mensuelles calculées sur 9 ans (108 mois)
A13: CE QUI RENTRE (+) | F13: CE QUI SORT (−) | K13: BILAN À 9 ANS
A14: Loyer mensuel moyen | D14: =AVERAGE(Moteur!B4:B12)/12 -> 796.61097 | F14: Mensualité de crédit | I14: ='Hypothèses'!B20+'Hypothèses'!B19 -> 1312.3562 | K14: Capital consitué (net PV) | M14: =Moteur!AH12 -> 73286.154
A15: Gain Fiscal à réinvestir / mois | D15: =SUM(Moteur!AG4:AG12)/(9*12) -> 294.11968 | F15: Charges d'exploitation / mois | I15: =AVERAGE(Moteur!C4:C12)/12 -> 238.98329 | K15: Gain fiscal total | M15: =SUM(Moteur!AG4:AG12) -> 31764.926
A16: TOTAL ENTRÉES | D16: =D14+D15 -> 1090.7307 | F16: TOTAL SORTIES | I16: =I14+I15 -> 1551.3395 | K16: dont déficit naturel (intérêts) | M16: =M15-M17 -> 7528.654
A17: EFFORT D'INVESTISSEMENT MENSUEL MOYEN | G17: =D16-I16 -> -460.60881 | K17: dont Jeanbrun (amortissement) | M17: =SUM(Moteur!B125:J125) -> 24236.272
A19: 🔸 HORIZON 15 ANS - COMPTE EN T
A20: Moyennes mensuelles calculées sur 15 ans (180 mois)
A21: CE QUI RENTRE (+) | F21: CE QUI SORT (−) | K21: BILAN À 15 ANS
A22: Loyer mensuel moyen | D22: =AVERAGE(Moteur!B4:B18)/12 -> 834.10689 | F22: Mensualité de crédit | I22: ='Hypothèses'!B20+'Hypothèses'!B19 -> 1312.3562 | K22: Capital consitué (net PV) | M22: =Moteur!AH18 -> 122412.87
A23: Gain Fiscal à réinvestir / mois | D23: =SUM(Moteur!AG4:AG18)/(15*12) -> 260.14178 | F23: Charges d'exploitation / mois | I23: =AVERAGE(Moteur!C4:C18)/12 -> 250.23207 | K23: Gain fiscal total | M23: =SUM(Moteur!AG4:AG18) -> 46825.52
A24: TOTAL ENTRÉES | D24: =D22+D23 -> 1094.2487 | F24: TOTAL SORTIES | I24: =I22+I23 -> 1562.5882 | K24: dont déficit naturel (intérêts) | M24: =M23-M25 -> 3636.2605
A25: EFFORT D'INVESTISSEMENT MENSUEL MOYEN | G25: =D24-I24 -> -468.33957 | K25: dont Jeanbrun (amortissement) | M25: =SUM(Moteur!B125:P125) -> 43189.26
A27: ⭐ HORIZON 25 ANS - COMPTE EN T
A28: Moyennes mensuelles calculées sur 25 ans (300 mois)
A29: CE QUI RENTRE (+) | F29: CE QUI SORT (−) | K29: BILAN À 25 ANS
A30: Loyer mensuel moyen | D30: =AVERAGE(Moteur!B4:B28)/12 -> 901.89071 | F30: Mensualité de crédit | I30: ='Hypothèses'!B20+'Hypothèses'!B19 -> 1312.3562 | K30: Capital consitué (net PV) | M30: =Moteur!AH28 -> 250441.1
A31: Gain Fiscal à réinvestir / mois | D31: =SUM(Moteur!AG4:AG28)/(25*12) -> 185.12192 | F31: Charges d'exploitation / mois | I31: =AVERAGE(Moteur!C4:C28)/12 -> 270.56721 | K31: Gain fiscal total | M31: =SUM(Moteur!AG4:AG28) -> 55536.575
A32: TOTAL ENTRÉES | D32: =D30+D31 -> 1087.0126 | F32: TOTAL SORTIES | I32: =I30+I31 -> 1582.9234 | K32: dont déficit naturel (intérêts) | M32: =M31-M33 -> -20529.165
A33: EFFORT D'INVESTISSEMENT MENSUEL MOYEN | G33: =D32-I32 -> -495.91076 | K33: dont Jeanbrun (amortissement) | M33: =SUM(Moteur!B125:Z125) -> 76065.74
A36: COMMENT LIRE CE TABLEAU
A37: ▸ Le côté VERT (+) = ce que vous percevez : loyers + économie d'impôt grâce au dispositif Jeanbrun.
A38: ▸ Le côté ROUGE (−) = ce que vous déboursez : mensualité de crédit + charges d'exploitation.
A39: ▸ L'EFFORT D'ÉPARGNE = reste à charge réel. Un chiffre négatif = complément mensuel à prévoir.
A40: ▸ Le « Gain fiscal total » se décompose en deux parties qui s'additionnent :
A41: – « dont déficit naturel » : l'économie liée aux intérêts d'emprunt, acquise même sans le Jeanbrun.
A42: – « dont Jeanbrun » : l'économie supplémentaire apportée par l'amortissement du dispositif.
A43: ▸ Ce document est une simulation non contractuelle. Hypothèses d'indexation et fiscalité constantes.
A45: médicis IMMOBILIER NEUF — www.medicis-immobilier-neuf.fr
A46: Ce document est une simulation personnalisée et non contractuelle.
A92: Données graphiques (masqué)
A93: Année | B93: 1 | C93: 2 | D93: 3 | E93: 4 | F93: 5 | G93: 6 | H93: 7 | I93: 8 | J93: 9 | K93: 10 | L93: 11 | M93: 12 | N93: 13 | O93: 14 | P93: 15 | Q93: 16 | R93: 17 | S93: 18 | T93: 19 | U93: 20 | V93: 21 | W93: 22 | X93: 23 | Y93: 24 | Z93: 25
A94: Enrichissement 0% | B94: =Moteur!B102 -> 13820.615 | C94: =Moteur!C102 -> 20663.045 | D94: =Moteur!D102 -> 26887.643 | E94: =Moteur!E102 -> 31560.888 | F94: =Moteur!F102 -> 36478.998 | G94: =Moteur!G102 -> 50403.338 | H94: =Moteur!H102 -> 58471.426 | I94: =Moteur!I102 -> 66809.825 | ... Z94: =Moteur!Z102 -> 250441.1
A95: Enrichissement 1,5%/an | B95: =Moteur!B107 -> 17720.615 | C95: =Moteur!C107 -> 27465.048 | D95: =Moteur!D107 -> 34464.772 | E95: =Moteur!E107 -> 41739.873 | F95: =Moteur!F107 -> 49298.868 | G95: =Moteur!G107 -> 71403.455 | H95: =Moteur!H107 -> 80020.536 | I95: =Moteur!I107 -> 89280.21 | ... Z95: =Moteur!Z107 -> 358612.07
A96: Sans Jeanbrun (0%) | B96: =Moteur!B146 -> 13820.615 | C96: =Moteur!C146 -> 20663.045 | D96: =Moteur!D146 -> 27734.723 | E96: =Moteur!E146 -> 35043.328 | F96: =Moteur!F146 -> 42596.798 | G96: =Moteur!G146 -> 50403.338 | H96: =Moteur!H146 -> 58471.426 | I96: =Moteur!I146 -> 66809.825 | ... Z96: =Moteur!Z146 -> 260000
A97: Sans Jeanbrun (1,5%/an) | B97: =Moteur!B147 -> 17720.615 | C97: =Moteur!C147 -> 28521.545 | D97: =Moteur!D147 -> 39611.1 | E97: =Moteur!E147 -> 50997.851 | F97: =Moteur!F147 -> 62475.668 | G97: =Moteur!G147 -> 74698.586 | H97: =Moteur!H147 -> 87031.103 | I97: =Moteur!I147 -> 99697.897 | ... Z97: =Moteur!Z147 -> 372698.87
A99: Bilan net avec JB 0% | B99: =Moteur!B162 -> 3176.5914 | C99: =Moteur!C162 -> 4360.6508 | D99: =Moteur!D162 -> 4925.2453 | E99: =Moteur!E162 -> 3935.5585 | F99: =Moteur!F162 -> 3186.4492 | G99: =Moteur!G162 -> 11437.858 | H99: =Moteur!H162 -> 13825.812 | I99: =Moteur!I162 -> 16475.316 | ... Z99: =Moteur!Z162 -> 95379.824
A100: Bilan net avec JB 1,5%/an | B100: =Moteur!B163 -> 7076.5914 | C100: =Moteur!C163 -> 11162.654 | D100: =Moteur!D163 -> 12502.374 | E100: =Moteur!E163 -> 14114.544 | F100: =Moteur!F163 -> 16006.32 | G100: =Moteur!G163 -> 32437.975 | H100: =Moteur!H163 -> 35374.923 | I100: =Moteur!I163 -> 38945.701 | ... Z100: =Moteur!Z163 -> 203550.79
A101: Bilan net sans JB 0% | B101: =Moteur!B164 -> -7719.3613 | C101: =Moteur!C164 -> -9147.3508 | D101: =Moteur!D164 -> -10352.885 | E101: =Moteur!E164 -> -11375.284 | F101: =Moteur!F164 -> -12209.399 | G101: =Moteur!G164 -> -12849.925 | H101: =Moteur!H164 -> -13291.392 | I101: =Moteur!I164 -> -13528.165 | ... Z101: =Moteur!Z164 -> 20161.032

Sheet Synthèse Client - détaillée
A1: PROJECTION FINANCIÈRE — DISPOSITIF JEANBRUN
A2: Simulation personnalisée • Document non contractuel
A4: SITUATION DU FOYER | H4: OPÉRATION IMMOBILIÈRE
A5: Revenus déclarés (avant abatt.) | C5: ='Hypothèses'!B37 -> 95000 | D5: Nombre de parts | F5: ='Hypothèses'!B39 -> 2.5 | H5: Prix d'acquisition | J5: ='Hypothèses'!B4 -> 260000 | K5: Zone | M5: ='Hypothèses'!B9 -> A
A6: Impôt avant opération | C6: =Moteur!P4 -> 12458.98 | D6: TMI | F6: =Moteur!L4 -> 0.3 | H6: Surface pondérée | J6: ='Hypothèses'!F9 -> 47.5 | K6: Type de loyer | M6: ='Hypothèses'!B23 -> Loyer intermédiaire
A7: Impôt après opération (an 1) | C7: =Moteur!AF4 -> 7366.6823 | D7: Économie fiscale an 1 | F7: =Moteur!AG4 -> 5092.2977 | H7: Loyer mensuel initial | J7: ='Hypothèses'!B25 -> 750
A9: FINANCEMENT | H9: DISPOSITIF JEANBRUN
A10: Apport personnel | C10: ='Hypothèses'!B14 -> 15000 | H10: Base amortissable (80%) | J10: ='Hypothèses'!B31 -> 208000
A11: Montant emprunté | C11: ='Hypothèses'!B15 -> 252800 | H11: Amortissement annuel | J11: ='Hypothèses'!B34 -> 7280
A12: Taux nominal | C12: ='Hypothèses'!B16 -> 0.033 | D12: Mensualité totale | F12: ='Tableau dAMT financier'!F8 -> 1312.3562 | H12: Plafond annuel | J12: ='Hypothèses'!B33 -> 8000 | K12: Charges exploitation | M12: ='Hypothèses'!B28 -> 0.3
A14: PROJECTION ANNUELLE
A15: Année | B15: Loyers perçus | C15: Rembours. prêt | D15: Charges exploit. | E15: Amort. Jeanbrun | F15: Revenu foncier net imputé | G15: Impôt avant | H15: Impôt après | I15: Économie fiscale | J15: Effort d'investissement mensuel | K15: Capital net constitué net (0%) | L15: Capital net constitué. net (1,5%) | M15: Amt restant
A16: =Moteur!A4 -> 1 | B16: =Moteur!B4 -> 9000 | C16: ='Tableau dAMT financier'!G16 -> 15748.274 | D16: =Moteur!C4 -> 2700 | E16: =Moteur!F4 -> 7280 | F16: =Moteur!T4 -> -9107.659 | G16: =Moteur!P4 -> 12458.98 | H16: =Moteur!AF4 -> 7366.6823 | I16: =Moteur!AG4 -> 5092.2977 | J16: =Moteur!AI4 -> -362.99803 | K16: =Moteur!B102 -> 13820.615 | L16: =Moteur!B107 -> 17720.615 | M16: ='Hypothèses'!$B$31-Moteur!AL4 -> 200720
A17: =Moteur!A5 -> 2 | B17: =Moteur!B5 -> 9135 | C17: ='Tableau dAMT financier'!G17 -> 15748.274 | D17: =Moteur!C5 -> 2740.5 | E17: =Moteur!F5 -> 7280 | F17: =Moteur!T5 -> -4791.3437 | G17: =Moteur!P5 -> 12356.98 | H17: =Moteur!AF5 -> 8661.5769 | I17: =Moteur!AG5 -> 3695.4031 | J17: =Moteur!AI5 -> -471.53091 | K17: =Moteur!C102 -> 20663.045 | L17: =Moteur!C107 -> 27465.048 | M17: ='Hypothèses'!$B$31-Moteur!AL5 -> 193440
A18: =Moteur!A6 -> 3 | B18: =Moteur!B6 -> 9272.025 | C18: ='Tableau dAMT financier'!G18 -> 15748.274 | D18: =Moteur!C6 -> 2781.6075 | E18: =Moteur!F6 -> 7280 | F18: =Moteur!T6 -> -4466.1793 | G18: =Moteur!P6 -> 12356.98 | H18: =Moteur!AF6 -> 8759.1262 | I18: =Moteur!AG6 -> 3597.8538 | J18: =Moteur!AI6 -> -471.6669 | K18: =Moteur!D102 -> 26887.643 | L18: =Moteur!D107 -> 34464.772 | M18: ='Hypothèses'!$B$31-Moteur!AL6 -> 186160
A19: =Moteur!A7 -> 4 | B19: =Moteur!B7 -> 9411.1054 | C19: ='Tableau dAMT financier'!G19 -> 15748.274 | D19: =Moteur!C7 -> 2823.3316 | E19: =Moteur!F7 -> 7280 | F19: =Moteur!T7 -> -4131.8955 | G19: =Moteur!P7 -> 12356.98 | H19: =Moteur!AF7 -> 8859.4114 | I19: =Moteur!AG7 -> 3497.5686 | J19: =Moteur!AI7 -> -471.91097 | K19: =Moteur!E102 -> 31560.888 | L19: =Moteur!E107 -> 41739.873 | M19: ='Hypothèses'!$B$31-Moteur!AL7 -> 178880
A20: =Moteur!A8 -> 5 | B20: =Moteur!B8 -> 9552.272 | C20: ='Tableau dAMT financier'!G20 -> 15748.274 | D20: =Moteur!C8 -> 2865.6816 | E20: =Moteur!F8 -> 7280 | F20: =Moteur!T8 -> -3788.2134 | G20: =Moteur!P8 -> 12356.98 | H20: =Moteur!AF8 -> 8962.516 | I20: =Moteur!AG8 -> 3394.464 | J20: =Moteur!AI8 -> -472.26831 | K20: =Moteur!F102 -> 36478.998 | L20: =Moteur!F107 -> 49298.868 | M20: ='Hypothèses'!$B$31-Moteur!AL8 -> 171600
A21: =Moteur!A9 -> 6 | B21: =Moteur!B9 -> 9695.556 | C21: ='Tableau dAMT financier'!G21 -> 15748.274 | D21: =Moteur!C9 -> 2908.6668 | E21: =Moteur!F9 -> 7280 | F21: =Moteur!T9 -> -3434.8451 | G21: =Moteur!P9 -> 12356.98 | H21: =Moteur!AF9 -> 9068.5265 | I21: =Moteur!AG9 -> 3288.4535 | J21: =Moteur!AI9 -> -472.74428 | K21: =Moteur!G102 -> 50403.338 | L21: =Moteur!G107 -> 71403.455 | M21: ='Hypothèses'!$B$31-Moteur!AL9 -> 164320
A22: =Moteur!A10 -> 7 | B22: =Moteur!B10 -> 9840.9894 | C22: ='Tableau dAMT financier'!G22 -> 15748.274 | D22: =Moteur!C10 -> 2952.2968 | E22: =Moteur!F10 -> 7280 | F22: =Moteur!T10 -> -3071.4935 | G22: =Moteur!P10 -> 12356.98 | H22: =Moteur!AF10 -> 9177.5319 | I22: =Moteur!AG10 -> 3179.4481 | J22: =Moteur!AI10 -> -473.34445 | K22: =Moteur!H102 -> 58471.426 | L22: =Moteur!H107 -> 80020.536 | M22: ='Hypothèses'!$B$31-Moteur!AL10 -> 157040
A23: =Moteur!A11 -> 8 | B23: =Moteur!B11 -> 9988.6042 | C23: ='Tableau dAMT financier'!G23 -> 15748.274 | D23: =Moteur!C11 -> 2996.5813 | E23: =Moteur!F11 -> 7280 | F23: =Moteur!T11 -> -2697.8521 | G23: =Moteur!P11 -> 12356.98 | H23: =Moteur!AF11 -> 9289.6244 | I23: =Moteur!AG11 -> 3067.3556 | J23: =Moteur!AI11 -> -474.07462 | K23: =Moteur!I102 -> 66809.825 | L23: =Moteur!I107 -> 89280.21 | M23: ='Hypothèses'!$B$31-Moteur!AL11 -> 149760
A24: =Moteur!A12 -> 9 | B24: =Moteur!B12 -> 10138.433 | C24: ='Tableau dAMT financier'!G24 -> 15748.274 | D24: =Moteur!C12 -> 3041.53 | E24: =Moteur!F12 -> 7280 | F24: =Moteur!T12 -> -2313.6043 | G24: =Moteur!P12 -> 12356.98 | H24: =Moteur!AF12 -> 9404.8987 | I24: =Moteur!AG12 -> 2952.0813 | J24: =Moteur!AI12 -> -474.94079 | K24: =Moteur!J102 -> 73286.154 | L24: =Moteur!J107 -> 99194.933 | M24: ='Hypothèses'!$B$31-Moteur!AL12 -> 142480
A25: =Moteur!A13 -> 10 | B25: =Moteur!B13 -> 10290.51 | C25: ='Tableau dAMT financier'!G25 -> 15748.274 | D25: =Moteur!C13 -> 3087.1529 | E25: =Moteur!F13 -> 7280 | F25: =Moteur!T13 -> -1918.4235 | G25: =Moteur!P13 -> 12356.98 | H25: =Moteur!AF13 -> 9523.453 | I25: =Moteur!AG13 -> 2833.527 | J25: =Moteur!AI13 -> -475.94918 | K25: =Moteur!K102 -> 80175.502 | L25: =Moteur!K107 -> 109777.53 | M25: ='Hypothèses'!$B$31-Moteur!AL13 -> 135200
A26: =Moteur!A14 -> 11 | B26: =Moteur!B14 -> 10444.867 | C26: ='Tableau dAMT financier'!G26 -> 15748.274 | D26: =Moteur!C14 -> 3133.4602 | E26: =Moteur!F14 -> 7280 | F26: =Moteur!T14 -> -1511.9724 | G26: =Moteur!P14 -> 12356.98 | H26: =Moteur!AF14 -> 9645.3883 | I26: =Moteur!AG14 -> 2711.5917 | J26: =Moteur!AI14 -> -477.10626 | K26: =Moteur!L102 -> 87570.556 | L26: =Moteur!L107 -> 121041.2 | M26: ='Hypothèses'!$B$31-Moteur!AL14 -> 127920
A27: =Moteur!A15 -> 12 | B27: =Moteur!B15 -> 10601.54 | C27: ='Tableau dAMT financier'!G27 -> 15748.274 | D27: =Moteur!C15 -> 3180.4621 | E27: =Moteur!F15 -> 7280 | F27: =Moteur!T15 -> -1093.903 | G27: =Moteur!P15 -> 12356.98 | H27: =Moteur!AF15 -> 9770.8091 | I27: =Moteur!AG15 -> 2586.1709 | J27: =Moteur!AI15 -> -478.41874 | K27: =Moteur!M102 -> 95481.313 | L27: =Moteur!M107 -> 132999.54 | M27: ='Hypothèses'!$B$31-Moteur!AL15 -> 120640
A28: =Moteur!A16 -> 13 | B28: =Moteur!B16 -> 10760.564 | C28: ='Tableau dAMT financier'!G28 -> 15748.274 | D28: =Moteur!C16 -> 3228.1691 | E28: =Moteur!F16 -> 7280 | F28: =Moteur!T16 -> -663.85601 | G28: =Moteur!P16 -> 12356.98 | H28: =Moteur!AF16 -> 9899.8232 | I28: =Moteur!AG16 -> 2457.1568 | J28: =Moteur!AI16 -> -479.89357 | K28: =Moteur!N102 -> 103918.11 | L28: =Moteur!N107 -> 145666.55 | M28: ='Hypothèses'!$B$31-Moteur!AL16 -> 113360
A29: =Moteur!A17 -> 14 | B29: =Moteur!B17 -> 10921.972 | C29: ='Tableau dAMT financier'!G29 -> 15748.274 | D29: =Moteur!C17 -> 3276.5916 | E29: =Moteur!F17 -> 7280 | F29: =Moteur!T17 -> -221.46064 | G29: =Moteur!P17 -> 12356.98 | H29: =Moteur!AF17 -> 10032.542 | I29: =Moteur!AG17 -> 2324.4382 | J29: =Moteur!AI17 -> -481.53796 | K29: =Moteur!O102 -> 112891.61 | L29: =Moteur!O107 -> 159056.64 | M29: ='Hypothèses'!$B$31-Moteur!AL17 -> 106080
A30: =Moteur!A18 -> 15 | B30: =Moteur!B18 -> 11085.802 | C30: ='Tableau dAMT financier'!G30 -> 15748.274 | D30: =Moteur!C18 -> 3325.7405 | E30: =Moteur!F18 -> 7280 | F30: =Moteur!T18 -> 233.66597 | G30: =Moteur!P18 -> 12356.98 | H30: =Moteur!AF18 -> 10209.27 | I30: =Moteur!AG18 -> 2147.7097 | J30: =Moteur!AI18 -> -486.70861 | K30: =Moteur!P102 -> 122412.87 | L30: =Moteur!P107 -> 173184.66 | M30: ='Hypothèses'!$B$31-Moteur!AL18 -> 98800
A31: =Moteur!A19 -> 16 | B31: =Moteur!B19 -> 11252.089 | C31: ='Tableau dAMT financier'!G31 -> 15748.274 | D31: =Moteur!C19 -> 3375.6266 | E31: =Moteur!F19 -> 7280 | F31: =Moteur!T19 -> 701.91899 | G31: =Moteur!P19 -> 12356.98 | H31: =Moteur!AF19 -> 10425.519 | I31: =Moteur!AG19 -> 1931.461 | J31: =Moteur!AI19 -> -495.02925 | K31: =Moteur!Q102 -> 132493.29 | L31: =Moteur!Q107 -> 188065.89 | M31: ='Hypothèses'!$B$31-Moteur!AL19 -> 91520
A32: =Moteur!A20 -> 17 | B32: =Moteur!B20 -> 11420.87 | C32: ='Tableau dAMT financier'!G32 -> 15748.274 | D32: =Moteur!C20 -> 3426.261 | E32: =Moteur!F20 -> 7280 | F32: =Moteur!T20 -> 1183.7064 | G32: =Moteur!P20 -> 12356.98 | H32: =Moteur!AF20 -> 10643.37 | I32: =Moteur!AG20 -> 1713.6097 | J32: =Moteur!AI20 -> -503.33795 | K32: =Moteur!R102 -> 143144.65 | L32: =Moteur!R107 -> 203716.07 | M32: ='Hypothèses'!$B$31-Moteur!AL20 -> 84240
A33: =Moteur!A21 -> 18 | B33: =Moteur!B21 -> 11592.183 | C33: ='Tableau dAMT financier'!G33 -> 15748.274 | D33: =Moteur!C21 -> 3477.6549 | E33: =Moteur!F21 -> 7280 | F33: =Moteur!T21 -> 1679.4493 | G33: =Moteur!P21 -> 12356.98 | H33: =Moteur!AF21 -> 10867.532 | I33: =Moteur!AG21 -> 1489.4475 | J33: =Moteur!AI21 -> -512.02487 | K33: =Moteur!S102 -> 154379.14 | L33: =Moteur!S107 -> 220151.41 | M33: ='Hypothèses'!$B$31-Moteur!AL21 -> 76960
A34: =Moteur!A22 -> 19 | B34: =Moteur!B22 -> 11766.066 | C34: ='Tableau dAMT financier'!G34 -> 15748.274 | D34: =Moteur!C22 -> 3529.8197 | E34: =Moteur!F22 -> 7280 | F34: =Moteur!T22 -> 2189.5825 | G34: =Moteur!P22 -> 12356.98 | H34: =Moteur!AF22 -> 11098.202 | I34: =Moteur!AG22 -> 1258.7778 | J34: =Moteur!AI22 -> -521.10419 | K34: =Moteur!T102 -> 166209.36 | L34: =Moteur!T107 -> 237388.6 | M34: ='Hypothèses'!$B$31-Moteur!AL22 -> 69680
A35: =Moteur!A23 -> 20 | B35: =Moteur!B23 -> 11942.557 | C35: ='Tableau dAMT financier'!G35 -> 15748.274 | D35: =Moteur!C23 -> 3582.767 | E35: =Moteur!F23 -> 7280 | F35: =Moteur!T23 -> 2714.5548 | G35: =Moteur!P23 -> 12356.98 | H35: =Moteur!AF23 -> 11335.582 | I35: =Moteur!AG23 -> 1021.3976 | J35: =Moteur!AI23 -> -530.59056 | K35: =Moteur!U102 -> 178648.3 | L35: =Moteur!U107 -> 255444.85 | M35: ='Hypothèses'!$B$31-Moteur!AL23 -> 62400
A36: =Moteur!A24 -> 21 | B36: =Moteur!B24 -> 12121.695 | C36: ='Tableau dAMT financier'!G36 -> 15748.274 | D36: =Moteur!C24 -> 3636.5085 | E36: =Moteur!F24 -> 7280 | F36: =Moteur!T24 -> 3254.8296 | G36: =Moteur!P24 -> 12356.98 | H36: =Moteur!AF24 -> 11579.883 | I36: =Moteur!AG24 -> 777.09733 | J36: =Moteur!AI24 -> -540.49918 | K36: =Moteur!V102 -> 191709.43 | L36: =Moteur!V107 -> 274337.85 | M36: ='Hypothèses'!$B$31-Moteur!AL24 -> 55120
A37: =Moteur!A25 -> 22 | B37: =Moteur!B25 -> 12303.52 | C37: ='Tableau dAMT financier'!G37 -> 15748.274 | D37: =Moteur!C25 -> 3691.0561 | E37: =Moteur!F25 -> 7280 | F37: =Moteur!T25 -> 3810.8854 | G37: =Moteur!P25 -> 12356.98 | H37: =Moteur!AF25 -> 11831.319 | I37: =Moteur!AG25 -> 525.66063 | J37: =Moteur!AI25 -> -550.84576 | K37: =Moteur!W102 -> 205011.59 | L37: =Moteur!W107 -> 293299.22 | M37: ='Hypothèses'!$B$31-Moteur!AL25 -> 47840
A38: =Moteur!A26 -> 23 | B38: =Moteur!B26 -> 12488.073 | C38: ='Tableau dAMT financier'!G38 -> 15748.274 | D38: =Moteur!C26 -> 3746.422 | E38: =Moteur!F26 -> 7280 | F38: =Moteur!T26 -> 4383.2159 | G38: =Moteur!P26 -> 12356.98 | H38: =Moteur!AF26 -> 12090.116 | I38: =Moteur!AG26 -> 266.86414 | J38: =Moteur!AI26 -> -561.64655 | K38: =Moteur!X102 -> 219466.27 | L38: =Moteur!X107 -> 314138.87 | M38: ='Hypothèses'!$B$31-Moteur!AL26 -> 40560
A39: =Moteur!A27 -> 24 | B39: =Moteur!B27 -> 12675.394 | C39: ='Tableau dAMT financier'!G39 -> 15748.274 | D39: =Moteur!C27 -> 3802.6183 | E39: =Moteur!F27 -> 7280 | F39: =Moteur!T27 -> 4972.3313 | G39: =Moteur!P27 -> 12356.98 | H39: =Moteur!AF27 -> 12356.503 | I39: =Moteur!AG27 -> 0.47724157 | J39: =Moteur!AI27 -> -572.9184 | K39: =Moteur!Y102 -> 234604.32 | L39: =Moteur!Y107 -> 335903.08 | M39: ='Hypothèses'!$B$31-Moteur!AL27 -> 33280
A40: =Moteur!A28 -> 25 | B40: =Moteur!B28 -> 12865.525 | C40: ='Tableau dAMT financier'!G40 -> 15748.274 | D40: =Moteur!C28 -> 3859.6576 | E40: =Moteur!F28 -> 7280 | F40: =Moteur!T28 -> 5578.7579 | G40: =Moteur!P28 -> 12356.98 | H40: =Moteur!AF28 -> 12630.718 | I40: =Moteur!AG28 -> -273.73816 | J40: =Moteur!AI28 -> -584.67871 | K40: =Moteur!Z102 -> 250441.1 | L40: =Moteur!Z107 -> 358612.07 | M40: ='Hypothèses'!$B$31-Moteur!AL28 -> 26000
A41: TOTAL | B41: =SUM(B16:B40) -> 270567.21 | C41: =SUM(C16:C40) -> 393706.85 | D41: =SUM(D16:D40) -> 81170.164 | E41: =SUM(E16:E40) -> 182000 | I41: =SUM(I16:I40) -> 55536.575
A43: ━ Ligne dorée = horizon 15 ans • ━ Ligne bleue = fin de crédit (20 ans)
A44: Le TRI mesure la rentabilité annualisée si revente à la date indiquée, après impôt PV. L'effort d'épargne est le reste à charge mensuel réel après loyers et économie fiscale.
A46: BILAN GLOBAL DE L'OPÉRATION
A73: COMMENT LIRE CETTE SIMULATION
A74: ▸ Le dispositif Jeanbrun déduit un amortissement de vos revenus fonciers, créant un déficit qui réduit votre impôt chaque année.
A75: ▸ L'effort d'épargne mensuel = reste à charge réel après loyers et économie fiscale.
A76: ▸ Le « Gain fiscal total » se décompose en deux parties qui s'additionnent :
A77: – « dont déficit naturel » : l'économie liée aux intérêts d'emprunt, acquise même sans le Jeanbrun.
A78: – « dont Jeanbrun » : l'économie supplémentaire apportée par l'amortissement du dispositif.
A79: ▸ Le « Capital net à la revente » = prix de vente – CRD – impôt PV. Le « Bilan net total » y ajoute la trésorerie cumulée sur la détention.
A80: ▸ L'exonération totale d'IR sur la PV intervient à 22 ans de détention ; celle des PS à 30 ans.
A82: Ce document est une simulation personnalisée et non contractuelle.
... A243: Données graphiques
A244: Année | B244: 1 | C244: 2 | D244: 3 | E244: 4 | F244: 5 | G244: 6 | H244: 7 | I244: 8 | J244: 9 | K244: 10 | L244: 11 | M244: 12 | N244: 13 | O244: 14 | P244: 15 | Q244: 16 | R244: 17 | S244: 18 | T244: 19 | U244: 20 | V244: 21 | W244: 22 | X244: 23 | Y244: 24 | Z244: 25
A245: Enrichissement 0% | B245: =Moteur!B102 -> 13820.615 | C245: =Moteur!C102 -> 20663.045 | D245: =Moteur!D102 -> 26887.643 | E245: =Moteur!E102 -> 31560.888 | F245: =Moteur!F102 -> 36478.998 | G245: =Moteur!G102 -> 50403.338 | H245: =Moteur!H102 -> 58471.426 | I245: =Moteur!I102 -> 66809.825 | ... Z245: =Moteur!Z102 -> 250441.1
A246: Enrichissement 1,5%/an | B246: =Moteur!B107 -> 17720.615 | C246: =Moteur!C107 -> 27465.048 | D246: =Moteur!D107 -> 34464.772 | E246: =Moteur!E107 -> 41739.873 | F246: =Moteur!F107 -> 49298.868 | G246: =Moteur!G107 -> 71403.455 | H246: =Moteur!H107 -> 80020.536 | I246: =Moteur!I107 -> 89280.21 | ... Z246: =Moteur!Z107 -> 358612.07
B247: =Moteur!B146 -> 13820.615 | C247: =Moteur!C146 -> 20663.045 | D247: =Moteur!D146 -> 27734.723 | E247: =Moteur!E146 -> 35043.328 | F247: =Moteur!F146 -> 42596.798 | G247: =Moteur!G146 -> 50403.338 | H247: =Moteur!H146 -> 58471.426 | I247: =Moteur!I146 -> 66809.825 | ... Z247: =Moteur!Z146 -> 260000
A250: Bilan net avec JB 0% | B250: =Moteur!B162 -> 3176.5914 | C250: =Moteur!C162 -> 4360.6508 | D250: =Moteur!D162 -> 4925.2453 | E250: =Moteur!E162 -> 3935.5585 | F250: =Moteur!F162 -> 3186.4492 | G250: =Moteur!G162 -> 11437.858 | H250: =Moteur!H162 -> 13825.812 | I250: =Moteur!I162 -> 16475.316 | ... Z250: =Moteur!Z162 -> 95379.824
A251: Bilan net avec JB 1,5%/an | B251: =Moteur!B163 -> 7076.5914 | C251: =Moteur!C163 -> 11162.654 | D251: =Moteur!D163 -> 12502.374 | E251: =Moteur!E163 -> 14114.544 | F251: =Moteur!F163 -> 16006.32 | G251: =Moteur!G163 -> 32437.975 | H251: =Moteur!H163 -> 35374.923 | I251: =Moteur!I163 -> 38945.701 | ... Z251: =Moteur!Z163 -> 203550.79
N252: =Moteur!N164 -> -11431.863 | O252: =Moteur!O164 -> -10311.985 | P252: =Moteur!P164 -> -8942.7749 | Q252: =Moteur!Q164 -> -7317.0429 | R252: =Moteur!R164 -> -5427.3748 | S252: =Moteur!S164 -> -3266.1259 | T252: =Moteur!T164 -> -825.41363 | U252: =Moteur!U164 -> 1902.8908 | ... Z252: =Moteur!Z164 -> 20161.032

Sheet Revente
A1: SIMULATION DE REVENTE — DISPOSITIF JEANBRUN
A2: Calcul pédagogique de la plus-value et de votre enrichissement net à la revente
B4: 🔹 REVENTE À 9 ANS | E4: 🔸 REVENTE À 15 ANS | H4: ⭐ REVENTE À 25 ANS
B5: PRIX DE VENTE | E5: PRIX DE VENTE | H5: PRIX DE VENTE
B6: Prix de vente (0% revalo.) | C6: ='Hypothèses'!$B$4 -> 260000 | E6: Prix de vente (0% revalo.) | F6: ='Hypothèses'!$B$4 -> 260000 | H6: Prix de vente (0% revalo.) | I6: ='Hypothèses'!$B$4 -> 260000
B7: Prix de vente (1,5%/an revalo.) | C7: ='Hypothèses'!$B$4*1.015^9 -> 297281.39 | E7: Prix de vente (1,5%/an revalo.) | F7: ='Hypothèses'!$B$4*1.015^15 -> 325060.34 | H7: Prix de vente (1,5%/an revalo.) | I7: ='Hypothèses'!$B$4*1.015^25 -> 377245.79
B9: CALCUL DE LA PLUS-VALUE | E9: CALCUL DE LA PLUS-VALUE | H9: CALCUL DE LA PLUS-VALUE
B10: Prix d'acquisition | C10: ='Hypothèses'!$B$4 -> 260000 | E10: Prix d'acquisition | F10: ='Hypothèses'!$B$4 -> 260000 | H10: Prix d'acquisition | I10: ='Hypothèses'!$B$4 -> 260000
B11: + Forfait frais d'acquisition (7,5%) | C11: =MAX('Hypothèses'!$B$4*'Hypothèses'!$B$5,'Hypothèses'!$B$4*'Hypothèses'!$B$43) -> 19500 | E11: + Forfait frais d'acquisition (7,5%) | F11: =MAX('Hypothèses'!$B$4*'Hypothèses'!$B$5,'Hypothèses'!$B$4*'Hypothèses'!$B$43) -> 19500 | H11: + Forfait frais d'acquisition (7,5%) | I11: =MAX('Hypothèses'!$B$4*'Hypothèses'!$B$5,'Hypothèses'!$B$4*'Hypothèses'!$B$43) -> 19500
B12: + Forfait travaux 15% (si > 5 ans) | C12: ='Hypothèses'!$B$4*'Hypothèses'!$B$44 -> 39000 | E12: + Forfait travaux 15% (si > 5 ans) | F12: ='Hypothèses'!$B$4*'Hypothèses'!$B$44 -> 39000 | H12: + Forfait travaux 15% (si > 5 ans) | I12: ='Hypothèses'!$B$4*'Hypothèses'!$B$44 -> 39000
B13: – Amortissements réintégrés | C13: =Moteur!AL12 -> 65520 | E13: – Amortissements réintégrés | F13: =Moteur!AL18 -> 109200 | H13: – Amortissements réintégrés | I13: =Moteur!AL28 -> 182000
B14: = Prix de revient corrigé | C14: ='Hypothèses'!$B$4+MAX('Hypothèses'!$B$4*'Hypothèses'!$B$5,'Hypothèses'!$B$4*'Hypothèses'!$B$43)+'Hypothèses'!$B$4*'Hypothèses'!$B$44-Moteur!AL12 -> 252980 | E14: = Prix de revient corrigé | F14: ='Hypothèses'!$B$4+MAX('Hypothèses'!$B$4*'Hypothèses'!$B$5,'Hypothèses'!$B$4*'Hypothèses'!$B$43)+'Hypothèses'!$B$4*'Hypothèses'!$B$44-Moteur!AL18 -> 209300 | H14: = Prix de revient corrigé | I14: ='Hypothèses'!$B$4+MAX('Hypothèses'!$B$4*'Hypothèses'!$B$5,'Hypothèses'!$B$4*'Hypothèses'!$B$43)+'Hypothèses'!$B$4*'Hypothèses'!$B$44-Moteur!AL28 -> 136500
B16: ➜ PV brute (prix vente 0% – prix revient) | C16: =Moteur!J98 -> 7020 | E16: ➜ PV brute (prix vente 0% – prix revient) | F16: =Moteur!P98 -> 50700 | H16: ➜ PV brute (prix vente 0% – prix revient) | I16: =Moteur!Z98 -> 123500
B17: ➜ PV brute (prix vente 1,5%/an – prix revient) | C17: =Moteur!J103 -> 44301.394 | E17: ➜ PV brute (prix vente 1,5%/an – prix revient) | F17: =Moteur!P103 -> 115760.34 | H17: ➜ PV brute (prix vente 1,5%/an – prix revient) | I17: =Moteur!Z103 -> 240745.79
B19: ABATTEMENTS POUR DURÉE DE DÉTENTION | E19: ABATTEMENTS POUR DURÉE DE DÉTENTION | H19: ABATTEMENTS POUR DURÉE DE DÉTENTION
B20: Abattement IR (%) | C20: =Moteur!AO12 -> 0.24 | E20: Abattement IR (%) | F20: =Moteur!AO18 -> 0.6 | H20: Abattement IR (%) | I20: =Moteur!AO28 -> 1
B21: PV imposable IR (0%) | C21: =Moteur!J99 -> 5335.2 | E21: PV imposable IR (0%) | F21: =Moteur!P99 -> 20280 | H21: PV imposable IR (0%) | I21: =Moteur!Z99 -> 0
B22: PV imposable IR (1,5%) | C22: =Moteur!J104 -> 33669.059 | E22: PV imposable IR (1,5%) | F22: =Moteur!P104 -> 46304.135 | H22: PV imposable IR (1,5%) | I22: =Moteur!Z104 -> 0
B23: Abattement PS (%) | C23: =Moteur!AQ12 -> 0.066 | E23: Abattement PS (%) | F23: =Moteur!AQ18 -> 0.165 | H23: Abattement PS (%) | I23: =Moteur!AQ28 -> 0.55
B24: PV imposable PS (0%) | C24: =Moteur!J100 -> 6556.68 | E24: PV imposable PS (0%) | F24: =Moteur!P100 -> 42334.5 | H24: PV imposable PS (0%) | I24: =Moteur!Z100 -> 55575
B25: PV imposable PS (1,5%) | C25: =Moteur!J105 -> 41377.502 | E25: PV imposable PS (1,5%) | F25: =Moteur!P105 -> 96659.882 | H25: PV imposable PS (1,5%) | I25: =Moteur!Z105 -> 108335.61
B27: IMPÔT SUR LA PLUS-VALUE | E27: IMPÔT SUR LA PLUS-VALUE | H27: IMPÔT SUR LA PLUS-VALUE
B28: IR (19%) — scénario 0% | C28: =Moteur!J99*'Hypothèses'!$B$45 -> 1013.688 | E28: IR (19%) — scénario 0% | F28: =Moteur!P99*'Hypothèses'!$B$45 -> 3853.2 | H28: IR (19%) — scénario 0% | I28: =Moteur!Z99*'Hypothèses'!$B$45 -> 0
B29: IR (19%) — scénario 1,5% | C29: =Moteur!J104*'Hypothèses'!$B$45 -> 6397.1212 | E29: IR (19%) — scénario 1,5% | F29: =Moteur!P104*'Hypothèses'!$B$45 -> 8797.7856 | H29: IR (19%) — scénario 1,5% | I29: =Moteur!Z104*'Hypothèses'!$B$45 -> 0
B30: PS (17,2%) — scénario 0% | C30: =Moteur!J100*'Hypothèses'!$B$46 -> 1127.749 | E30: PS (17,2%) — scénario 0% | F30: =Moteur!P100*'Hypothèses'!$B$46 -> 7281.534 | H30: PS (17,2%) — scénario 0% | I30: =Moteur!Z100*'Hypothèses'!$B$46 -> 9558.9
B31: PS (17,2%) — scénario 1,5% | C31: =Moteur!J105*'Hypothèses'!$B$46 -> 7116.9303 | E31: PS (17,2%) — scénario 1,5% | F31: =Moteur!P105*'Hypothèses'!$B$46 -> 16625.5 | H31: PS (17,2%) — scénario 1,5% | I31: =Moteur!Z105*'Hypothèses'!$B$46 -> 18633.724
B32: Surtaxe éventuelle (0%) | C32: =IF(Moteur!J99<=50000,0,IF(Moteur!J99<=60000,Moteur!J99*0.02-(60000-Moteur!J99)/20,IF(Moteur!J99<=100000,Moteur!J99*0.02,IF(Moteur!J99<=110000,Moteur!J99*0.03-(110000-Moteur!J99)/10,IF(Moteur!J99<=150000,Moteur!J99*0.03,IF(Moteur!J99<=160000,Moteur!J99*0.04-(160000-Moteur!J99)*3/20,IF(Moteur!J99<=200000,Moteur!J99*0.04,IF(Moteur!J99<=210000,Moteur!J99*0.05-(210000-Moteur!J99)/5,IF(Moteur!J99<=250000,Moteur!J99*0.05,IF(Moteur!J99<=260000,Moteur!J99*0.06-(260000-Moteur!J99)/4,Moteur!J99*0.06)))))))))) -> 0 | E32: Surtaxe éventuelle (0%) | F32: =IF(Moteur!P99<=50000,0,IF(Moteur!P99<=60000,Moteur!P99*0.02-(60000-Moteur!P99)/20,IF(Moteur!P99<=100000,Moteur!P99*0.02,IF(Moteur!P99<=110000,Moteur!P99*0.03-(110000-Moteur!P99)/10,IF(Moteur!P99<=150000,Moteur!P99*0.03,IF(Moteur!P99<=160000,Moteur!P99*0.04-(160000-Moteur!P99)*3/20,IF(Moteur!P99<=200000,Moteur!P99*0.04,IF(Moteur!P99<=210000,Moteur!P99*0.05-(210000-Moteur!P99)/5,IF(Moteur!P99<=250000,Moteur!P99*0.05,IF(Moteur!P99<=260000,Moteur!P99*0.06-(260000-Moteur!P99)/4,Moteur!P99*0.06)))))))))) -> 0 | H32: Surtaxe éventuelle (0%) | I32: =IF(Moteur!Z99<=50000,0,IF(Moteur!Z99<=60000,Moteur!Z99*0.02-(60000-Moteur!Z99)/20,IF(Moteur!Z99<=100000,Moteur!Z99*0.02,IF(Moteur!Z99<=110000,Moteur!Z99*0.03-(110000-Moteur!Z99)/10,IF(Moteur!Z99<=150000,Moteur!Z99*0.03,IF(Moteur!Z99<=160000,Moteur!Z99*0.04-(160000-Moteur!Z99)*3/20,IF(Moteur!Z99<=200000,Moteur!Z99*0.04,IF(Moteur!Z99<=210000,Moteur!Z99*0.05-(210000-Moteur!Z99)/5,IF(Moteur!Z99<=250000,Moteur!Z99*0.05,IF(Moteur!Z99<=260000,Moteur!Z99*0.06-(260000-Moteur!Z99)/4,Moteur!Z99*0.06)))))))))) -> 0
B33: Surtaxe éventuelle (1,5%) | C33: =IF(Moteur!J104<=50000,0,IF(Moteur!J104<=60000,Moteur!J104*0.02-(60000-Moteur!J104)/20,IF(Moteur!J104<=100000,Moteur!J104*0.02,IF(Moteur!J104<=110000,Moteur!J104*0.03-(110000-Moteur!J104)/10,IF(Moteur!J104<=150000,Moteur!J104*0.03,IF(Moteur!J104<=160000,Moteur!J104*0.04-(160000-Moteur!J104)*3/20,IF(Moteur!J104<=200000,Moteur!J104*0.04,IF(Moteur!J104<=210000,Moteur!J104*0.05-(210000-Moteur!J104)/5,IF(Moteur!J104<=250000,Moteur!J104*0.05,IF(Moteur!J104<=260000,Moteur!J104*0.06-(260000-Moteur!J104)/4,Moteur!J104*0.06)))))))))) -> 0 | E33: Surtaxe éventuelle (1,5%) | F33: =IF(Moteur!P104<=50000,0,IF(Moteur!P104<=60000,Moteur!P104*0.02-(60000-Moteur!P104)/20,IF(Moteur!P104<=100000,Moteur!P104*0.02,IF(Moteur!P104<=110000,Moteur!P104*0.03-(110000-Moteur!P104)/10,IF(Moteur!P104<=150000,Moteur!P104*0.03,IF(Moteur!P104<=160000,Moteur!P104*0.04-(160000-Moteur!P104)*3/20,IF(Moteur!P104<=200000,Moteur!P104*0.04,IF(Moteur!P104<=210000,Moteur!P104*0.05-(210000-Moteur!P104)/5,IF(Moteur!P104<=250000,Moteur!P104*0.05,IF(Moteur!P104<=260000,Moteur!P104*0.06-(260000-Moteur!P104)/4,Moteur!P104*0.06)))))))))) -> 0 | H33: Surtaxe éventuelle (1,5%) | I33: =IF(Moteur!Z104<=50000,0,IF(Moteur!Z104<=60000,Moteur!Z104*0.02-(60000-Moteur!Z104)/20,IF(Moteur!Z104<=100000,Moteur!Z104*0.02,IF(Moteur!Z104<=110000,Moteur!Z104*0.03-(110000-Moteur!Z104)/10,IF(Moteur!Z104<=150000,Moteur!Z104*0.03,IF(Moteur!Z104<=160000,Moteur!Z104*0.04-(160000-Moteur!Z104)*3/20,IF(Moteur!Z104<=200000,Moteur!Z104*0.04,IF(Moteur!Z104<=210000,Moteur!Z104*0.05-(210000-Moteur!Z104)/5,IF(Moteur!Z104<=250000,Moteur!Z104*0.05,IF(Moteur!Z104<=260000,Moteur!Z104*0.06-(260000-Moteur!Z104)/4,Moteur!Z104*0.06)))))))))) -> 0
B34: = TOTAL IMPÔT PV (0%) | C34: =Moteur!J101 -> 2141.437 | E34: = TOTAL IMPÔT PV (0%) | F34: =Moteur!P101 -> 11134.734 | H34: = TOTAL IMPÔT PV (0%) | I34: =Moteur!Z101 -> 9558.9
B35: = TOTAL IMPÔT PV (1,5%) | C35: =Moteur!J106 -> 13514.052 | E35: = TOTAL IMPÔT PV (1,5%) | F35: =Moteur!P106 -> 25423.285 | H35: = TOTAL IMPÔT PV (1,5%) | I35: =Moteur!Z106 -> 18633.724
B37: CAPITAL RESTANT DÛ | E37: CAPITAL RESTANT DÛ | H37: CAPITAL RESTANT DÛ
B38: CRD à la date de revente | C38: =Moteur!G12 -> 184572.41 | E38: CRD à la date de revente | F38: =Moteur!G18 -> 126452.39 | H38: CRD à la date de revente | I38: =Moteur!G28 -> 2.8521754e-09
B40: CAPITAL CONSTITUÉ NET | E40: CAPITAL CONSTITUÉ NET | H40: CAPITAL CONSTITUÉ NET
B41: = Prix vente – CRD – Impôt PV (0%) | C41: =Moteur!J102 -> 73286.154 | E41: = Prix vente – CRD – Impôt PV (0%) | F41: =Moteur!P102 -> 122412.87 | H41: = Prix vente – CRD – Impôt PV (0%) | I41: =Moteur!Z102 -> 250441.1
B42: = Prix vente – CRD – Impôt PV (1,5%/an) | C42: =Moteur!J107 -> 99194.933 | E42: = Prix vente – CRD – Impôt PV (1,5%/an) | F42: =Moteur!P107 -> 173184.66 | H42: = Prix vente – CRD – Impôt PV (1,5%/an) | I42: =Moteur!Z107 -> 358612.07
A45: 💡 COMPRENDRE VOTRE ENRICHISSEMENT
A46: ▸ Le capital constitué net = ce qui vous reste en poche après avoir soldé votre crédit et payé l'impôt sur la plus-value.
A47: ▸ Plus vous détenez longtemps, plus les abattements pour durée de détention réduisent l'impôt PV : exonération totale d'IR à 22 ans, de PS à 30 ans.
A48: ▸ L'amortissement Jeanbrun est réintégré dans la plus-value à la revente, mais l'économie d'impôt réalisée chaque année (déficit foncier) vous a déjà profité.
A49: ▸ Le scénario 0% est conservateur (pas de hausse des prix). Le scénario 1,5%/an reflète l'évolution historique moyenne du marché immobilier français.
A50: ▸ À 25 ans, le crédit est soldé (CRD = 0) : votre capital constitué net = valeur du bien – impôt PV uniquement.
A52: Ce document est une simulation personnalisée et non contractuelle.

Sheet Moteur
A1: SIMULATION
AV2: CSG DÉDUCTIBLE
A3: Année | B3: Loyers annuels | C3: Charges exploit. | D3: Intérêts | E3: Assurance | F3: Amort. Jeanbrun | G3: CRD fin année | H3: Valeur bien | I3: RF autres | J3: Revenu total avant | K3: Quotient avant | L3: TMI avant | M3: Taux moy avant | N3: IR avant | O3: PS avant | P3: Total avant | Q3: RF bruts globaux | R3: Charges financières | S3: Charges non-fin. | T3: RF net global | U3: Déduc. RG | V3: Déf. report. généré | W3: Stock déf. report. | X3: Déf. imputé année N | Y3: RF net taxable | Z3: Revenu total après | AA3: Quotient après | AB3: TMI après | AC3: Taux moy après | AD3: IR après | AE3: PS après | AF3: Total après | AG3: Économie fiscale | AH3: Enrichis. patrimoine net PV | AI3: Effort d'epargne MENSUEL (hors apport) | AJ3: Effort d'épargne moyen | AK3: Cash Flow cumulé (avec apport) | AL3: Amt. cumulé | AM3: Stock report amt | AN3: PV brute si revente | AO3: Abatt. IR PV (%) | AP3: PV impos. IR | AQ3: Abatt. PS PV (%) | AR3: PV impos. PS | AS3: Impôt PV (IR+PS+surtaxe) | AT3: Déf. périmé (>10 ans) | AU3: TRI investisseur (si revente) | AV3: CSG déd. avant (N) | AW3: CSG déd. après (N)
A4: 1 | B4: ='Hypothèses'!$B$26 -> 9000 | C4: =B4*'Hypothèses'!$B$28 -> 2700 | D4: ='Tableau dAMT financier'!E16 -> 8242.859 | E4: ='Tableau dAMT financier'!F16 -> 884.8 | F4: =MIN('Hypothèses'!$B$34,MAX(0,'Hypothèses'!$B$31)) -> 7280 | G4: ='Tableau dAMT financier'!H16 -> 246179.38 | H4: ='Hypothèses'!B4 -> 260000 | I4: ='Hypothèses'!$B$38 -> 5000 | J4: ='Hypothèses'!$B$50+I4 -> 90500 | K4: =J4/'Hypothèses'!$B$39 -> 36200 | L4: =IF(K4<='Barème fiscal'!$B$4,'Barème fiscal'!$C$4,IF(K4<='Barème fiscal'!$B$5,'Barème fiscal'!$C$5,IF(K4<='Barème fiscal'!$B$6,'Barème fiscal'!$C$6,IF(K4<='Barème fiscal'!$B$7,'Barème fiscal'!$C$7,'Barème fiscal'!$C$8)))) -> 0.3 | M4: =IF(J4>0,N4/J4,0) -> 0.12816552 | N4: =MAX(0,IF(J4/2<='Barème fiscal'!$B$4,0,IF(J4/2<='Barème fiscal'!$B$5,J4*'Barème fiscal'!$C$5-'Barème fiscal'!$D$5*2,IF(J4/2<='Barème fiscal'!$B$6,J4*'Barème fiscal'!$C$6-'Barème fiscal'!$D$6*2,IF(J4/2<='Barème fiscal'!$B$7,J4*'Barème fiscal'!$C$7-'Barème fiscal'!$D$7*2,J4*'Barème fiscal'!$C$8-'Barème fiscal'!$D$8*2)))))-MIN(MAX(IF(J4/2<='Barème fiscal'!$B$4,0,IF(J4/2<='Barème fiscal'!$B$5,J4*'Barème fiscal'!$C$5-'Barème fiscal'!$D$5*2,IF(J4/2<='Barème fiscal'!$B$6,J4*'Barème fiscal'!$C$6-'Barème fiscal'!$D$6*2,IF(J4/2<='Barème fiscal'!$B$7,J4*'Barème fiscal'!$C$7-'Barème fiscal'!$D$7*2,J4*'Barème fiscal'!$C$8-'Barème fiscal'!$D$8*2))))-MAX(0,IF(K4<='Barème fiscal'!$B$4,0,IF(K4<='Barème fiscal'!$B$5,J4*'Barème fiscal'!$C$5-'Barème fiscal'!$D$5*'Hypothèses'!$B$39,IF(K4<='Barème fiscal'!$B$6,J4*'Barème fiscal'!$C$6-'Barème fiscal'!$D$6*'Hypothèses'!$B$39,IF(K4<='Barème fiscal'!$B$7,J4*'Barème fiscal'!$C$7-'Barème fiscal'!$D$7*'Hypothèses'!$B$39,J4*'Barème fiscal'!$C$8-'Barème fiscal'!$D$8*'Hypothèses'!$B$39))))),0),MAX('Hypothèses'!$B$39-2,0)*2*'Barème fiscal'!$B$10) -> 11598.98 | O4: =MAX(0,I4)*'Hypothèses'!$B$40 -> 860 | P4: =N4+O4 -> 12458.98 | Q4: =B4+I4 -> 14000 | R4: =D4+E4+'Hypothèses'!$B$21 -> 13127.659 | S4: =C4+F4 -> 9980 | T4: =Q4-R4-S4 -> -9107.659 | U4: =IF(T4>=0,0,IF(Q4>=R4,MAX(T4,-'Barème fiscal'!$B$11),MAX(-S4,-'Barème fiscal'!$B$11))) -> -9107.659 | V4: =IF(T4>=0,0,IF(Q4>=R4,MAX(0,-T4-'Barème fiscal'!$B$11),(R4-Q4)+MAX(0,S4-'Barème fiscal'!$B$11))) -> 0 | W4: =V4 -> 0 | X4: =IF(T4>0,MIN(W4,T4),0) -> 0 | Y4: =MAX(0,T4-X4) -> 0 | Z4: ='Hypothèses'!$B$50+Y4+U4 -> 76392.341 | AA4: =Z4/'Hypothèses'!$B$39 -> 30556.936 | AB4: =IF(AA4<='Barème fiscal'!$B$4,'Barème fiscal'!$C$4,IF(AA4<='Barème fiscal'!$B$5,'Barème fiscal'!$C$5,IF(AA4<='Barème fiscal'!$B$6,'Barème fiscal'!$C$6,IF(AA4<='Barème fiscal'!$B$7,'Barème fiscal'!$C$7,'Barème fiscal'!$C$8)))) -> 0.3 | AC4: =IF(Z4>0,AD4/Z4,0) -> 0.09643221 | AD4: =MAX(0,IF(Z4/2<='Barème fiscal'!$B$4,0,IF(Z4/2<='Barème fiscal'!$B$5,Z4*'Barème fiscal'!$C$5-'Barème fiscal'!$D$5*2,IF(Z4/2<='Barème fiscal'!$B$6,Z4*'Barème fiscal'!$C$6-'Barème fiscal'!$D$6*2,IF(Z4/2<='Barème fiscal'!$B$7,Z4*'Barème fiscal'!$C$7-'Barème fiscal'!$D$7*2,Z4*'Barème fiscal'!$C$8-'Barème fiscal'!$D$8*2)))))-MIN(MAX(IF(Z4/2<='Barème fiscal'!$B$4,0,IF(Z4/2<='Barème fiscal'!$B$5,Z4*'Barème fiscal'!$C$5-'Barème fiscal'!$D$5*2,IF(Z4/2<='Barème fiscal'!$B$6,Z4*'Barème fiscal'!$C$6-'Barème fiscal'!$D$6*2,IF(Z4/2<='Barème fiscal'!$B$7,Z4*'Barème fiscal'!$C$7-'Barème fiscal'!$D$7*2,Z4*'Barème fiscal'!$C$8-'Barème fiscal'!$D$8*2))))-MAX(0,IF(AA4<='Barème fiscal'!$B$4,0,IF(AA4<='Barème fiscal'!$B$5,Z4*'Barème fiscal'!$C$5-'Barème fiscal'!$D$5*'Hypothèses'!$B$39,IF(AA4<='Barème fiscal'!$B$6,Z4*'Barème fiscal'!$C$6-'Barème fiscal'!$D$6*'Hypothèses'!$B$39,IF(AA4<='Barème fiscal'!$B$7,Z4*'Barème fiscal'!$C$7-'Barème fiscal'!$D$7*'Hypothèses'!$B$39,Z4*'Barème fiscal'!$C$8-'Barème fiscal'!$D$8*'Hypothèses'!$B$39))))),0),MAX('Hypothèses'!$B$39-2,0)*2*'Barème fiscal'!$B$10) -> 7366.6823 | AE4: =Y4*'Hypothèses'!$B$40 -> 0 | AF4: =AD4+AE4 -> 7366.6823 | AG4: =P4-AF4 -> 5092.2977 | AH4: =H4-G4-AS4 -> 13820.615 | AI4: =(B4-'Tableau dAMT financier'!G16-C4+AG4)/12 -> -362.99803 | AJ4: =AVERAGE(AI4:AI12) -> -460.60881 | AK4: =-AI4*12-apport -> -10644.024 | AL4: =F4 -> 7280 | AM4: =MAX(0,A4*'Hypothèses'!$B$31*'Hypothèses'!$B$32-AL4) -> 0 | AN4: =H4-('Hypothèses'!$B$4+MAX('Hypothèses'!$B$4*'Hypothèses'!$B$5,'Hypothèses'!$B$4*'Hypothèses'!$B$43)+IF(A4>5,'Hypothèses'!$B$4*'Hypothèses'!$B$44,0)-AL4) -> -12220 | AO4: =IF(A4<=5,0,IF(A4<=21,(A4-5)*0.06,1)) -> 0 | AP4: =MAX(0,AN4*(1-AO4)) -> 0 | AQ4: =IF(A4<=5,0,IF(A4<=21,(A4-5)*0.0165,IF(A4=22,(21-5)*0.0165+0.016,IF(A4<=30,(21-5)*0.0165+0.016+(A4-22)*0.09,1)))) -> 0 | AR4: =MAX(0,AN4*(1-AQ4)) -> 0 | AS4: =IF(AN4<=0,0,AP4*'Hypothèses'!$B$45+AR4*'Hypothèses'!$B$46+IF(AP4<=50000,0,IF(AP4<=60000,AP4*0.02-(60000-AP4)/20,IF(AP4<=100000,AP4*0.02,IF(AP4<=110000,AP4*0.03-(110000-AP4)/10,IF(AP4<=150000,AP4*0.03,IF(AP4<=160000,AP4*0.04-(160000-AP4)*3/20,IF(AP4<=200000,AP4*0.04,IF(AP4<=210000,AP4*0.05-(210000-AP4)/5,IF(AP4<=250000,AP4*0.05,IF(AP4<=260000,AP4*0.06-(260000-AP4)/4,AP4*0.06))))))))))) -> 0 | AT4: 0 | AU4: =IFERROR(IRR(B60:C60),"") -> -0.36902409 | AV4: =MAX(0,I4)*'Barème fiscal'!$B$13 -> 340 | AW4: =Y4*'Barème fiscal'!$B$13 -> 0
A5: 2 | B5: =B4*(1+'Hypothèses'!$B$27) -> 9135 | C5: =B5*'Hypothèses'!$B$28 -> 2740.5 | D5: ='Tableau dAMT financier'!E17 -> 8021.0437 | E5: ='Tableau dAMT financier'!F17 -> 884.8 | F5: =MIN('Hypothèses'!$B$34,MAX(0,'Hypothèses'!$B$31-AL4)) -> 7280 | G5: ='Tableau dAMT financier'!H17 -> 239336.95 | H5: =H4*(1+index) -> 260000 | I5: =I4*(1+index) -> 5000 | J5: ='Hypothèses'!$B$50+I5-AV4 -> 90160 | K5: =J5/'Hypothèses'!$B$39 -> 36064 | L5: =IF(K5<='Barème fiscal'!$B$4,'Barème fiscal'!$C$4,IF(K5<='Barème fiscal'!$B$5,'Barème fiscal'!$C$5,IF(K5<='Barème fiscal'!$B$6,'Barème fiscal'!$C$6,IF(K5<='Barème fiscal'!$B$7,'Barème fiscal'!$C$7,'Barème fiscal'!$C$8)))) -> 0.3 | M5: =IF(J5>0,N5/J5,0) -> 0.12751752 | N5: =MAX(0,IF(J5/2<='Barème fiscal'!$B$4,0,IF(J5/2<='Barème fiscal'!$B$5,J5*'Barème fiscal'!$C$5-'Barème fiscal'!$D$5*2,IF(J5/2<='Barème fiscal'!$B$6,J5*'Barème fiscal'!$C$6-'Barème fiscal'!$D$6*2,IF(J5/2<='Barème fiscal'!$B$7,J5*'Barème fiscal'!$C$7-'Barème fiscal'!$D$7*2,J5*'Barème fiscal'!$C$8-'Barème fiscal'!$D$8*2)))))-MIN(MAX(IF(J5/2<='Barème fiscal'!$B$4,0,IF(J5/2<='Barème fiscal'!$B$5,J5*'Barème fiscal'!$C$5-'Barème fiscal'!$D$5*2,IF(J5/2<='Barème fiscal'!$B$6,J5*'Barème fiscal'!$C$6-'Barème fiscal'!$D$6*2,IF(J5/2<='Barème fiscal'!$B$7,J5*'Barème fiscal'!$C$7-'Barème fiscal'!$D$7*2,J5*'Barème fiscal'!$C$8-'Barème fiscal'!$D$8*2))))-MAX(0,IF(K5<='Barème fiscal'!$B$4,0,IF(K5<='Barème fiscal'!$B$5,J5*'Barème fiscal'!$C$5-'Barème fiscal'!$D$5*'Hypothèses'!$B$39,IF(K5<='Barème fiscal'!$B$6,J5*'Barème fiscal'!$C$6-'Barème fiscal'!$D$6*'Hypothèses'!$B$39,IF(K5<='Barème fiscal'!$B$7,J5*'Barème fiscal'!$C$7-'Barème fiscal'!$D$7*'Hypothèses'!$B$39,J5*'Barème fiscal'!$C$8-'Barème fiscal'!$D$8*'Hypothèses'!$B$39))))),0),MAX('Hypothèses'!$B$39-2,0)*2*'Barème fiscal'!$B$10) -> 11496.98 | O5: =MAX(0,I5)*'Hypothèses'!$B$40 -> 860 | P5: =N5+O5 -> 12356.98 | Q5: =B5+I5 -> 14135 | R5: =D5+E5 -> 8905.8437 | S5: =C5+F5 -> 10020.5 | T5: =Q5-R5-S5 -> -4791.3437 | U5: =IF(T5>=0,0,IF(Q5>=R5,MAX(T5,-'Barème fiscal'!$B$11),MAX(-S5,-'Barème fiscal'!$B$11))) -> -4791.3437 | V5: =IF(T5>=0,0,IF(Q5>=R5,MAX(0,-T5-'Barème fiscal'!$B$11),(R5-Q5)+MAX(0,S5-'Barème fiscal'!$B$11))) -> 0 | W5: =W4+V5-X4-AT5 -> 0 | X5: =IF(T5>0,MIN(W5,T5),0) -> 0 | Y5: =MAX(0,T5-X5) -> 0 | Z5: ='Hypothèses'!$B$50+Y5+U5-AW4 -> 80708.656 | AA5: =Z5/'Hypothèses'!$B$39 -> 32283.463 | AB5: =IF(AA5<='Barème fiscal'!$B$4,'Barème fiscal'!$C$4,IF(AA5<='Barème fiscal'!$B$5,'Barème fiscal'!$C$5,IF(AA5<='Barème fiscal'!$B$6,'Barème fiscal'!$C$6,IF(AA5<='Barème fiscal'!$B$7,'Barème fiscal'!$C$7,'Barème fiscal'!$C$8)))) -> 0.3 | AC5: =IF(Z5>0,AD5/Z5,0) -> 0.10731906 | AD5: =MAX(0,IF(Z5/2<='Barème fiscal'!$B$4,0,IF(Z5/2<='Barème fiscal'!$B$5,Z5*'Barème fiscal'!$C$5-'Barème fiscal'!$D$5*2,IF(Z5/2<='Barème fiscal'!$B$6,Z5*'Barème fiscal'!$C$6-'Barème fiscal'!$D$6*2,IF(Z5/2<='Barème fiscal'!$B$7,Z5*'Barème fiscal'!$C$7-'Barème fiscal'!$D$7*2,Z5*'Barème fiscal'!$C$8-'Barème fiscal'!$D$8*2)))))-MIN(MAX(IF(Z5/2<='Barème fiscal'!$B$4,0,IF(Z5/2<='Barème fiscal'!$B$5,Z5*'Barème fiscal'!$C$5-'Barème fiscal'!$D$5*2,IF(Z5/2<='Barème fiscal'!$B$6,Z5*'Barème fiscal'!$C$6-'Barème fiscal'!$D$6*2,IF(Z5/2<='Barème fiscal'!$B$7,Z5*'Barème fiscal'!$C$7-'Barème fiscal'!$D$7*2,Z5*'Barème fiscal'!$C$8-'Barème fiscal'!$D$8*2))))-MAX(0,IF(AA5<='Barème fiscal'!$B$4,0,IF(AA5<='Barème fiscal'!$B$5,Z5*'Barème fiscal'!$C$5-'Barème fiscal'!$D$5*'Hypothèses'!$B$39,IF(AA5<='Barème fiscal'!$B$6,Z5*'Barème fiscal'!$C$6-'Barème fiscal'!$D$6*'Hypothèses'!$B$39,IF(AA5<='Barème fiscal'!$B$7,Z5*'Barème fiscal'!$C$7-'Barème fiscal'!$D$7*'Hypothèses'!$B$39,Z5*'Barème fiscal'!$C$8-'Barème fiscal'!$D$8*'Hypothèses'!$B$39))))),0),MAX('Hypothèses'!$B$39-2,0)*2*'Barème fiscal'!$B$10) -> 8661.5769 | AE5: =Y5*'Hypothèses'!$B$40 -> 0 | AF5: =AD5+AE5 -> 8661.5769 | AG5: =P5-AF5 -> 3695.4031 | AH5: =H5-G5-AS5 -> 20663.045 | AI5: =(B5-'Tableau dAMT financier'!G17-C5+AG5)/12 -> -471.53091 | AK5: =AK4+AI5*12 -> -16302.395 | AL5: =AL4+F5 -> 14560 | AM5: =MAX(0,A5*'Hypothèses'!$B$31*'Hypothèses'!$B$32-AL5) -> 0 | AN5: =H5-('Hypothèses'!$B$4+MAX('Hypothèses'!$B$4*'Hypothèses'!$B$5,'Hypothèses'!$B$4*'Hypothèses'!$B$43)+IF(A5>5,'Hypothèses'!$B$4*'Hypothèses'!$B$44,0)-AL5) -> -4940 | AO5: =IF(A5<=5,0,IF(A5<=21,(A5-5)*0.06,1)) -> 0 | AP5: =MAX(0,AN5*(1-AO5)) -> 0 | AQ5: =IF(A5<=5,0,IF(A5<=21,(A5-5)*0.0165,IF(A5=22,(21-5)*0.0165+0.016,IF(A5<=30,(21-5)*0.0165+0.016+(A5-22)*0.09,1)))) -> 0 | AR5: =MAX(0,AN5*(1-AQ5)) -> 0 | AS5: =IF(AN5<=0,0,AP5*'Hypothèses'!$B$45+AR5*'Hypothèses'!$B$46+IF(AP5<=50000,0,IF(AP5<=60000,AP5*0.02-(60000-AP5)/20,IF(AP5<=100000,AP5*0.02,IF(AP5<=110000,AP5*0.03-(110000-AP5)/10,IF(AP5<=150000,AP5*0.03,IF(AP5<=160000,AP5*0.04-(160000-AP5)*3/20,IF(AP5<=200000,AP5*0.04,IF(AP5<=210000,AP5*0.05-(210000-AP5)/5,IF(AP5<=250000,AP5*0.05,IF(AP5<=260000,AP5*0.06-(260000-AP5)/4,AP5*0.06))))))))))) -> 0 | AT5: 0 | AU5: =IFERROR(IRR(B61:D61),"") -> -0.1345586 | AV5: =MAX(0,I5)*'Barème fiscal'!$B$13 -> 340 | AW5: =Y5*'Barème fiscal'!$B$13 -> 0
A6: 3 | B6: =B5*(1+'Hypothèses'!$B$27) -> 9272.025 | C6: =B6*'Hypothèses'!$B$28 -> 2781.6075 | D6: ='Tableau dAMT financier'!E18 -> 7791.7968 | E6: ='Tableau dAMT financier'!F18 -> 884.8 | F6: =MIN('Hypothèses'!$B$34,MAX(0,'Hypothèses'!$B$31-AL5)) -> 7280 | G6: ='Tableau dAMT financier'!H18 -> 232265.28 | H6: =H5*(1+index) -> 260000 | I6: =I5*(1+index) -> 5000 | J6: ='Hypothèses'!$B$50+I6-AV5 -> 90160 | K6: =J6/'Hypothèses'!$B$39 -> 36064 | L6: =IF(K6<='Barème fiscal'!$B$4,'Barème fiscal'!$C$4,IF(K6<='Barème fiscal'!$B$5,'Barème fiscal'!$C$5,IF(K6<='Barème fiscal'!$B$6,'Barème fiscal'!$C$6,IF(K6<='Barème fiscal'!$B$7,'Barème fiscal'!$C$7,'Barème fiscal'!$C$8)))) -> 0.3 | M6: =IF(J6>0,N6/J6,0) -> 0.12751752 | N6: =MAX(0,IF(J6/2<='Barème fiscal'!$B$4,0,IF(J6/2<='Barème fiscal'!$B$5,J6*'Barème fiscal'!$C$5-'Barème fiscal'!$D$5*2,IF(J6/2<='Barème fiscal'!$B$6,J6*'Barème fiscal'!$C$6-'Barème fiscal'!$D$6*2,IF(J6/2<='Barème fiscal'!$B$7,J6*'Barème fiscal'!$C$7-'Barème fiscal'!$D$7*2,J6*'Barème fiscal'!$C$8-'Barème fiscal'!$D$8*2)))))-MIN(MAX(IF(J6/2<='Barème fiscal'!$B$4,0,IF(J6/2<='Barème fiscal'!$B$5,J6*'Barème fiscal'!$C$5-'Barème fiscal'!$D$5*2,IF(J6/2<='Barème fiscal'!$B$6,J6*'Barème fiscal'!$C$6-'Barème fiscal'!$D$6*2,IF(J6/2<='Barème fiscal'!$B$7,J6*'Barème fiscal'!$C$7-'Barème fiscal'!$D$7*2,J6*'Barème fiscal'!$C$8-'Barème fiscal'!$D$8*2))))-MAX(0,IF(K6<='Barème fiscal'!$B$4,0,IF(K6<='Barème fiscal'!$B$5,J6*'Barème fiscal'!$C$5-'Barème fiscal'!$D$5*'Hypothèses'!$B$39,IF(K6<='Barème fiscal'!$B$6,J6*'Barème fiscal'!$C$6-'Barème fiscal'!$D$6*'Hypothèses'!$B$39,IF(K6<='Barème fiscal'!$B$7,J6*'Barème fiscal'!$C$7-'Barème fiscal'!$D$7*'Hypothèses'!$B$39,J6*'Barème fiscal'!$C$8-'Barème fiscal'!$D$8*'Hypothèses'!$B$39))))),0),MAX('Hypothèses'!$B$39-2,0)*2*'Barème fiscal'!$B$10) -> 11496.98 | O6: =MAX(0,I6)*'Hypothèses'!$B$40 -> 860 | P6: =N6+O6 -> 12356.98 | Q6: =B6+I6 -> 14272.025 | R6: =D6+E6 -> 8676.5968 | S6: =C6+F6 -> 10061.608 | T6: =Q6-R6-S6 -> -4466.1793 | U6: =IF(T6>=0,0,IF(Q6>=R6,MAX(T6,-'Barème fiscal'!$B$11),MAX(-S6,-'Barème fiscal'!$B$11))) -> -4466.1793 | V6: =IF(T6>=0,0,IF(Q6>=R6,MAX(0,-T6-'Barème fiscal'!$B$11),(R6-Q6)+MAX(0,S6-'Barème fiscal'!$B$11))) -> 0 | W6: =W5+V6-X5-AT6 -> 0 | X6: =IF(T6>0,MIN(W6,T6),0) -> 0 | Y6: =MAX(0,T6-X6) -> 0 | Z6: ='Hypothèses'!$B$50+Y6+U6-AW5 -> 81033.821 | AA6: =Z6/'Hypothèses'!$B$39 -> 32413.528 | AB6: =IF(AA6<='Barème fiscal'!$B$4,'Barème fiscal'!$C$4,IF(AA6<='Barème fiscal'!$B$5,'Barème fiscal'!$C$5,IF(AA6<='Barème fiscal'!$B$6,'Barème fiscal'!$C$6,IF(AA6<='Barème fiscal'!$B$7,'Barème fiscal'!$C$7,'Barème fiscal'!$C$8)))) -> 0.3 | AC6: =IF(Z6>0,AD6/Z6,0) -> 0.10809223 | AD6: =MAX(0,IF(Z6/2<='Barème fiscal'!$B$4,0,IF(Z6/2<='Barème fiscal'!$B$5,Z6*'Barème fiscal'!$C$5-'Barème fiscal'!$D$5*2,IF(Z6/2<='Barème fiscal'!$B$6,Z6*'Barème fiscal'!$C$6-'Barème fiscal'!$D$6*2,IF(Z6/2<='Barème fiscal'!$B$7,Z6*'Barème fiscal'!$C$7-'Barème fiscal'!$D$7*2,Z6*'Barème fiscal'!$C$8-'Barème fiscal'!$D$8*2)))))-MIN(MAX(IF(Z6/2<='Barème fiscal'!$B$4,0,IF(Z6/2<='Barème fiscal'!$B$5,Z6*'Barème fiscal'!$C$5-'Barème fiscal'!$D$5*2,IF(Z6/2<='Barème fiscal'!$B$6,Z6*'Barème fiscal'!$C$6-'Barème fiscal'!$D$6*2,IF(Z6/2<='Barème fiscal'!$B$7,Z6*'Barème fiscal'!$C$7-'Barème fiscal'!$D$7*2,Z6*'Barème fiscal'!$C$8-'Barème fiscal'!$D$8*2))))-MAX(0,IF(AA6<='Barème fiscal'!$B$4,0,IF(AA6<='Barème fiscal'!$B$5,Z6*'Barème fiscal'!$C$5-'Barème fiscal'!$D$5*'Hypothèses'!$B$39,IF(AA6<='Barème fiscal'!$B$6,Z6*'Barème fiscal'!$C$6-'Barème fiscal'!$D$6*'Hypothèses'!$B$39,IF(AA6<='Barème fiscal'!$B$7,Z6*'Barème fiscal'!$C$7-'Barème fiscal'!$D$7*'Hypothèses'!$B$39,Z6*'Barème fiscal'!$C$8-'Barème fiscal'!$D$8*'Hypothèses'!$B$39))))),0),MAX('Hypothèses'!$B$39-2,0)*2*'Barème fiscal'!$B$10) -> 8759.1262 | AE6: =Y6*'Hypothèses'!$B$40 -> 0 | AF6: =AD6+AE6 -> 8759.1262 | AG6: =P6-AF6 -> 3597.8538 | AH6: =H6-G6-AS6 -> 26887.643 | AI6: =(B6-'Tableau dAMT financier'!G18-C6+AG6)/12 -> -471.6669 | AK6: =AK5+AI6*12 -> -21962.397 | AL6: =AL5+F6 -> 21840 | AM6: =MAX(0,A6*'Hypothèses'!$B$31*'Hypothèses'!$B$32-AL6) -> 0 | AN6: =H6-('Hypothèses'!$B$4+MAX('Hypothèses'!$B$4*'Hypothèses'!$B$5,'Hypothèses'!$B$4*'Hypothèses'!$B$43)+IF(A6>5,'Hypothèses'!$B$4*'Hypothèses'!$B$44,0)-AL6) -> 2340 | AO6: =IF(A6<=5,0,IF(A6<=21,(A6-5)*0.06,1)) -> 0 | AP6: =MAX(0,AN6*(1-AO6)) -> 2340 | AQ6: =IF(A6<=5,0,IF(A6<=21,(A6-5)*0.0165,IF(A6=22,(21-5)*0.0165+0.016,IF(A6<=30,(21-5)*0.0165+0.016+(A6-22)*0.09,1)))) -> 0 | AR6: =MAX(0,AN6*(1-AQ6)) -> 2340 | AS6: =IF(AN6<=0,0,AP6*'Hypothèses'!$B$45+AR6*'Hypothèses'!$B$46+IF(AP6<=50000,0,IF(AP6<=60000,AP6*0.02-(60000-AP6)/20,IF(AP6<=100000,AP6*0.02,IF(AP6<=110000,AP6*0.03-(110000-AP6)/10,IF(AP6<=150000,AP6*0.03,IF(AP6<=160000,AP6*0.04-(160000-AP6)*3/20,IF(AP6<=200000,AP6*0.04,IF(AP6<=210000,AP6*0.05-(210000-AP6)/5,IF(AP6<=250000,AP6*0.05,IF(AP6<=260000,AP6*0.06-(260000-AP6)/4,AP6*0.06))))))))))) -> 847.08 | AT6: 0 | AU6: =IFERROR(IRR(B62:E62),"") -> -0.067490088 | AV6: =MAX(0,I6)*'Barème fiscal'!$B$13 -> 340 | AW6: =Y6*'Barème fiscal'!$B$13 -> 0
A7: 4 | B7: =B6*(1+'Hypothèses'!$B$27) -> 9411.1054 | C7: =B7*'Hypothèses'!$B$28 -> 2823.3316 | D7: ='Tableau dAMT financier'!E19 -> 7554.8692 | E7: ='Tableau dAMT financier'!F19 -> 884.8 | F7: =MIN('Hypothèses'!$B$34,MAX(0,'Hypothèses'!$B$31-AL6)) -> 7280 | G7: ='Tableau dAMT financier'!H19 -> 224956.67 | H7: =H6*(1+index) -> 260000 | I7: =I6*(1+index) -> 5000 | J7: ='Hypothèses'!$B$50+I7-AV6 -> 90160 | K7: =J7/'Hypothèses'!$B$39 -> 36064 | L7: =IF(K7<='Barème fiscal'!$B$4,'Barème fiscal'!$C$4,IF(K7<='Barème fiscal'!$B$5,'Barème fiscal'!$C$5,IF(K7<='Barème fiscal'!$B$6,'Barème fiscal'!$C$6,IF(K7<='Barème fiscal'!$B$7,'Barème fiscal'!$C$7,'Barème fiscal'!$C$8)))) -> 0.3 | M7: =IF(J7>0,N7/J7,0) -> 0.12751752 | N7: =MAX(0,IF(J7/2<='Barème fiscal'!$B$4,0,IF(J7/2<='Barème fiscal'!$B$5,J7*'Barème fiscal'!$C$5-'Barème fiscal'!$D$5*2,IF(J7/2<='Barème fiscal'!$B$6,J7*'Barème fiscal'!$C$6-'Barème fiscal'!$D$6*2,IF(J7/2<='Barème fiscal'!$B$7,J7*'Barème fiscal'!$C$7-'Barème fiscal'!$D$7*2,J7*'Barème fiscal'!$C$8-'Barème fiscal'!$D$8*2)))))-MIN(MAX(IF(J7/2<='Barème fiscal'!$B$4,0,IF(J7/2<='Barème fiscal'!$B$5,J7*'Barème fiscal'!$C$5-'Barème fiscal'!$D$5*2,IF(J7/2<='Barème fiscal'!$B$6,J7*'Barème fiscal'!$C$6-'Barème fiscal'!$D$6*2,IF(J7/2<='Barème fiscal'!$B$7,J7*'Barème fiscal'!$C$7-'Barème fiscal'!$D$7*2,J7*'Barème fiscal'!$C$8-'Barème fiscal'!$D$8*2))))-MAX(0,IF(K7<='Barème fiscal'!$B$4,0,IF(K7<='Barème fiscal'!$B$5,J7*'Barème fiscal'!$C$5-'Barème fiscal'!$D$5*'Hypothèses'!$B$39,IF(K7<='Barème fiscal'!$B$6,J7*'Barème fiscal'!$C$6-'Barème fiscal'!$D$6*'Hypothèses'!$B$39,IF(K7<='Barème fiscal'!$B$7,J7*'Barème fiscal'!$C$7-'Barème fiscal'!$D$7*'Hypothèses'!$B$39,J7*'Barème fiscal'!$C$8-'Barème fiscal'!$D$8*'Hypothèses'!$B$39))))),0),MAX('Hypothèses'!$B$39-2,0)*2*'Barème fiscal'!$B$10) -> 11496.98 | O7: =MAX(0,I7)*'Hypothèses'!$B$40 -> 860 | P7: =N7+O7 -> 12356.98 | Q7: =B7+I7 -> 14411.105 | R7: =D7+E7 -> 8439.6692 | S7: =C7+F7 -> 10103.332 | T7: =Q7-R7-S7 -> -4131.8955 | U7: =IF(T7>=0,0,IF(Q7>=R7,MAX(T7,-'Barème fiscal'!$B$11),MAX(-S7,-'Barème fiscal'!$B$11))) -> -4131.8955 | V7: =IF(T7>=0,0,IF(Q7>=R7,MAX(0,-T7-'Barème fiscal'!$B$11),(R7-Q7)+MAX(0,S7-'Barème fiscal'!$B$11))) -> 0 | W7: =W6+V7-X6-AT7 -> 0 | X7: =IF(T7>0,MIN(W7,T7),0) -> 0 | Y7: =MAX(0,T7-X7) -> 0 | Z7: ='Hypothèses'!$B$50+Y7+U7-AW6 -> 81368.105 | AA7: =Z7/'Hypothèses'!$B$39 -> 32547.242 | AB7: =IF(AA7<='Barème fiscal'!$B$4,'Barème fiscal'!$C$4,IF(AA7<='Barème fiscal'!$B$5,'Barème fiscal'!$C$5,IF(AA7<='Barème fiscal'!$B$6,'Barème fiscal'!$C$6,IF(AA7<='Barème fiscal'!$B$7,'Barème fiscal'!$C$7,'Barème fiscal'!$C$8)))) -> 0.3 | AC7: =IF(Z7>0,AD7/Z7,0) -> 0.10888064 | AD7: =MAX(0,IF(Z7/2<='Barème fiscal'!$B$4,0,IF(Z7/2<='Barème fiscal'!$B$5,Z7*'Barème fiscal'!$C$5-'Barème fiscal'!$D$5*2,IF(Z7/2<='Barème fiscal'!$B$6,Z7*'Barème fiscal'!$C$6-'Barème fiscal'!$D$6*2,IF(Z7/2<='Barème fiscal'!$B$7,Z7*'Barème fiscal'!$C$7-'Barème fiscal'!$D$7*2,Z7*'Barème fiscal'!$C$8-'Barème fiscal'!$D$8*2)))))-MIN(MAX(IF(Z7/2<='Barème fiscal'!$B$4,0,IF(Z7/2<='Barème fiscal'!$B$5,Z7*'Barème fiscal'!$C$5-'Barème fiscal'!$D$5*2,IF(Z7/2<='Barème fiscal'!$B$6,Z7*'Barème fiscal'!$C$6-'Barème fiscal'!$D$6*2,IF(Z7/2<='Barème fiscal'!$B$7,Z7*'Barème fiscal'!$C$7-'Barème fiscal'!$D$7*2,Z7*'Barème fiscal'!$C$8-'Barème fiscal'!$D$8*2))))-MAX(0,IF(AA7<='Barème fiscal'!$B$4,0,IF(AA7<='Barème fiscal'!$B$5,Z7*'Barème fiscal'!$C$5-'Barème fiscal'!$D$5*'Hypothèses'!$B$39,IF(AA7<='Barème fiscal'!$B$6,Z7*'Barème fiscal'!$C$6-'Barème fiscal'!$D$6*'Hypothèses'!$B$39,IF(AA7<='Barème fiscal'!$B$7,Z7*'Barème fiscal'!$C$7-'Barème fiscal'!$D$7*'Hypothèses'!$B$39,Z7*'Barème fiscal'!$C$8-'Barème fiscal'!$D$8*'Hypothèses'!$B$39))))),0),MAX('Hypothèses'!$B$39-2,0)*2*'Barème fiscal'!$B$10) -> 8859.4114 | AE7: =Y7*'Hypothèses'!$B$40 -> 0 | AF7: =AD7+AE7 -> 8859.4114 | AG7: =P7-AF7 -> 3497.5686 | AH7: =H7-G7-AS7 -> 31560.888 | AI7: =(B7-'Tableau dAMT financier'!G19-C7+AG7)/12 -> -471.91097 | AK7: =AK6+AI7*12 -> -27625.329 | AL7: =AL6+F7 -> 29120 | AM7: =MAX(0,A7*'Hypothèses'!$B$31*'Hypothèses'!$B$32-AL7) -> 0 | AN7: =H7-('Hypothèses'!$B$4+MAX('Hypothèses'!$B$4*'Hypothèses'!$B$5,'Hypothèses'!$B$4*'Hypothèses'!$B$43)+IF(A7>5,'Hypothèses'!$B$4*'Hypothèses'!$B$44,0)-AL7) -> 9620 | AO7: =IF(A7<=5,0,IF(A7<=21,(A7-5)*0.06,1)) -> 0 | AP7: =MAX(0,AN7*(1-AO7)) -> 9620 | AQ7: =IF(A7<=5,0,IF(A7<=21,(A7-5)*0.0165,IF(A7=22,(21-5)*0.0165+0.016,IF(A7<=30,(21-5)*0.0165+0.016+(A7-22)*0.09,1)))) -> 0 | AR7: =MAX(0,AN7*(1-AQ7)) -> 9620 | AS7: =IF(AN7<=0,0,AP7*'Hypothèses'!$B$45+AR7*'Hypothèses'!$B$46+IF(AP7<=50000,0,IF(AP7<=60000,AP7*0.02-(60000-AP7)/20,IF(AP7<=100000,AP7*0.02,IF(AP7<=110000,AP7*0.03-(110000-AP7)/10,IF(AP7<=150000,AP7*0.03,IF(AP7<=160000,AP7*0.04-(160000-AP7)*3/20,IF(AP7<=200000,AP7*0.04,IF(AP7<=210000,AP7*0.05-(210000-AP7)/5,IF(AP7<=250000,AP7*0.05,IF(AP7<=260000,AP7*0.06-(260000-AP7)/4,AP7*0.06))))))))))) -> 3482.44 | AT7: 0 | AU7: =IFERROR(IRR(B63:F63),"") -> -0.05681273 | AV7: =MAX(0,I7)*'Barème fiscal'!$B$13 -> 340 | AW7: =Y7*'Barème fiscal'!$B$13 -> 0
A8: 5 | B8: =B7*(1+'Hypothèses'!$B$27) -> 9552.272 | C8: =B8*'Hypothèses'!$B$28 -> 2865.6816 | D8: ='Tableau dAMT financier'!E20 -> 7310.0037 | E8: ='Tableau dAMT financier'!F20 -> 884.8 | F8: =MIN('Hypothèses'!$B$34,MAX(0,'Hypothèses'!$B$31-AL7)) -> 7280 | G8: ='Tableau dAMT financier'!H20 -> 217403.2 | H8: =H7*(1+index) -> 260000 | I8: =I7*(1+index) -> 5000 | J8: ='Hypothèses'!$B$50+I8-AV7 -> 90160 | K8: =J8/'Hypothèses'!$B$39 -> 36064 | L8: =IF(K8<='Barème fiscal'!$B$4,'Barème fiscal'!$C$4,IF(K8<='Barème fiscal'!$B$5,'Barème fiscal'!$C$5,IF(K8<='Barème fiscal'!$B$6,'Barème fiscal'!$C$6,IF(K8<='Barème fiscal'!$B$7,'Barème fiscal'!$C$7,'Barème fiscal'!$C$8)))) -> 0.3 | M8: =IF(J8>0,N8/J8,0) -> 0.12751752 | N8: =MAX(0,IF(J8/2<='Barème fiscal'!$B$4,0,IF(J8/2<='Barème fiscal'!$B$5,J8*'Barème fiscal'!$C$5-'Barème fiscal'!$D$5*2,IF(J8/2<='Barème fiscal'!$B$6,J8*'Barème fiscal'!$C$6-'Barème fiscal'!$D$6*2,IF(J8/2<='Barème fiscal'!$B$7,J8*'Barème fiscal'!$C$7-'Barème fiscal'!$D$7*2,J8*'Barème fiscal'!$C$8-'Barème fiscal'!$D$8*2)))))-MIN(MAX(IF(J8/2<='Barème fiscal'!$B$4,0,IF(J8/2<='Barème fiscal'!$B$5,J8*'Barème fiscal'!$C$5-'Barème fiscal'!$D$5*2,IF(J8/2<='Barème fiscal'!$B$6,J8*'Barème fiscal'!$C$6-'Barème fiscal'!$D$6*2,IF(J8/2<='Barème fiscal'!$B$7,J8*'Barème fiscal'!$C$7-'Barème fiscal'!$D$7*2,J8*'Barème fiscal'!$C$8-'Barème fiscal'!$D$8*2))))-MAX(0,IF(K8<='Barème fiscal'!$B$4,0,IF(K8<='Barème fiscal'!$B$5,J8*'Barème fiscal'!$C$5-'Barème fiscal'!$D$5*'Hypothèses'!$B$39,IF(K8<='Barème fiscal'!$B$6,J8*'Barème fiscal'!$C$6-'Barème fiscal'!$D$6*'Hypothèses'!$B$39,IF(K8<='Barème fiscal'!$B$7,J8*'Barème fiscal'!$C$7-'Barème fiscal'!$D$7*'Hypothèses'!$B$39,J8*'Barème fiscal'!$C$8-'Barème fiscal'!$D$8*'Hypothèses'!$B$39))))),0),MAX('Hypothèses'!$B$39-2,0)*2*'Barème fiscal'!$B$10) -> 11496.98 | O8: =MAX(0,I8)*'Hypothèses'!$B$40 -> 860 | P8: =N8+O8 -> 12356.98 | Q8: =B8+I8 -> 14552.272 | R8: =D8+E8 -> 8194.8037 | S8: =C8+F8 -> 10145.682 | T8: =Q8-R8-S8 -> -3788.2134 | U8: =IF(T8>=0,0,IF(Q8>=R8,MAX(T8,-'Barème fiscal'!$B$11),MAX(-S8,-'Barème fiscal'!$B$11))) -> -3788.2134 | V8: =IF(T8>=0,0,IF(Q8>=R8,MAX(0,-T8-'Barème fiscal'!$B$11),(R8-Q8)+MAX(0,S8-'Barème fiscal'!$B$11))) -> 0 | W8: =W7+V8-X7-AT8 -> 0 | X8: =IF(T8>0,MIN(W8,T8),0) -> 0 | Y8: =MAX(0,T8-X8) -> 0 | Z8: ='Hypothèses'!$B$50+Y8+U8-AW7 -> 81711.787 | AA8: =Z8/'Hypothèses'!$B$39 -> 32684.715 | AB8: =IF(AA8<='Barème fiscal'!$B$4,'Barème fiscal'!$C$4,IF(AA8<='Barème fiscal'!$B$5,'Barème fiscal'!$C$5,IF(AA8<='Barème fiscal'!$B$6,'Barème fiscal'!$C$6,IF(AA8<='Barème fiscal'!$B$7,'Barème fiscal'!$C$7,'Barème fiscal'!$C$8)))) -> 0.3 | AC8: =IF(Z8>0,AD8/Z8,0) -> 0.10968449 | AD8: =MAX(0,IF(Z8/2<='Barème fiscal'!$B$4,0,IF(Z8/2<='Barème fiscal'!$B$5,Z8*'Barème fiscal'!$C$5-'Barème fiscal'!$D$5*2,IF(Z8/2<='Barème fiscal'!$B$6,Z8*'Barème fiscal'!$C$6-'Barème fiscal'!$D$6*2,IF(Z8/2<='Barème fiscal'!$B$7,Z8*'Barème fiscal'!$C$7-'Barème fiscal'!$D$7*2,Z8*'Barème fiscal'!$C$8-'Barème fiscal'!$D$8*2)))))-MIN(MAX(IF(Z8/2<='Barème fiscal'!$B$4,0,IF(Z8/2<='Barème fiscal'!$B$5,Z8*'Barème fiscal'!$C$5-'Barème fiscal'!$D$5*2,IF(Z8/2<='Barème fiscal'!$B$6,Z8*'Barème fiscal'!$C$6-'Barème fiscal'!$D$6*2,IF(Z8/2<='Barème fiscal'!$B$7,Z8*'Barème fiscal'!$C$7-'Barème fiscal'!$D$7*2,Z8*'Barème fiscal'!$C$8-'Barème fiscal'!$D$8*2))))-MAX(0,IF(AA8<='Barème fiscal'!$B$4,0,IF(AA8<='Barème fiscal'!$B$5,Z8*'Barème fiscal'!$C$5-'Barème fiscal'!$D$5*'Hypothèses'!$B$39,IF(AA8<='Barème fiscal'!$B$6,Z8*'Barème fiscal'!$C$6-'Barème fiscal'!$D$6*'Hypothèses'!$B$39,IF(AA8<='Barème fiscal'!$B$7,Z8*'Barème fiscal'!$C$7-'Barème fiscal'!$D$7*'Hypothèses'!$B$39,Z8*'Barème fiscal'!$C$8-'Barème fiscal'!$D$8*'Hypothèses'!$B$39))))),0),MAX('Hypothèses'!$B$39-2,0)*2*'Barème fiscal'!$B$10) -> 8962.516 | AE8: =Y8*'Hypothèses'!$B$40 -> 0 | AF8: =AD8+AE8 -> 8962.516 | AG8: =P8-AF8 -> 3394.464 | AH8: =H8-G8-AS8 -> 36478.998 | AI8: =(B8-'Tableau dAMT financier'!G20-C8+AG8)/12 -> -472.26831 | AK8: =AK7+AI8*12 -> -33292.549 | AL8: =AL7+F8 -> 36400 | AM8: =MAX(0,A8*'Hypothèses'!$B$31*'Hypothèses'!$B$32-AL8) -> 0 | AN8: =H8-('Hypothèses'!$B$4+MAX('Hypothèses'!$B$4*'Hypothèses'!$B$5,'Hypothèses'!$B$4*'Hypothèses'!$B$43)+IF(A8>5,'Hypothèses'!$B$4*'Hypothèses'!$B$44,0)-AL8) -> 16900 | AO8: =IF(A8<=5,0,IF(A8<=21,(A8-5)*0.06,1)) -> 0 | AP8: =MAX(0,AN8*(1-AO8)) -> 16900 | AQ8: =IF(A8<=5,0,IF(A8<=21,(A8-5)*0.0165,IF(A8=22,(21-5)*0.0165+0.016,IF(A8<=30,(21-5)*0.0165+0.016+(A8-22)*0.09,1)))) -> 0 | AR8: =MAX(0,AN8*(1-AQ8)) -> 16900 | AS8: =IF(AN8<=0,0,AP8*'Hypothèses'!$B$45+AR8*'Hypothèses'!$B$46+IF(AP8<=50000,0,IF(AP8<=60000,AP8*0.02-(60000-AP8)/20,IF(AP8<=100000,AP8*0.02,IF(AP8<=110000,AP8*0.03-(110000-AP8)/10,IF(AP8<=150000,AP8*0.03,IF(AP8<=160000,AP8*0.04-(160000-AP8)*3/20,IF(AP8<=200000,AP8*0.04,IF(AP8<=210000,AP8*0.05-(210000-AP8)/5,IF(AP8<=250000,AP8*0.05,IF(AP8<=260000,AP8*0.06-(260000-AP8)/4,AP8*0.06))))))))))) -> 6117.8 | AT8: 0 | AU8: =IFERROR(IRR(B64:G64),"") -> -0.047064803 | AV8: =MAX(0,I8)*'Barème fiscal'!$B$13 -> 340 | AW8: =Y8*'Barème fiscal'!$B$13 -> 0
A9: 6 | B9: =B8*(1+'Hypothèses'!$B$27) -> 9695.556 | C9: =B9*'Hypothèses'!$B$28 -> 2908.6668 | D9: ='Tableau dAMT financier'!E21 -> 7056.9343 | E9: ='Tableau dAMT financier'!F21 -> 884.8 | F9: =MIN('Hypothèses'!$B$34,MAX(0,'Hypothèses'!$B$31-AL8)) -> 7280 | G9: ='Tableau dAMT financier'!H21 -> 209596.66 | H9: =H8*(1+index) -> 260000 | I9: =I8*(1+index) -> 5000 | J9: ='Hypothèses'!$B$50+I9-AV8 -> 90160 | K9: =J9/'Hypothèses'!$B$39 -> 36064 | L9: =IF(K9<='Barème fiscal'!$B$4,'Barème fiscal'!$C$4,IF(K9<='Barème fiscal'!$B$5,'Barème fiscal'!$C$5,IF(K9<='Barème fiscal'!$B$6,'Barème fiscal'!$C$6,IF(K9<='Barème fiscal'!$B$7,'Barème fiscal'!$C$7,'Barème fiscal'!$C$8)))) -> 0.3 | M9: =IF(J9>0,N9/J9,0) -> 0.12751752 | N9: =MAX(0,IF(J9/2<='Barème fiscal'!$B$4,0,IF(J9/2<='Barème fiscal'!$B$5,J9*'Barème fiscal'!$C$5-'Barème fiscal'!$D$5*2,IF(J9/2<='Barème fiscal'!$B$6,J9*'Barème fiscal'!$C$6-'Barème fiscal'!$D$6*2,IF(J9/2<='Barème fiscal'!$B$7,J9*'Barème fiscal'!$C$7-'Barème fiscal'!$D$7*2,J9*'Barème fiscal'!$C$8-'Barème fiscal'!$D$8*2)))))-MIN(MAX(IF(J9/2<='Barème fiscal'!$B$4,0,IF(J9/2<='Barème fiscal'!$B$5,J9*'Barème fiscal'!$C$5-'Barème fiscal'!$D$5*2,IF(J9/2<='Barème fiscal'!$B$6,J9*'Barème fiscal'!$C$6-'Barème fiscal'!$D$6*2,IF(J9/2<='Barème fiscal'!$B$7,J9*'Barème fiscal'!$C$7-'Barème fiscal'!$D$7*2,J9*'Barème fiscal'!$C$8-'Barème fiscal'!$D$8*2))))-MAX(0,IF(K9<='Barème fiscal'!$B$4,0,IF(K9<='Barème fiscal'!$B$5,J9*'Barème fiscal'!$C$5-'Barème fiscal'!$D$5*'Hypothèses'!$B$39,IF(K9<='Barème fiscal'!$B$6,J9*'Barème fiscal'!$C$6-'Barème fiscal'!$D$6*'Hypothèses'!$B$39,IF(K9<='Barème fiscal'!$B$7,J9*'Barème fiscal'!$C$7-'Barème fiscal'!$D$7*'Hypothèses'!$B$39,J9*'Barème fiscal'!$C$8-'Barème fiscal'!$D$8*'Hypothèses'!$B$39))))),0),MAX('Hypothèses'!$B$39-2,0)*2*'Barème fiscal'!$B$10) -> 11496.98 | O9: =MAX(0,I9)*'Hypothèses'!$B$40 -> 860 | P9: =N9+O9 -> 12356.98 | Q9: =B9+I9 -> 14695.556 | R9: =D9+E9 -> 7941.7343 | S9: =C9+F9 -> 10188.667 | T9: =Q9-R9-S9 -> -3434.8451 | U9: =IF(T9>=0,0,IF(Q9>=R9,MAX(T9,-'Barème fiscal'!$B$11),MAX(-S9,-'Barème fiscal'!$B$11))) -> -3434.8451 | V9: =IF(T9>=0,0,IF(Q9>=R9,MAX(0,-T9-'Barème fiscal'!$B$11),(R9-Q9)+MAX(0,S9-'Barème fiscal'!$B$11))) -> 0 | W9: =W8+V9-X8-AT9 -> 0 | X9: =IF(T9>0,MIN(W9,T9),0) -> 0 | Y9: =MAX(0,T9-X9) -> 0 | Z9: ='Hypothèses'!$B$50+Y9+U9-AW8 -> 82065.155 | AA9: =Z9/'Hypothèses'!$B$39 -> 32826.062 | AB9: =IF(AA9<='Barème fiscal'!$B$4,'Barème fiscal'!$C$4,IF(AA9<='Barème fiscal'!$B$5,'Barème fiscal'!$C$5,IF(AA9<='Barème fiscal'!$B$6,'Barème fiscal'!$C$6,IF(AA9<='Barème fiscal'!$B$7,'Barème fiscal'!$C$7,'Barème fiscal'!$C$8)))) -> 0.3 | AC9: =IF(Z9>0,AD9/Z9,0) -> 0.11050398 | AD9: =MAX(0,IF(Z9/2<='Barème fiscal'!$B$4,0,IF(Z9/2<='Barème fiscal'!$B$5,Z9*'Barème fiscal'!$C$5-'Barème fiscal'!$D$5*2,IF(Z9/2<='Barème fiscal'!$B$6,Z9*'Barème fiscal'!$C$6-'Barème fiscal'!$D$6*2,IF(Z9/2<='Barème fiscal'!$B$7,Z9*'Barème fiscal'!$C$7-'Barème fiscal'!$D$7*2,Z9*'Barème fiscal'!$C$8-'Barème fiscal'!$D$8*2)))))-MIN(MAX(IF(Z9/2<='Barème fiscal'!$B$4,0,IF(Z9/2<='Barème fiscal'!$B$5,Z9*'Barème fiscal'!$C$5-'Barème fiscal'!$D$5*2,IF(Z9/2<='Barème fiscal'!$B$6,Z9*'Barème fiscal'!$C$6-'Barème fiscal'!$D$6*2,IF(Z9/2<='Barème fiscal'!$B$7,Z9*'Barème fiscal'!$C$7-'Barème fiscal'!$D$7*2,Z9*'Barème fiscal'!$C$8-'Barème fiscal'!$D$8*2))))-MAX(0,IF(AA9<='Barème fiscal'!$B$4,0,IF(AA9<='Barème fiscal'!$B$5,Z9*'Barème fiscal'!$C$5-'Barème fiscal'!$D$5*'Hypothèses'!$B$39,IF(AA9<='Barème fiscal'!$B$6,Z9*'Barème fiscal'!$C$6-'Barème fiscal'!$D$6*'Hypothèses'!$B$39,IF(AA9<='Barème fiscal'!$B$7,Z9*'Barème fiscal'!$C$7-'Barème fiscal'!$D$7*'Hypothèses'!$B$39,Z9*'Barème fiscal'!$C$8-'Barème fiscal'!$D$8*'Hypothèses'!$B$39))))),0),MAX('Hypothèses'!$B$39-2,0)*2*'Barème fiscal'!$B$10) -> 9068.5265 | AE9: =Y9*'Hypothèses'!$B$40 -> 0 | AF9: =AD9+AE9 -> 9068.5265 | AG9: =P9-AF9 -> 3288.4535 | AH9: =H9-G9-AS9 -> 50403.338 | AI9: =(B9-'Tableau dAMT financier'!G21-C9+AG9)/12 -> -472.74428 | AK9: =AK8+AI9*12 -> -38965.48 | AL9: =AL8+F9 -> 43680 | AM9: =MAX(0,A9*'Hypothèses'!$B$31*'Hypothèses'!$B$32-AL9) -> 0 | AN9: =H9-('Hypothèses'!$B$4+MAX('Hypothèses'!$B$4*'Hypothèses'!$B$5,'Hypothèses'!$B$4*'Hypothèses'!$B$43)+IF(A9>5,'Hypothèses'!$B$4*'Hypothèses'!$B$44,0)-AL9) -> -14820 | AO9: =IF(A9<=5,0,IF(A9<=21,(A9-5)*0.06,1)) -> 0.06 | AP9: =MAX(0,AN9*(1-AO9)) -> 0 | AQ9: =IF(A9<=5,0,IF(A9<=21,(A9-5)*0.0165,IF(A9=22,(21-5)*0.0165+0.016,IF(A9<=30,(21-5)*0.0165+0.016+(A9-22)*0.09,1)))) -> 0.0165 | AR9: =MAX(0,AN9*(1-AQ9)) -> 0 | AS9: =IF(AN9<=0,0,AP9*'Hypothèses'!$B$45+AR9*'Hypothèses'!$B$46+IF(AP9<=50000,0,IF(AP9<=60000,AP9*0.02-(60000-AP9)/20,IF(AP9<=100000,AP9*0.02,IF(AP9<=110000,AP9*0.03-(110000-AP9)/10,IF(AP9<=150000,AP9*0.03,IF(AP9<=160000,AP9*0.04-(160000-AP9)*3/20,IF(AP9<=200000,AP9*0.04,IF(AP9<=210000,AP9*0.05-(210000-AP9)/5,IF(AP9<=250000,AP9*0.05,IF(AP9<=260000,AP9*0.06-(260000-AP9)/4,AP9*0.06))))))))))) -> 0 | AT9: 0 | AU9: =IFERROR(IRR(B65:H65),"") -> 0.015703556 | AV9: =MAX(0,I9)*'Barème fiscal'!$B$13 -> 340 | AW9: =Y9*'Barème fiscal'!$B$13 -> 0
A10: 7 | B10: =B9*(1+'Hypothèses'!$B$27) -> 9840.9894 | C10: =B10*'Hypothèses'!$B$28 -> 2952.2968 | D10: ='Tableau dAMT financier'!E22 -> 6795.3861 | E10: ='Tableau dAMT financier'!F22 -> 884.8 | F10: =MIN('Hypothèses'!$B$34,MAX(0,'Hypothèses'!$B$31-AL9)) -> 7280 | G10: ='Tableau dAMT financier'!H22 -> 201528.57 | H10: =H9*(1+index) -> 260000 | I10: =I9*(1+index) -> 5000 | J10: ='Hypothèses'!$B$50+I10-AV9 -> 90160 | K10: =J10/'Hypothèses'!$B$39 -> 36064 | L10: =IF(K10<='Barème fiscal'!$B$4,'Barème fiscal'!$C$4,IF(K10<='Barème fiscal'!$B$5,'Barème fiscal'!$C$5,IF(K10<='Barème fiscal'!$B$6,'Barème fiscal'!$C$6,IF(K10<='Barème fiscal'!$B$7,'Barème fiscal'!$C$7,'Barème fiscal'!$C$8)))) -> 0.3 | M10: =IF(J10>0,N10/J10,0) -> 0.12751752 | N10: =MAX(0,IF(J10/2<='Barème fiscal'!$B$4,0,IF(J10/2<='Barème fiscal'!$B$5,J10*'Barème fiscal'!$C$5-'Barème fiscal'!$D$5*2,IF(J10/2<='Barème fiscal'!$B$6,J10*'Barème fiscal'!$C$6-'Barème fiscal'!$D$6*2,IF(J10/2<='Barème fiscal'!$B$7,J10*'Barème fiscal'!$C$7-'Barème fiscal'!$D$7*2,J10*'Barème fiscal'!$C$8-'Barème fiscal'!$D$8*2)))))-MIN(MAX(IF(J10/2<='Barème fiscal'!$B$4,0,IF(J10/2<='Barème fiscal'!$B$5,J10*'Barème fiscal'!$C$5-'Barème fiscal'!$D$5*2,IF(J10/2<='Barème fiscal'!$B$6,J10*'Barème fiscal'!$C$6-'Barème fiscal'!$D$6*2,IF(J10/2<='Barème fiscal'!$B$7,J10*'Barème fiscal'!$C$7-'Barème fiscal'!$D$7*2,J10*'Barème fiscal'!$C$8-'Barème fiscal'!$D$8*2))))-MAX(0,IF(K10<='Barème fiscal'!$B$4,0,IF(K10<='Barème fiscal'!$B$5,J10*'Barème fiscal'!$C$5-'Barème fiscal'!$D$5*'Hypothèses'!$B$39,IF(K10<='Barème fiscal'!$B$6,J10*'Barème fiscal'!$C$6-'Barème fiscal'!$D$6*'Hypothèses'!$B$39,IF(K10<='Barème fiscal'!$B$7,J10*'Barème fiscal'!$C$7-'Barème fiscal'!$D$7*'Hypothèses'!$B$39,J10*'Barème fiscal'!$C$8-'Barème fiscal'!$D$8*'Hypothèses'!$B$39))))),0),MAX('Hypothèses'!$B$39-2,0)*2*'Barème fiscal'!$B$10) -> 11496.98 | O10: =MAX(0,I10)*'Hypothèses'!$B$40 -> 860 | P10: =N10+O10 -> 12356.98 | Q10: =B10+I10 -> 14840.989 | R10: =D10+E10 -> 7680.1861 | S10: =C10+F10 -> 10232.297 | T10: =Q10-R10-S10 -> -3071.4935 | U10: =IF(T10>=0,0,IF(Q10>=R10,MAX(T10,-'Barème fiscal'!$B$11),MAX(-S10,-'Barème fiscal'!$B$11))) -> -3071.4935 | V10: =IF(T10>=0,0,IF(Q10>=R10,MAX(0,-T10-'Barème fiscal'!$B$11),(R10-Q10)+MAX(0,S10-'Barème fiscal'!$B$11))) -> 0 | W10: =W9+V10-X9-AT10 -> 0 | X10: =IF(T10>0,MIN(W10,T10),0) -> 0 | Y10: =MAX(0,T10-X10) -> 0 | Z10: ='Hypothèses'!$B$50+Y10+U10-AW9 -> 82428.506 | AA10: =Z10/'Hypothèses'!$B$39 -> 32971.403 | AB10: =IF(AA10<='Barème fiscal'!$B$4,'Barème fiscal'!$C$4,IF(AA10<='Barème fiscal'!$B$5,'Barème fiscal'!$C$5,IF(AA10<='Barème fiscal'!$B$6,'Barème fiscal'!$C$6,IF(AA10<='Barème fiscal'!$B$7,'Barème fiscal'!$C$7,'Barème fiscal'!$C$8)))) -> 0.3 | AC10: =IF(Z10>0,AD10/Z10,0) -> 0.1113393 | AD10: =MAX(0,IF(Z10/2<='Barème fiscal'!$B$4,0,IF(Z10/2<='Barème fiscal'!$B$5,Z10*'Barème fiscal'!$C$5-'Barème fiscal'!$D$5*2,IF(Z10/2<='Barème fiscal'!$B$6,Z10*'Barème fiscal'!$C$6-'Barème fiscal'!$D$6*2,IF(Z10/2<='Barème fiscal'!$B$7,Z10*'Barème fiscal'!$C$7-'Barème fiscal'!$D$7*2,Z10*'Barème fiscal'!$C$8-'Barème fiscal'!$D$8*2)))))-MIN(MAX(IF(Z10/2<='Barème fiscal'!$B$4,0,IF(Z10/2<='Barème fiscal'!$B$5,Z10*'Barème fiscal'!$C$5-'Barème fiscal'!$D$5*2,IF(Z10/2<='Barème fiscal'!$B$6,Z10*'Barème fiscal'!$C$6-'Barème fiscal'!$D$6*2,IF(Z10/2<='Barème fiscal'!$B$7,Z10*'Barème fiscal'!$C$7-'Barème fiscal'!$D$7*2,Z10*'Barème fiscal'!$C$8-'Barème fiscal'!$D$8*2))))-MAX(0,IF(AA10<='Barème fiscal'!$B$4,0,IF(AA10<='Barème fiscal'!$B$5,Z10*'Barème fiscal'!$C$5-'Barème fiscal'!$D$5*'Hypothèses'!$B$39,IF(AA10<='Barème fiscal'!$B$6,Z10*'Barème fiscal'!$C$6-'Barème fiscal'!$D$6*'Hypothèses'!$B$39,IF(AA10<='Barème fiscal'!$B$7,Z10*'Barème fiscal'!$C$7-'Barème fiscal'!$D$7*'Hypothèses'!$B$39,Z10*'Barème fiscal'!$C$8-'Barème fiscal'!$D$8*'Hypothèses'!$B$39))))),0),MAX('Hypothèses'!$B$39-2,0)*2*'Barème fiscal'!$B$10) -> 9177.5319 | AE10: =Y10*'Hypothèses'!$B$40 -> 0 | AF10: =AD10+AE10 -> 9177.5319 | AG10: =P10-AF10 -> 3179.4481 | AH10: =H10-G10-AS10 -> 58471.426 | AI10: =(B10-'Tableau dAMT financier'!G22-C10+AG10)/12 -> -473.34445 | AK10: =AK9+AI10*12 -> -44645.614 | AL10: =AL9+F10 -> 50960 | AM10: =MAX(0,A10*'Hypothèses'!$B$31*'Hypothèses'!$B$32-AL10) -> 0 | AN10: =H10-('Hypothèses'!$B$4+MAX('Hypothèses'!$B$4*'Hypothèses'!$B$5,'Hypothèses'!$B$4*'Hypothèses'!$B$43)+IF(A10>5,'Hypothèses'!$B$4*'Hypothèses'!$B$44,0)-AL10) -> -7540 | AO10: =IF(A10<=5,0,IF(A10<=21,(A10-5)*0.06,1)) -> 0.12 | AP10: =MAX(0,AN10*(1-AO10)) -> 0 | AQ10: =IF(A10<=5,0,IF(A10<=21,(A10-5)*0.0165,IF(A10=22,(21-5)*0.0165+0.016,IF(A10<=30,(21-5)*0.0165+0.016+(A10-22)*0.09,1)))) -> 0.033 | AR10: =MAX(0,AN10*(1-AQ10)) -> 0 | AS10: =IF(AN10<=0,0,AP10*'Hypothèses'!$B$45+AR10*'Hypothèses'!$B$46+IF(AP10<=50000,0,IF(AP10<=60000,AP10*0.02-(60000-AP10)/20,IF(AP10<=100000,AP10*0.02,IF(AP10<=110000,AP10*0.03-(110000-AP10)/10,IF(AP10<=150000,AP10*0.03,IF(AP10<=160000,AP10*0.04-(160000-AP10)*3/20,IF(AP10<=200000,AP10*0.04,IF(AP10<=210000,AP10*0.05-(210000-AP10)/5,IF(AP10<=250000,AP10*0.05,IF(AP10<=260000,AP10*0.06-(260000-AP10)/4,AP10*0.06))))))))))) -> 0 | AT10: 0 | AU10: =IFERROR(IRR(B66:I66),"") -> 0.02247688 | AV10: =MAX(0,I10)*'Barème fiscal'!$B$13 -> 340 | AW10: =Y10*'Barème fiscal'!$B$13 -> 0
A11: 8 | B11: =B10*(1+'Hypothèses'!$B$27) -> 9988.6042 | C11: =B11*'Hypothèses'!$B$28 -> 2996.5813 | D11: ='Tableau dAMT financier'!E23 -> 6525.0751 | E11: ='Tableau dAMT financier'!F23 -> 884.8 | F11: =MIN('Hypothèses'!$B$34,MAX(0,'Hypothèses'!$B$31-AL10)) -> 7280 | G11: ='Tableau dAMT financier'!H23 -> 193190.18 | H11: =H10*(1+index) -> 260000 | I11: =I10*(1+index) -> 5000 | J11: ='Hypothèses'!$B$50+I11-AV10 -> 90160 | K11: =J11/'Hypothèses'!$B$39 -> 36064 | L11: =IF(K11<='Barème fiscal'!$B$4,'Barème fiscal'!$C$4,IF(K11<='Barème fiscal'!$B$5,'Barème fiscal'!$C$5,IF(K11<='Barème fiscal'!$B$6,'Barème fiscal'!$C$6,IF(K11<='Barème fiscal'!$B$7,'Barème fiscal'!$C$7,'Barème fiscal'!$C$8)))) -> 0.3 | M11: =IF(J11>0,N11/J11,0) -> 0.12751752 | N11: =MAX(0,IF(J11/2<='Barème fiscal'!$B$4,0,IF(J11/2<='Barème fiscal'!$B$5,J11*'Barème fiscal'!$C$5-'Barème fiscal'!$D$5*2,IF(J11/2<='Barème fiscal'!$B$6,J11*'Barème fiscal'!$C$6-'Barème fiscal'!$D$6*2,IF(J11/2<='Barème fiscal'!$B$7,J11*'Barème fiscal'!$C$7-'Barème fiscal'!$D$7*2,J11*'Barème fiscal'!$C$8-'Barème fiscal'!$D$8*2)))))-MIN(MAX(IF(J11/2<='Barème fiscal'!$B$4,0,IF(J11/2<='Barème fiscal'!$B$5,J11*'Barème fiscal'!$C$5-'Barème fiscal'!$D$5*2,IF(J11/2<='Barème fiscal'!$B$6,J11*'Barème fiscal'!$C$6-'Barème fiscal'!$D$6*2,IF(J11/2<='Barème fiscal'!$B$7,J11*'Barème fiscal'!$C$7-'Barème fiscal'!$D$7*2,J11*'Barème fiscal'!$C$8-'Barème fiscal'!$D$8*2))))-MAX(0,IF(K11<='Barème fiscal'!$B$4,0,IF(K11<='Barème fiscal'!$B$5,J11*'Barème fiscal'!$C$5-'Barème fiscal'!$D$5*'Hypothèses'!$B$39,IF(K11<='Barème fiscal'!$B$6,J11*'Barème fiscal'!$C$6-'Barème fiscal'!$D$6*'Hypothèses'!$B$39,IF(K11<='Barème fiscal'!$B$7,J11*'Barème fiscal'!$C$7-'Barème fiscal'!$D$7*'Hypothèses'!$B$39,J11*'Barème fiscal'!$C$8-'Barème fiscal'!$D$8*'Hypothèses'!$B$39))))),0),MAX('Hypothèses'!$B$39-2,0)*2*'Barème fiscal'!$B$10) -> 11496.98 | O11: =MAX(0,I11)*'Hypothèses'!$B$40 -> 860 | P11: =N11+O11 -> 12356.98 | Q11: =B11+I11 -> 14988.604 | R11: =D11+E11 -> 7409.8751 | S11: =C11+F11 -> 10276.581 | T11: =Q11-R11-S11 -> -2697.8521 | U11: =IF(T11>=0,0,IF(Q11>=R11,MAX(T11,-'Barème fiscal'!$B$11),MAX(-S11,-'Barème fiscal'!$B$11))) -> -2697.8521 | V11: =IF(T11>=0,0,IF(Q11>=R11,MAX(0,-T11-'Barème fiscal'!$B$11),(R11-Q11)+MAX(0,S11-'Barème fiscal'!$B$11))) -> 0 | W11: =W10+V11-X10-AT11 -> 0 | X11: =IF(T11>0,MIN(W11,T11),0) -> 0 | Y11: =MAX(0,T11-X11) -> 0 | Z11: ='Hypothèses'!$B$50+Y11+U11-AW10 -> 82802.148 | AA11: =Z11/'Hypothèses'!$B$39 -> 33120.859 | AB11: =IF(AA11<='Barème fiscal'!$B$4,'Barème fiscal'!$C$4,IF(AA11<='Barème fiscal'!$B$5,'Barème fiscal'!$C$5,IF(AA11<='Barème fiscal'!$B$6,'Barème fiscal'!$C$6,IF(AA11<='Barème fiscal'!$B$7,'Barème fiscal'!$C$7,'Barème fiscal'!$C$8)))) -> 0.3 | AC11: =IF(Z11>0,AD11/Z11,0) -> 0.11219062 | AD11: =MAX(0,IF(Z11/2<='Barème fiscal'!$B$4,0,IF(Z11/2<='Barème fiscal'!$B$5,Z11*'Barème fiscal'!$C$5-'Barème fiscal'!$D$5*2,IF(Z11/2<='Barème fiscal'!$B$6,Z11*'Barème fiscal'!$C$6-'Barème fiscal'!$D$6*2,IF(Z11/2<='Barème fiscal'!$B$7,Z11*'Barème fiscal'!$C$7-'Barème fiscal'!$D$7*2,Z11*'Barème fiscal'!$C$8-'Barème fiscal'!$D$8*2)))))-MIN(MAX(IF(Z11/2<='Barème fiscal'!$B$4,0,IF(Z11/2<='Barème fiscal'!$B$5,Z11*'Barème fiscal'!$C$5-'Barème fiscal'!$D$5*2,IF(Z11/2<='Barème fiscal'!$B$6,Z11*'Barème fiscal'!$C$6-'Barème fiscal'!$D$6*2,IF(Z11/2<='Barème fiscal'!$B$7,Z11*'Barème fiscal'!$C$7-'Barème fiscal'!$D$7*2,Z11*'Barème fiscal'!$C$8-'Barème fiscal'!$D$8*2))))-MAX(0,IF(AA11<='Barème fiscal'!$B$4,0,IF(AA11<='Barème fiscal'!$B$5,Z11*'Barème fiscal'!$C$5-'Barème fiscal'!$D$5*'Hypothèses'!$B$39,IF(AA11<='Barème fiscal'!$B$6,Z11*'Barème fiscal'!$C$6-'Barème fiscal'!$D$6*'Hypothèses'!$B$39,IF(AA11<='Barème fiscal'!$B$7,Z11*'Barème fiscal'!$C$7-'Barème fiscal'!$D$7*'Hypothèses'!$B$39,Z11*'Barème fiscal'!$C$8-'Barème fiscal'!$D$8*'Hypothèses'!$B$39))))),0),MAX('Hypothèses'!$B$39-2,0)*2*'Barème fiscal'!$B$10) -> 9289.6244 | AE11: =Y11*'Hypothèses'!$B$40 -> 0 | AF11: =AD11+AE11 -> 9289.6244 | AG11: =P11-AF11 -> 3067.3556 | AH11: =H11-G11-AS11 -> 66809.825 | AI11: =(B11-'Tableau dAMT financier'!G23-C11+AG11)/12 -> -474.07462 | AK11: =AK10+AI11*12 -> -50334.509 | AL11: =AL10+F11 -> 58240 | AM11: =MAX(0,A11*'Hypothèses'!$B$31*'Hypothèses'!$B$32-AL11) -> 0 | AN11: =H11-('Hypothèses'!$B$4+MAX('Hypothèses'!$B$4*'Hypothèses'!$B$5,'Hypothèses'!$B$4*'Hypothèses'!$B$43)+IF(A11>5,'Hypothèses'!$B$4*'Hypothèses'!$B$44,0)-AL11) -> -260 | AO11: =IF(A11<=5,0,IF(A11<=21,(A11-5)*0.06,1)) -> 0.18 | AP11: =MAX(0,AN11*(1-AO11)) -> 0 | AQ11: =IF(A11<=5,0,IF(A11<=21,(A11-5)*0.0165,IF(A11=22,(21-5)*0.0165+0.016,IF(A11<=30,(21-5)*0.0165+0.016+(A11-22)*0.09,1)))) -> 0.0495 | AR11: =MAX(0,AN11*(1-AQ11)) -> 0 | AS11: =IF(AN11<=0,0,AP11*'Hypothèses'!$B$45+AR11*'Hypothèses'!$B$46+IF(AP11<=50000,0,IF(AP11<=60000,AP11*0.02-(60000-AP11)/20,IF(AP11<=100000,AP11*0.02,IF(AP11<=110000,AP11*0.03-(110000-AP11)/10,IF(AP11<=150000,AP11*0.03,IF(AP11<=160000,AP11*0.04-(160000-AP11)*3/20,IF(AP11<=200000,AP11*0.04,IF(AP11<=210000,AP11*0.05-(210000-AP11)/5,IF(AP11<=250000,AP11*0.05,IF(AP11<=260000,AP11*0.06-(260000-AP11)/4,AP11*0.06))))))))))) -> 0 | AT11: 0 | AU11: =IFERROR(IRR(B67:J67),"") -> 0.026830922 | AV11: =MAX(0,I11)*'Barème fiscal'!$B$13 -> 340 | AW11: =Y11*'Barème fiscal'!$B$13 -> 0
A12: 9 | B12: =B11*(1+'Hypothèses'!$B$27) -> 10138.433 | C12: =B12*'Hypothèses'!$B$28 -> 3041.53 | D12: ='Tableau dAMT financier'!E24 -> 6245.7076 | E12: ='Tableau dAMT financier'!F24 -> 884.8 | F12: =MIN('Hypothèses'!$B$34,MAX(0,'Hypothèses'!$B$31-AL11)) -> 7280 | G12: ='Tableau dAMT financier'!H24 -> 184572.41 | H12: =H11*(1+index) -> 260000 | I12: =I11*(1+index) -> 5000 | J12: ='Hypothèses'!$B$50+I12-AV11 -> 90160 | K12: =J12/'Hypothèses'!$B$39 -> 36064 | L12: =IF(K12<='Barème fiscal'!$B$4,'Barème fiscal'!$C$4,IF(K12<='Barème fiscal'!$B$5,'Barème fiscal'!$C$5,IF(K12<='Barème fiscal'!$B$6,'Barème fiscal'!$C$6,IF(K12<='Barème fiscal'!$B$7,'Barème fiscal'!$C$7,'Barème fiscal'!$C$8)))) -> 0.3 | M12: =IF(J12>0,N12/J12,0) -> 0.12751752 | N12: =MAX(0,IF(J12/2<='Barème fiscal'!$B$4,0,IF(J12/2<='Barème fiscal'!$B$5,J12*'Barème fiscal'!$C$5-'Barème fiscal'!$D$5*2,IF(J12/2<='Barème fiscal'!$B$6,J12*'Barème fiscal'!$C$6-'Barème fiscal'!$D$6*2,IF(J12/2<='Barème fiscal'!$B$7,J12*'Barème fiscal'!$C$7-'Barème fiscal'!$D$7*2,J12*'Barème fiscal'!$C$8-'Barème fiscal'!$D$8*2)))))-MIN(MAX(IF(J12/2<='Barème fiscal'!$B$4,0,IF(J12/2<='Barème fiscal'!$B$5,J12*'Barème fiscal'!$C$5-'Barème fiscal'!$D$5*2,IF(J12/2<='Barème fiscal'!$B$6,J12*'Barème fiscal'!$C$6-'Barème fiscal'!$D$6*2,IF(J12/2<='Barème fiscal'!$B$7,J12*'Barème fiscal'!$C$7-'Barème fiscal'!$D$7*2,J12*'Barème fiscal'!$C$8-'Barème fiscal'!$D$8*2))))-MAX(0,IF(K12<='Barème fiscal'!$B$4,0,IF(K12<='Barème fiscal'!$B$5,J12*'Barème fiscal'!$C$5-'Barème fiscal'!$D$5*'Hypothèses'!$B$39,IF(K12<='Barème fiscal'!$B$6,J12*'Barème fiscal'!$C$6-'Barème fiscal'!$D$6*'Hypothèses'!$B$39,IF(K12<='Barème fiscal'!$B$7,J12*'Barème fiscal'!$C$7-'Barème fiscal'!$D$7*'Hypothèses'!$B$39,J12*'Barème fiscal'!$C$8-'Barème fiscal'!$D$8*'Hypothèses'!$B$39))))),0),MAX('Hypothèses'!$B$39-2,0)*2*'Barème fiscal'!$B$10) -> 11496.98 | O12: =MAX(0,I12)*'Hypothèses'!$B$40 -> 860 | P12: =N12+O12 -> 12356.98 | Q12: =B12+I12 -> 15138.433 | R12: =D12+E12 -> 7130.5076 | S12: =C12+F12 -> 10321.53 | T12: =Q12-R12-S12 -> -2313.6043 | U12: =IF(T12>=0,0,IF(Q12>=R12,MAX(T12,-'Barème fiscal'!$B$11),MAX(-S12,-'Barème fiscal'!$B$11))) -> -2313.6043 | V12: =IF(T12>=0,0,IF(Q12>=R12,MAX(0,-T12-'Barème fiscal'!$B$11),(R12-Q12)+MAX(0,S12-'Barème fiscal'!$B$11))) -> 0 | W12: =W11+V12-X11-AT12 -> 0 | X12: =IF(T12>0,MIN(W12,T12),0) -> 0 | Y12: =MAX(0,T12-X12) -> 0 | Z12: ='Hypothèses'!$B$50+Y12+U12-AW11 -> 83186.396 | AA12: =Z12/'Hypothèses'!$B$39 -> 33274.558 | AB12: =IF(AA12<='Barème fiscal'!$B$4,'Barème fiscal'!$C$4,IF(AA12<='Barème fiscal'!$B$5,'Barème fiscal'!$C$5,IF(AA12<='Barème fiscal'!$B$6,'Barème fiscal'!$C$6,IF(AA12<='Barème fiscal'!$B$7,'Barème fiscal'!$C$7,'Barème fiscal'!$C$8)))) -> 0.3 | AC12: =IF(Z12>0,AD12/Z12,0) -> 0.11305813 | AD12: =MAX(0,IF(Z12/2<='Barème fiscal'!$B$4,0,IF(Z12/2<='Barème fiscal'!$B$5,Z12*'Barème fiscal'!$C$5-'Barème fiscal'!$D$5*2,IF(Z12/2<='Barème fiscal'!$B$6,Z12*'Barème fiscal'!$C$6-'Barème fiscal'!$D$6*2,IF(Z12/2<='Barème fiscal'!$B$7,Z12*'Barème fiscal'!$C$7-'Barème fiscal'!$D$7*2,Z12*'Barème fiscal'!$C$8-'Barème fiscal'!$D$8*2)))))-MIN(MAX(IF(Z12/2<='Barème fiscal'!$B$4,0,IF(Z12/2<='Barème fiscal'!$B$5,Z12*'Barème fiscal'!$C$5-'Barème fiscal'!$D$5*2,IF(Z12/2<='Barème fiscal'!$B$6,Z12*'Barème fiscal'!$C$6-'Barème fiscal'!$D$6*2,IF(Z12/2<='Barème fiscal'!$B$7,Z12*'Barème fiscal'!$C$7-'Barème fiscal'!$D$7*2,Z12*'Barème fiscal'!$C$8-'Barème fiscal'!$D$8*2))))-MAX(0,IF(AA12<='Barème fiscal'!$B$4,0,IF(AA12<='Barème fiscal'!$B$5,Z12*'Barème fiscal'!$C$5-'Barème fiscal'!$D$5*'Hypothèses'!$B$39,IF(AA12<='Barème fiscal'!$B$6,Z12*'Barème fiscal'!$C$6-'Barème fiscal'!$D$6*'Hypothèses'!$B$39,IF(AA12<='Barème fiscal'!$B$7,Z12*'Barème fiscal'!$C$7-'Barème fiscal'!$D$7*'Hypothèses'!$B$39,Z12*'Barème fiscal'!$C$8-'Barème fiscal'!$D$8*'Hypothèses'!$B$39))))),0),MAX('Hypothèses'!$B$39-2,0)*2*'Barème fiscal'!$B$10) -> 9404.8987 | AE12: =Y12*'Hypothèses'!$B$40 -> 0 | AF12: =AD12+AE12 -> 9404.8987 | AG12: =P12-AF12 -> 2952.0813 | AH12: =H12-G12-AS12 -> 73286.154 | AI12: =(B12-'Tableau dAMT financier'!G24-C12+AG12)/12 -> -474.94079 | AK12: =AK11+AI12*12 -> -56033.799 | AL12: =AL11+F12 -> 65520 | AM12: =MAX(0,A12*'Hypothèses'!$B$31*'Hypothèses'!$B$32-AL12) -> 0 | AN12: =H12-('Hypothèses'!$B$4+MAX('Hypothèses'!$B$4*'Hypothèses'!$B$5,'Hypothèses'!$B$4*'Hypothèses'!$B$43)+IF(A12>5,'Hypothèses'!$B$4*'Hypothèses'!$B$44,0)-AL12) -> 7020 | AO12: =IF(A12<=5,0,IF(A12<=21,(A12-5)*0.06,1)) -> 0.24 | AP12: =MAX(0,AN12*(1-AO12)) -> 5335.2 | AQ12: =IF(A12<=5,0,IF(A12<=21,(A12-5)*0.0165,IF(A12=22,(21-5)*0.0165+0.016,IF(A12<=30,(21-5)*0.0165+0.016+(A12-22)*0.09,1)))) -> 0.066 | AR12: =MAX(0,AN12*(1-AQ12)) -> 6556.68 | AS12: =IF(AN12<=0,0,AP12*'Hypothèses'!$B$45+AR12*'Hypothèses'!$B$46+IF(AP12<=50000,0,IF(AP12<=60000,AP12*0.02-(60000-AP12)/20,IF(AP12<=100000,AP12*0.02,IF(AP12<=110000,AP12*0.03-(110000-AP12)/10,IF(AP12<=150000,AP12*0.03,IF(AP12<=160000,AP12*0.04-(160000-AP12)*3/20,IF(AP12<=200000,AP12*0.04,IF(AP12<=210000,AP12*0.05-(210000-AP12)/5,IF(AP12<=250000,AP12*0.05,IF(AP12<=260000,AP12*0.06-(260000-AP12)/4,AP12*0.06))))))))))) -> 2141.437 | AT12: 0 | AU12: =IFERROR(IRR(B68:K68),"") -> 0.02417446 | AV12: =MAX(0,I12)*'Barème fiscal'!$B$13 -> 340 | AW12: =Y12*'Barème fiscal'!$B$13 -> 0
A13: 10 | B13: =B12*(1+'Hypothèses'!$B$27) -> 10290.51 | C13: =B13*'Hypothèses'!$B$28 -> 3087.1529 | D13: ='Tableau dAMT financier'!E25 -> 5956.9803 | E13: ='Tableau dAMT financier'!F25 -> 884.8 | F13: =MIN('Hypothèses'!$B$34,MAX(0,'Hypothèses'!$B$31-AL12)) -> 7280 | G13: ='Tableau dAMT financier'!H25 -> 175665.92 | H13: =H12*(1+index) -> 260000 | I13: =I12*(1+index) -> 5000 | J13: ='Hypothèses'!$B$50+I13-AV12 -> 90160 | K13: =J13/'Hypothèses'!$B$39 -> 36064 | L13: =IF(K13<='Barème fiscal'!$B$4,'Barème fiscal'!$C$4,IF(K13<='Barème fiscal'!$B$5,'Barème fiscal'!$C$5,IF(K13<='Barème fiscal'!$B$6,'Barème fiscal'!$C$6,IF(K13<='Barème fiscal'!$B$7,'Barème fiscal'!$C$7,'Barème fiscal'!$C$8)))) -> 0.3 | M13: =IF(J13>0,N13/J13,0) -> 0.12751752 | N13: =MAX(0,IF(J13/2<='Barème fiscal'!$B$4,0,IF(J13/2<='Barème fiscal'!$B$5,J13*'Barème fiscal'!$C$5-'Barème fiscal'!$D$5*2,IF(J13/2<='Barème fiscal'!$B$6,J13*'Barème fiscal'!$C$6-'Barème fiscal'!$D$6*2,IF(J13/2<='Barème fiscal'!$B$7,J13*'Barème fiscal'!$C$7-'Barème fiscal'!$D$7*2,J13*'Barème fiscal'!$C$8-'Barème fiscal'!$D$8*2)))))-MIN(MAX(IF(J13/2<='Barème fiscal'!$B$4,0,IF(J13/2<='Barème fiscal'!$B$5,J13*'Barème fiscal'!$C$5-'Barème fiscal'!$D$5*2,IF(J13/2<='Barème fiscal'!$B$6,J13*'Barème fiscal'!$C$6-'Barème fiscal'!$D$6*2,IF(J13/2<='Barème fiscal'!$B$7,J13*'Barème fiscal'!$C$7-'Barème fiscal'!$D$7*2,J13*'Barème fiscal'!$C$8-'Barème fiscal'!$D$8*2))))-MAX(0,IF(K13<='Barème fiscal'!$B$4,0,IF(K13<='Barème fiscal'!$B$5,J13*'Barème fiscal'!$C$5-'Barème fiscal'!$D$5*'Hypothèses'!$B$39,IF(K13<='Barème fiscal'!$B$6,J13*'Barème fiscal'!$C$6-'Barème fiscal'!$D$6*'Hypothèses'!$B$39,IF(K13<='Barème fiscal'!$B$7,J13*'Barème fiscal'!$C$7-'Barème fiscal'!$D$7*'Hypothèses'!$B$39,J13*'Barème fiscal'!$C$8-'Barème fiscal'!$D$8*'Hypothèses'!$B$39))))),0),MAX('Hypothèses'!$B$39-2,0)*2*'Barème fiscal'!$B$10) -> 11496.98 | O13: =MAX(0,I13)*'Hypothèses'!$B$40 -> 860 | P13: =N13+O13 -> 12356.98 | Q13: =B13+I13 -> 15290.51 | R13: =D13+E13 -> 6841.7803 | S13: =C13+F13 -> 10367.153 | T13: =Q13-R13-S13 -> -1918.4235 | U13: =IF(T13>=0,0,IF(Q13>=R13,MAX(T13,-'Barème fiscal'!$B$11),MAX(-S13,-'Barème fiscal'!$B$11))) -> -1918.4235 | V13: =IF(T13>=0,0,IF(Q13>=R13,MAX(0,-T13-'Barème fiscal'!$B$11),(R13-Q13)+MAX(0,S13-'Barème fiscal'!$B$11))) -> 0 | W13: =W12+V13-X12-AT13 -> 0 | X13: =IF(T13>0,MIN(W13,T13),0) -> 0 | Y13: =MAX(0,T13-X13) -> 0 | Z13: ='Hypothèses'!$B$50+Y13+U13-AW12 -> 83581.577 | AA13: =Z13/'Hypothèses'!$B$39 -> 33432.631 | AB13: =IF(AA13<='Barème fiscal'!$B$4,'Barème fiscal'!$C$4,IF(AA13<='Barème fiscal'!$B$5,'Barème fiscal'!$C$5,IF(AA13<='Barème fiscal'!$B$6,'Barème fiscal'!$C$6,IF(AA13<='Barème fiscal'!$B$7,'Barème fiscal'!$C$7,'Barème fiscal'!$C$8)))) -> 0.3 | AC13: =IF(Z13>0,AD13/Z13,0) -> 0.11394201 | AD13: =MAX(0,IF(Z13/2<='Barème fiscal'!$B$4,0,IF(Z13/2<='Barème fiscal'!$B$5,Z13*'Barème fiscal'!$C$5-'Barème fiscal'!$D$5*2,IF(Z13/2<='Barème fiscal'!$B$6,Z13*'Barème fiscal'!$C$6-'Barème fiscal'!$D$6*2,IF(Z13/2<='Barème fiscal'!$B$7,Z13*'Barème fiscal'!$C$7-'Barème fiscal'!$D$7*2,Z13*'Barème fiscal'!$C$8-'Barème fiscal'!$D$8*2)))))-MIN(MAX(IF(Z13/2<='Barème fiscal'!$B$4,0,IF(Z13/2<='Barème fiscal'!$B$5,Z13*'Barème fiscal'!$C$5-'Barème fiscal'!$D$5*2,IF(Z13/2<='Barème fiscal'!$B$6,Z13*'Barème fiscal'!$C$6-'Barème fiscal'!$D$6*2,IF(Z13/2<='Barème fiscal'!$B$7,Z13*'Barème fiscal'!$C$7-'Barème fiscal'!$D$7*2,Z13*'Barème fiscal'!$C$8-'Barème fiscal'!$D$8*2))))-MAX(0,IF(AA13<='Barème fiscal'!$B$4,0,IF(AA13<='Barème fiscal'!$B$5,Z13*'Barème fiscal'!$C$5-'Barème fiscal'!$D$5*'Hypothèses'!$B$39,IF(AA13<='Barème fiscal'!$B$6,Z13*'Barème fiscal'!$C$6-'Barème fiscal'!$D$6*'Hypothèses'!$B$39,IF(AA13<='Barème fiscal'!$B$7,Z13*'Barème fiscal'!$C$7-'Barème fiscal'!$D$7*'Hypothèses'!$B$39,Z13*'Barème fiscal'!$C$8-'Barème fiscal'!$D$8*'Hypothèses'!$B$39))))),0),MAX('Hypothèses'!$B$39-2,0)*2*'Barème fiscal'!$B$10) -> 9523.453 | AE13: =Y13*'Hypothèses'!$B$40 -> 0 | AF13: =AD13+AE13 -> 9523.453 | AG13: =P13-AF13 -> 2833.527 | AH13: =H13-G13-AS13 -> 80175.502 | AI13: =(B13-'Tableau dAMT financier'!G25-C13+AG13)/12 -> -475.94918 | AJ13: =AVERAGE(AI13:AI28) -> -515.76811 | AK13: =AK12+AI13*12 -> -61745.189 | AL13: =AL12+F13 -> 72800 | AM13: =MAX(0,A13*'Hypothèses'!$B$31*'Hypothèses'!$B$32-AL13) -> 0 | AN13: =H13-('Hypothèses'!$B$4+MAX('Hypothèses'!$B$4*'Hypothèses'!$B$5,'Hypothèses'!$B$4*'Hypothèses'!$B$43)+IF(A13>5,'Hypothèses'!$B$4*'Hypothèses'!$B$44,0)-AL13) -> 14300 | AO13: =IF(A13<=5,0,IF(A13<=21,(A13-5)*0.06,1)) -> 0.3 | AP13: =MAX(0,AN13*(1-AO13)) -> 10010 | AQ13: =IF(A13<=5,0,IF(A13<=21,(A13-5)*0.0165,IF(A13=22,(21-5)*0.0165+0.016,IF(A13<=30,(21-5)*0.0165+0.016+(A13-22)*0.09,1)))) -> 0.0825 | AR13: =MAX(0,AN13*(1-AQ13)) -> 13120.25 | AS13: =IF(AN13<=0,0,AP13*'Hypothèses'!$B$45+AR13*'Hypothèses'!$B$46+IF(AP13<=50000,0,IF(AP13<=60000,AP13*0.02-(60000-AP13)/20,IF(AP13<=100000,AP13*0.02,IF(AP13<=110000,AP13*0.03-(110000-AP13)/10,IF(AP13<=150000,AP13*0.03,IF(AP13<=160000,AP13*0.04-(160000-AP13)*3/20,IF(AP13<=200000,AP13*0.04,IF(AP13<=210000,AP13*0.05-(210000-AP13)/5,IF(AP13<=250000,AP13*0.05,IF(AP13<=260000,AP13*0.06-(260000-AP13)/4,AP13*0.06))))))))))) -> 4158.583 | AT13: 0 | AU13: =IFERROR(IRR(B69:L69),"") -> 0.022883149 | AV13: =MAX(0,I13)*'Barème fiscal'!$B$13 -> 340 | AW13: =Y13*'Barème fiscal'!$B$13 -> 0
A14: 11 | B14: =B13*(1+'Hypothèses'!$B$27) -> 10444.867 | C14: =B14*'Hypothèses'!$B$28 -> 3133.4602 | D14: ='Tableau dAMT financier'!E26 -> 5658.5796 | E14: ='Tableau dAMT financier'!F26 -> 884.8 | F14: =MIN('Hypothèses'!$B$34,MAX(0,'Hypothèses'!$B$31-AL13)) -> 7280 | G14: ='Tableau dAMT financier'!H26 -> 166461.02 | H14: =H13*(1+index) -> 260000 | I14: =I13*(1+index) -> 5000 | J14: ='Hypothèses'!$B$50+I14-AV13 -> 90160 | K14: =J14/'Hypothèses'!$B$39 -> 36064 | L14: =IF(K14<='Barème fiscal'!$B$4,'Barème fiscal'!$C$4,IF(K14<='Barème fiscal'!$B$5,'Barème fiscal'!$C$5,IF(K14<='Barème fiscal'!$B$6,'Barème fiscal'!$C$6,IF(K14<='Barème fiscal'!$B$7,'Barème fiscal'!$C$7,'Barème fiscal'!$C$8)))) -> 0.3 | M14: =IF(J14>0,N14/J14,0) -> 0.12751752 | N14: =MAX(0,IF(J14/2<='Barème fiscal'!$B$4,0,IF(J14/2<='Barème fiscal'!$B$5,J14*'Barème fiscal'!$C$5-'Barème fiscal'!$D$5*2,IF(J14/2<='Barème fiscal'!$B$6,J14*'Barème fiscal'!$C$6-'Barème fiscal'!$D$6*2,IF(J14/2<='Barème fiscal'!$B$7,J14*'Barème fiscal'!$C$7-'Barème fiscal'!$D$7*2,J14*'Barème fiscal'!$C$8-'Barème fiscal'!$D$8*2)))))-MIN(MAX(IF(J14/2<='Barème fiscal'!$B$4,0,IF(J14/2<='Barème fiscal'!$B$5,J14*'Barème fiscal'!$C$5-'Barème fiscal'!$D$5*2,IF(J14/2<='Barème fiscal'!$B$6,J14*'Barème fiscal'!$C$6-'Barème fiscal'!$D$6*2,IF(J14/2<='Barème fiscal'!$B$7,J14*'Barème fiscal'!$C$7-'Barème fiscal'!$D$7*2,J14*'Barème fiscal'!$C$8-'Barème fiscal'!$D$8*2))))-MAX(0,IF(K14<='Barème fiscal'!$B$4,0,IF(K14<='Barème fiscal'!$B$5,J14*'Barème fiscal'!$C$5-'Barème fiscal'!$D$5*'Hypothèses'!$B$39,IF(K14<='Barème fiscal'!$B$6,J14*'Barème fiscal'!$C$6-'Barème fiscal'!$D$6*'Hypothèses'!$B$39,IF(K14<='Barème fiscal'!$B$7,J14*'Barème fiscal'!$C$7-'Barème fiscal'!$D$7*'Hypothèses'!$B$39,J14*'Barème fiscal'!$C$8-'Barème fiscal'!$D$8*'Hypothèses'!$B$39))))),0),MAX('Hypothèses'!$B$39-2,0)*2*'Barème fiscal'!$B$10) -> 11496.98 | O14: =MAX(0,I14)*'Hypothèses'!$B$40 -> 860 | P14: =N14+O14 -> 12356.98 | Q14: =B14+I14 -> 15444.867 | R14: =D14+E14 -> 6543.3796 | S14: =C14+F14 -> 10413.46 | T14: =Q14-R14-S14 -> -1511.9724 | U14: =IF(T14>=0,0,IF(Q14>=R14,MAX(T14,-'Barème fiscal'!$B$11),MAX(-S14,-'Barème fiscal'!$B$11))) -> -1511.9724 | V14: =IF(T14>=0,0,IF(Q14>=R14,MAX(0,-T14-'Barème fiscal'!$B$11),(R14-Q14)+MAX(0,S14-'Barème fiscal'!$B$11))) -> 0 | W14: =W13+V14-X13-AT14 -> 0 | X14: =IF(T14>0,MIN(W14,T14),0) -> 0 | Y14: =MAX(0,T14-X14) -> 0 | Z14: ='Hypothèses'!$B$50+Y14+U14-AW13 -> 83988.028 | AA14: =Z14/'Hypothèses'!$B$39 -> 33595.211 | AB14: =IF(AA14<='Barème fiscal'!$B$4,'Barème fiscal'!$C$4,IF(AA14<='Barème fiscal'!$B$5,'Barème fiscal'!$C$5,IF(AA14<='Barème fiscal'!$B$6,'Barème fiscal'!$C$6,IF(AA14<='Barème fiscal'!$B$7,'Barème fiscal'!$C$7,'Barème fiscal'!$C$8)))) -> 0.3 | AC14: =IF(Z14>0,AD14/Z14,0) -> 0.11484242 | AD14: =MAX(0,IF(Z14/2<='Barème fiscal'!$B$4,0,IF(Z14/2<='Barème fiscal'!$B$5,Z14*'Barème fiscal'!$C$5-'Barème fiscal'!$D$5*2,IF(Z14/2<='Barème fiscal'!$B$6,Z14*'Barème fiscal'!$C$6-'Barème fiscal'!$D$6*2,IF(Z14/2<='Barème fiscal'!$B$7,Z14*'Barème fiscal'!$C$7-'Barème fiscal'!$D$7*2,Z14*'Barème fiscal'!$C$8-'Barème fiscal'!$D$8*2)))))-MIN(MAX(IF(Z14/2<='Barème fiscal'!$B$4,0,IF(Z14/2<='Barème fiscal'!$B$5,Z14*'Barème fiscal'!$C$5-'Barème fiscal'!$D$5*2,IF(Z14/2<='Barème fiscal'!$B$6,Z14*'Barème fiscal'!$C$6-'Barème fiscal'!$D$6*2,IF(Z14/2<='Barème fiscal'!$B$7,Z14*'Barème fiscal'!$C$7-'Barème fiscal'!$D$7*2,Z14*'Barème fiscal'!$C$8-'Barème fiscal'!$D$8*2))))-MAX(0,IF(AA14<='Barème fiscal'!$B$4,0,IF(AA14<='Barème fiscal'!$B$5,Z14*'Barème fiscal'!$C$5-'Barème fiscal'!$D$5*'Hypothèses'!$B$39,IF(AA14<='Barème fiscal'!$B$6,Z14*'Barème fiscal'!$C$6-'Barème fiscal'!$D$6*'Hypothèses'!$B$39,IF(AA14<='Barème fiscal'!$B$7,Z14*'Barème fiscal'!$C$7-'Barème fiscal'!$D$7*'Hypothèses'!$B$39,Z14*'Barème fiscal'!$C$8-'Barème fiscal'!$D$8*'Hypothèses'!$B$39))))),0),MAX('Hypothèses'!$B$39-2,0)*2*'Barème fiscal'!$B$10) -> 9645.3883 | AE14: =Y14*'Hypothèses'!$B$40 -> 0 | AF14: =AD14+AE14 -> 9645.3883 | AG14: =P14-AF14 -> 2711.5917 | AH14: =H14-G14-AS14 -> 87570.556 | AI14: =(B14-'Tableau dAMT financier'!G26-C14+AG14)/12 -> -477.10626 | AK14: =AK13+AI14*12 -> -67470.464 | AL14: =AL13+F14 -> 80080 | AM14: =MAX(0,A14*'Hypothèses'!$B$31*'Hypothèses'!$B$32-AL14) -> 0 | AN14: =H14-('Hypothèses'!$B$4+MAX('Hypothèses'!$B$4*'Hypothèses'!$B$5,'Hypothèses'!$B$4*'Hypothèses'!$B$43)+IF(A14>5,'Hypothèses'!$B$4*'Hypothèses'!$B$44,0)-AL14) -> 21580 | AO14: =IF(A14<=5,0,IF(A14<=21,(A14-5)*0.06,1)) -> 0.36 | AP14: =MAX(0,AN14*(1-AO14)) -> 13811.2 | AQ14: =IF(A14<=5,0,IF(A14<=21,(A14-5)*0.0165,IF(A14=22,(21-5)*0.0165+0.016,IF(A14<=30,(21-5)*0.0165+0.016+(A14-22)*0.09,1)))) -> 0.099 | AR14: =MAX(0,AN14*(1-AQ14)) -> 19443.58 | AS14: =IF(AN14<=0,0,AP14*'Hypothèses'!$B$45+AR14*'Hypothèses'!$B$46+IF(AP14<=50000,0,IF(AP14<=60000,AP14*0.02-(60000-AP14)/20,IF(AP14<=100000,AP14*0.02,IF(AP14<=110000,AP14*0.03-(110000-AP14)/10,IF(AP14<=150000,AP14*0.03,IF(AP14<=160000,AP14*0.04-(160000-AP14)*3/20,IF(AP14<=200000,AP14*0.04,IF(AP14<=210000,AP14*0.05-(210000-AP14)/5,IF(AP14<=250000,AP14*0.05,IF(AP14<=260000,AP14*0.06-(260000-AP14)/4,AP14*0.06))))))))))) -> 5968.4238 | AT14: 0 | AU14: =IFERROR(IRR(B70:M70),"") -> 0.022582168 | AV14: =MAX(0,I14)*'Barème fiscal'!$B$13 -> 340 | AW14: =Y14*'Barème fiscal'!$B$13 -> 0
A15: 12 | B15: =B14*(1+'Hypothèses'!$B$27) -> 10601.54 | C15: =B15*'Hypothèses'!$B$28 -> 3180.4621 | D15: ='Tableau dAMT financier'!E27 -> 5350.1813 | E15: ='Tableau dAMT financier'!F27 -> 884.8 | F15: =MIN('Hypothèses'!$B$34,MAX(0,'Hypothèses'!$B$31-AL14)) -> 7280 | G15: ='Tableau dAMT financier'!H27 -> 156947.73 | H15: =H14*(1+index) -> 260000 | I15: =I14*(1+index) -> 5000 | J15: ='Hypothèses'!$B$50+I15-AV14 -> 90160 | K15: =J15/'Hypothèses'!$B$39 -> 36064 | L15: =IF(K15<='Barème fiscal'!$B$4,'Barème fiscal'!$C$4,IF(K15<='Barème fiscal'!$B$5,'Barème fiscal'!$C$5,IF(K15<='Barème fiscal'!$B$6,'Barème fiscal'!$C$6,IF(K15<='Barème fiscal'!$B$7,'Barème fiscal'!$C$7,'Barème fiscal'!$C$8)))) -> 0.3 | M15: =IF(J15>0,N15/J15,0) -> 0.12751752 | N15: =MAX(0,IF(J15/2<='Barème fiscal'!$B$4,0,IF(J15/2<='Barème fiscal'!$B$5,J15*'Barème fiscal'!$C$5-'Barème fiscal'!$D$5*2,IF(J15/2<='Barème fiscal'!$B$6,J15*'Barème fiscal'!$C$6-'Barème fiscal'!$D$6*2,IF(J15/2<='Barème fiscal'!$B$7,J15*'Barème fiscal'!$C$7-'Barème fiscal'!$D$7*2,J15*'Barème fiscal'!$C$8-'Barème fiscal'!$D$8*2)))))-MIN(MAX(IF(J15/2<='Barème fiscal'!$B$4,0,IF(J15/2<='Barème fiscal'!$B$5,J15*'Barème fiscal'!$C$5-'Barème fiscal'!$D$5*2,IF(J15/2<='Barème fiscal'!$B$6,J15*'Barème fiscal'!$C$6-'Barème fiscal'!$D$6*2,IF(J15/2<='Barème fiscal'!$B$7,J15*'Barème fiscal'!$C$7-'Barème fiscal'!$D$7*2,J15*'Barème fiscal'!$C$8-'Barème fiscal'!$D$8*2))))-MAX(0,IF(K15<='Barème fiscal'!$B$4,0,IF(K15<='Barème fiscal'!$B$5,J15*'Barème fiscal'!$C$5-'Barème fiscal'!$D$5*'Hypothèses'!$B$39,IF(K15<='Barème fiscal'!$B$6,J15*'Barème fiscal'!$C$6-'Barème fiscal'!$D$6*'Hypothèses'!$B$39,IF(K15<='Barème fiscal'!$B$7,J15*'Barème fiscal'!$C$7-'Barème fiscal'!$D$7*'Hypothèses'!$B$39,J15*'Barème fiscal'!$C$8-'Barème fiscal'!$D$8*'Hypothèses'!$B$39))))),0),MAX('Hypothèses'!$B$39-2,0)*2*'Barème fiscal'!$B$10) -> 11496.98 | O15: =MAX(0,I15)*'Hypothèses'!$B$40 -> 860 | P15: =N15+O15 -> 12356.98 | Q15: =B15+I15 -> 15601.54 | R15: =D15+E15 -> 6234.9813 | S15: =C15+F15 -> 10460.462 | T15: =Q15-R15-S15 -> -1093.903 | U15: =IF(T15>=0,0,IF(Q15>=R15,MAX(T15,-'Barème fiscal'!$B$11),MAX(-S15,-'Barème fiscal'!$B$11))) -> -1093.903 | V15: =IF(T15>=0,0,IF(Q15>=R15,MAX(0,-T15-'Barème fiscal'!$B$11),(R15-Q15)+MAX(0,S15-'Barème fiscal'!$B$11))) -> 0 | W15: =W14+V15-X14-AT15 -> 0 | X15: =IF(T15>0,MIN(W15,T15),0) -> 0 | Y15: =MAX(0,T15-X15) -> 0 | Z15: ='Hypothèses'!$B$50+Y15+U15-AW14 -> 84406.097 | AA15: =Z15/'Hypothèses'!$B$39 -> 33762.439 | AB15: =IF(AA15<='Barème fiscal'!$B$4,'Barème fiscal'!$C$4,IF(AA15<='Barème fiscal'!$B$5,'Barème fiscal'!$C$5,IF(AA15<='Barème fiscal'!$B$6,'Barème fiscal'!$C$6,IF(AA15<='Barème fiscal'!$B$7,'Barème fiscal'!$C$7,'Barème fiscal'!$C$8)))) -> 0.3 | AC15: =IF(Z15>0,AD15/Z15,0) -> 0.11575952 | AD15: =MAX(0,IF(Z15/2<='Barème fiscal'!$B$4,0,IF(Z15/2<='Barème fiscal'!$B$5,Z15*'Barème fiscal'!$C$5-'Barème fiscal'!$D$5*2,IF(Z15/2<='Barème fiscal'!$B$6,Z15*'Barème fiscal'!$C$6-'Barème fiscal'!$D$6*2,IF(Z15/2<='Barème fiscal'!$B$7,Z15*'Barème fiscal'!$C$7-'Barème fiscal'!$D$7*2,Z15*'Barème fiscal'!$C$8-'Barème fiscal'!$D$8*2)))))-MIN(MAX(IF(Z15/2<='Barème fiscal'!$B$4,0,IF(Z15/2<='Barème fiscal'!$B$5,Z15*'Barème fiscal'!$C$5-'Barème fiscal'!$D$5*2,IF(Z15/2<='Barème fiscal'!$B$6,Z15*'Barème fiscal'!$C$6-'Barème fiscal'!$D$6*2,IF(Z15/2<='Barème fiscal'!$B$7,Z15*'Barème fiscal'!$C$7-'Barème fiscal'!$D$7*2,Z15*'Barème fiscal'!$C$8-'Barème fiscal'!$D$8*2))))-MAX(0,IF(AA15<='Barème fiscal'!$B$4,0,IF(AA15<='Barème fiscal'!$B$5,Z15*'Barème fiscal'!$C$5-'Barème fiscal'!$D$5*'Hypothèses'!$B$39,IF(AA15<='Barème fiscal'!$B$6,Z15*'Barème fiscal'!$C$6-'Barème fiscal'!$D$6*'Hypothèses'!$B$39,IF(AA15<='Barème fiscal'!$B$7,Z15*'Barème fiscal'!$C$7-'Barème fiscal'!$D$7*'Hypothèses'!$B$39,Z15*'Barème fiscal'!$C$8-'Barème fiscal'!$D$8*'Hypothèses'!$B$39))))),0),MAX('Hypothèses'!$B$39-2,0)*2*'Barème fiscal'!$B$10) -> 9770.8091 | AE15: =Y15*'Hypothèses'!$B$40 -> 0 | AF15: =AD15+AE15 -> 9770.8091 | AG15: =P15-AF15 -> 2586.1709 | AH15: =H15-G15-AS15 -> 95481.313 | AI15: =(B15-'Tableau dAMT financier'!G27-C15+AG15)/12 -> -478.41874 | AK15: =AK14+AI15*12 -> -73211.489 | AL15: =AL14+F15 -> 87360 | AM15: =MAX(0,A15*'Hypothèses'!$B$31*'Hypothèses'!$B$32-AL15) -> 0 | AN15: =H15-('Hypothèses'!$B$4+MAX('Hypothèses'!$B$4*'Hypothèses'!$B$5,'Hypothèses'!$B$4*'Hypothèses'!$B$43)+IF(A15>5,'Hypothèses'!$B$4*'Hypothèses'!$B$44,0)-AL15) -> 28860 | AO15: =IF(A15<=5,0,IF(A15<=21,(A15-5)*0.06,1)) -> 0.42 | AP15: =MAX(0,AN15*(1-AO15)) -> 16738.8 | AQ15: =IF(A15<=5,0,IF(A15<=21,(A15-5)*0.0165,IF(A15=22,(21-5)*0.0165+0.016,IF(A15<=30,(21-5)*0.0165+0.016+(A15-22)*0.09,1)))) -> 0.1155 | AR15: =MAX(0,AN15*(1-AQ15)) -> 25526.67 | AS15: =IF(AN15<=0,0,AP15*'Hypothèses'!$B$45+AR15*'Hypothèses'!$B$46+IF(AP15<=50000,0,IF(AP15<=60000,AP15*0.02-(60000-AP15)/20,IF(AP15<=100000,AP15*0.02,IF(AP15<=110000,AP15*0.03-(110000-AP15)/10,IF(AP15<=150000,AP15*0.03,IF(AP15<=160000,AP15*0.04-(160000-AP15)*3/20,IF(AP15<=200000,AP15*0.04,IF(AP15<=210000,AP15*0.05-(210000-AP15)/5,IF(AP15<=250000,AP15*0.05,IF(AP15<=260000,AP15*0.06-(260000-AP15)/4,AP15*0.06))))))))))) -> 7570.9592 | AT15: =V4 -> 0 | AU15: =IFERROR(IRR(B71:N71),"") -> 0.022878801 | AV15: =MAX(0,I15)*'Barème fiscal'!$B$13 -> 340 | AW15: =Y15*'Barème fiscal'!$B$13 -> 0
A16: 13 | B16: =B15*(1+'Hypothèses'!$B$27) -> 10760.564 | C16: =B16*'Hypothèses'!$B$28 -> 3228.1691 | D16: ='Tableau dAMT financier'!E28 -> 5031.4505 | E16: ='Tableau dAMT financier'!F28 -> 884.8 | F16: =MIN('Hypothèses'!$B$34,MAX(0,'Hypothèses'!$B$31-AL15)) -> 7280 | G16: ='Tableau dAMT financier'!H28 -> 147115.7 | H16: =H15*(1+index) -> 260000 | I16: =I15*(1+index) -> 5000 | J16: ='Hypothèses'!$B$50+I16-AV15 -> 90160 | K16: =J16/'Hypothèses'!$B$39 -> 36064 | L16: =IF(K16<='Barème fiscal'!$B$4,'Barème fiscal'!$C$4,IF(K16<='Barème fiscal'!$B$5,'Barème fiscal'!$C$5,IF(K16<='Barème fiscal'!$B$6,'Barème fiscal'!$C$6,IF(K16<='Barème fiscal'!$B$7,'Barème fiscal'!$C$7,'Barème fiscal'!$C$8)))) -> 0.3 | M16: =IF(J16>0,N16/J16,0) -> 0.12751752 | N16: =MAX(0,IF(J16/2<='Barème fiscal'!$B$4,0,IF(J16/2<='Barème fiscal'!$B$5,J16*'Barème fiscal'!$C$5-'Barème fiscal'!$D$5*2,IF(J16/2<='Barème fiscal'!$B$6,J16*'Barème fiscal'!$C$6-'Barème fiscal'!$D$6*2,IF(J16/2<='Barème fiscal'!$B$7,J16*'Barème fiscal'!$C$7-'Barème fiscal'!$D$7*2,J16*'Barème fiscal'!$C$8-'Barème fiscal'!$D$8*2)))))-MIN(MAX(IF(J16/2<='Barème fiscal'!$B$4,0,IF(J16/2<='Barème fiscal'!$B$5,J16*'Barème fiscal'!$C$5-'Barème fiscal'!$D$5*2,IF(J16/2<='Barème fiscal'!$B$6,J16*'Barème fiscal'!$C$6-'Barème fiscal'!$D$6*2,IF(J16/2<='Barème fiscal'!$B$7,J16*'Barème fiscal'!$C$7-'Barème fiscal'!$D$7*2,J16*'Barème fiscal'!$C$8-'Barème fiscal'!$D$8*2))))-MAX(0,IF(K16<='Barème fiscal'!$B$4,0,IF(K16<='Barème fiscal'!$B$5,J16*'Barème fiscal'!$C$5-'Barème fiscal'!$D$5*'Hypothèses'!$B$39,IF(K16<='Barème fiscal'!$B$6,J16*'Barème fiscal'!$C$6-'Barème fiscal'!$D$6*'Hypothèses'!$B$39,IF(K16<='Barème fiscal'!$B$7,J16*'Barème fiscal'!$C$7-'Barème fiscal'!$D$7*'Hypothèses'!$B$39,J16*'Barème fiscal'!$C$8-'Barème fiscal'!$D$8*'Hypothèses'!$B$39))))),0),MAX('Hypothèses'!$B$39-2,0)*2*'Barème fiscal'!$B$10) -> 11496.98 | O16: =MAX(0,I16)*'Hypothèses'!$B$40 -> 860 | P16: =N16+O16 -> 12356.98 | Q16: =B16+I16 -> 15760.564 | R16: =D16+E16 -> 5916.2505 | S16: =C16+F16 -> 10508.169 | T16: =Q16-R16-S16 -> -663.85601 | U16: =IF(T16>=0,0,IF(Q16>=R16,MAX(T16,-'Barème fiscal'!$B$11),MAX(-S16,-'Barème fiscal'!$B$11))) -> -663.85601 | V16: =IF(T16>=0,0,IF(Q16>=R16,MAX(0,-T16-'Barème fiscal'!$B$11),(R16-Q16)+MAX(0,S16-'Barème fiscal'!$B$11))) -> 0 | W16: =W15+V16-X15-AT16 -> 0 | X16: =IF(T16>0,MIN(W16,T16),0) -> 0 | Y16: =MAX(0,T16-X16) -> 0 | Z16: ='Hypothèses'!$B$50+Y16+U16-AW15 -> 84836.144 | AA16: =Z16/'Hypothèses'!$B$39 -> 33934.458 | AB16: =IF(AA16<='Barème fiscal'!$B$4,'Barème fiscal'!$C$4,IF(AA16<='Barème fiscal'!$B$5,'Barème fiscal'!$C$5,IF(AA16<='Barème fiscal'!$B$6,'Barème fiscal'!$C$6,IF(AA16<='Barème fiscal'!$B$7,'Barème fiscal'!$C$7,'Barème fiscal'!$C$8)))) -> 0.3 | AC16: =IF(Z16>0,AD16/Z16,0) -> 0.11669346 | AD16: =MAX(0,IF(Z16/2<='Barème fiscal'!$B$4,0,IF(Z16/2<='Barème fiscal'!$B$5,Z16*'Barème fiscal'!$C$5-'Barème fiscal'!$D$5*2,IF(Z16/2<='Barème fiscal'!$B$6,Z16*'Barème fiscal'!$C$6-'Barème fiscal'!$D$6*2,IF(Z16/2<='Barème fiscal'!$B$7,Z16*'Barème fiscal'!$C$7-'Barème fiscal'!$D$7*2,Z16*'Barème fiscal'!$C$8-'Barème fiscal'!$D$8*2)))))-MIN(MAX(IF(Z16/2<='Barème fiscal'!$B$4,0,IF(Z16/2<='Barème fiscal'!$B$5,Z16*'Barème fiscal'!$C$5-'Barème fiscal'!$D$5*2,IF(Z16/2<='Barème fiscal'!$B$6,Z16*'Barème fiscal'!$C$6-'Barème fiscal'!$D$6*2,IF(Z16/2<='Barème fiscal'!$B$7,Z16*'Barème fiscal'!$C$7-'Barème fiscal'!$D$7*2,Z16*'Barème fiscal'!$C$8-'Barème fiscal'!$D$8*2))))-MAX(0,IF(AA16<='Barème fiscal'!$B$4,0,IF(AA16<='Barème fiscal'!$B$5,Z16*'Barème fiscal'!$C$5-'Barème fiscal'!$D$5*'Hypothèses'!$B$39,IF(AA16<='Barème fiscal'!$B$6,Z16*'Barème fiscal'!$C$6-'Barème fiscal'!$D$6*'Hypothèses'!$B$39,IF(AA16<='Barème fiscal'!$B$7,Z16*'Barème fiscal'!$C$7-'Barème fiscal'!$D$7*'Hypothèses'!$B$39,Z16*'Barème fiscal'!$C$8-'Barème fiscal'!$D$8*'Hypothèses'!$B$39))))),0),MAX('Hypothèses'!$B$39-2,0)*2*'Barème fiscal'!$B$10) -> 9899.8232 | AE16: =Y16*'Hypothèses'!$B$40 -> 0 | AF16: =AD16+AE16 -> 9899.8232 | AG16: =P16-AF16 -> 2457.1568 | AH16: =H16-G16-AS16 -> 103918.11 | AI16: =(B16-'Tableau dAMT financier'!G28-C16+AG16)/12 -> -479.89357 | AK16: =AK15+AI16*12 -> -78970.212 | AL16: =AL15+F16 -> 94640 | AM16: =MAX(0,A16*'Hypothèses'!$B$31*'Hypothèses'!$B$32-AL16) -> 0 | AN16: =H16-('Hypothèses'!$B$4+MAX('Hypothèses'!$B$4*'Hypothèses'!$B$5,'Hypothèses'!$B$4*'Hypothèses'!$B$43)+IF(A16>5,'Hypothèses'!$B$4*'Hypothèses'!$B$44,0)-AL16) -> 36140 | AO16: =IF(A16<=5,0,IF(A16<=21,(A16-5)*0.06,1)) -> 0.48 | AP16: =MAX(0,AN16*(1-AO16)) -> 18792.8 | AQ16: =IF(A16<=5,0,IF(A16<=21,(A16-5)*0.0165,IF(A16=22,(21-5)*0.0165+0.016,IF(A16<=30,(21-5)*0.0165+0.016+(A16-22)*0.09,1)))) -> 0.132 | AR16: =MAX(0,AN16*(1-AQ16)) -> 31369.52 | AS16: =IF(AN16<=0,0,AP16*'Hypothèses'!$B$45+AR16*'Hypothèses'!$B$46+IF(AP16<=50000,0,IF(AP16<=60000,AP16*0.02-(60000-AP16)/20,IF(AP16<=100000,AP16*0.02,IF(AP16<=110000,AP16*0.03-(110000-AP16)/10,IF(AP16<=150000,AP16*0.03,IF(AP16<=160000,AP16*0.04-(160000-AP16)*3/20,IF(AP16<=200000,AP16*0.04,IF(AP16<=210000,AP16*0.05-(210000-AP16)/5,IF(AP16<=250000,AP16*0.05,IF(AP16<=260000,AP16*0.06-(260000-AP16)/4,AP16*0.06))))))))))) -> 8966.1894 | AT16: =V5 -> 0 | AU16: =IFERROR(IRR(B72:O72),"") -> 0.023527228 | AV16: =MAX(0,I16)*'Barème fiscal'!$B$13 -> 340 | AW16: =Y16*'Barème fiscal'!$B$13 -> 0
A17: 14 | B17: =B16*(1+'Hypothèses'!$B$27) -> 10921.972 | C17: =B17*'Hypothèses'!$B$28 -> 3276.5916 | D17: ='Tableau dAMT financier'!E29 -> 4702.041 | E17: ='Tableau dAMT financier'!F29 -> 884.8 | F17: =MIN('Hypothèses'!$B$34,MAX(0,'Hypothèses'!$B$31-AL16)) -> 7280 | G17: ='Tableau dAMT financier'!H29 -> 136954.27 | H17: =H16*(1+index) -> 260000 | I17: =I16*(1+index) -> 5000 | J17: ='Hypothèses'!$B$50+I17-AV16 -> 90160 | K17: =J17/'Hypothèses'!$B$39 -> 36064 | L17: =IF(K17<='Barème fiscal'!$B$4,'Barème fiscal'!$C$4,IF(K17<='Barème fiscal'!$B$5,'Barème fiscal'!$C$5,IF(K17<='Barème fiscal'!$B$6,'Barème fiscal'!$C$6,IF(K17<='Barème fiscal'!$B$7,'Barème fiscal'!$C$7,'Barème fiscal'!$C$8)))) -> 0.3 | M17: =IF(J17>0,N17/J17,0) -> 0.12751752 | N17: =MAX(0,IF(J17/2<='Barème fiscal'!$B$4,0,IF(J17/2<='Barème fiscal'!$B$5,J17*'Barème fiscal'!$C$5-'Barème fiscal'!$D$5*2,IF(J17/2<='Barème fiscal'!$B$6,J17*'Barème fiscal'!$C$6-'Barème fiscal'!$D$6*2,IF(J17/2<='Barème fiscal'!$B$7,J17*'Barème fiscal'!$C$7-'Barème fiscal'!$D$7*2,J17*'Barème fiscal'!$C$8-'Barème fiscal'!$D$8*2)))))-MIN(MAX(IF(J17/2<='Barème fiscal'!$B$4,0,IF(J17/2<='Barème fiscal'!$B$5,J17*'Barème fiscal'!$C$5-'Barème fiscal'!$D$5*2,IF(J17/2<='Barème fiscal'!$B$6,J17*'Barème fiscal'!$C$6-'Barème fiscal'!$D$6*2,IF(J17/2<='Barème fiscal'!$B$7,J17*'Barème fiscal'!$C$7-'Barème fiscal'!$D$7*2,J17*'Barème fiscal'!$C$8-'Barème fiscal'!$D$8*2))))-MAX(0,IF(K17<='Barème fiscal'!$B$4,0,IF(K17<='Barème fiscal'!$B$5,J17*'Barème fiscal'!$C$5-'Barème fiscal'!$D$5*'Hypothèses'!$B$39,IF(K17<='Barème fiscal'!$B$6,J17*'Barème fiscal'!$C$6-'Barème fiscal'!$D$6*'Hypothèses'!$B$39,IF(K17<='Barème fiscal'!$B$7,J17*'Barème fiscal'!$C$7-'Barème fiscal'!$D$7*'Hypothèses'!$B$39,J17*'Barème fiscal'!$C$8-'Barème fiscal'!$D$8*'Hypothèses'!$B$39))))),0),MAX('Hypothèses'!$B$39-2,0)*2*'Barème fiscal'!$B$10) -> 11496.98 | O17: =MAX(0,I17)*'Hypothèses'!$B$40 -> 860 | P17: =N17+O17 -> 12356.98 | Q17: =B17+I17 -> 15921.972 | R17: =D17+E17 -> 5586.841 | S17: =C17+F17 -> 10556.592 | T17: =Q17-R17-S17 -> -221.46064 | U17: =IF(T17>=0,0,IF(Q17>=R17,MAX(T17,-'Barème fiscal'!$B$11),MAX(-S17,-'Barème fiscal'!$B$11))) -> -221.46064 | V17: =IF(T17>=0,0,IF(Q17>=R17,MAX(0,-T17-'Barème fiscal'!$B$11),(R17-Q17)+MAX(0,S17-'Barème fiscal'!$B$11))) -> 0 | W17: =W16+V17-X16-AT17 -> 0 | X17: =IF(T17>0,MIN(W17,T17),0) -> 0 | Y17: =MAX(0,T17-X17) -> 0 | Z17: ='Hypothèses'!$B$50+Y17+U17-AW16 -> 85278.539 | AA17: =Z17/'Hypothèses'!$B$39 -> 34111.416 | AB17: =IF(AA17<='Barème fiscal'!$B$4,'Barème fiscal'!$C$4,IF(AA17<='Barème fiscal'!$B$5,'Barème fiscal'!$C$5,IF(AA17<='Barème fiscal'!$B$6,'Barème fiscal'!$C$6,IF(AA17<='Barème fiscal'!$B$7,'Barème fiscal'!$C$7,'Barème fiscal'!$C$8)))) -> 0.3 | AC17: =IF(Z17>0,AD17/Z17,0) -> 0.11764439 | AD17: =MAX(0,IF(Z17/2<='Barème fiscal'!$B$4,0,IF(Z17/2<='Barème fiscal'!$B$5,Z17*'Barème fiscal'!$C$5-'Barème fiscal'!$D$5*2,IF(Z17/2<='Barème fiscal'!$B$6,Z17*'Barème fiscal'!$C$6-'Barème fiscal'!$D$6*2,IF(Z17/2<='Barème fiscal'!$B$7,Z17*'Barème fiscal'!$C$7-'Barème fiscal'!$D$7*2,Z17*'Barème fiscal'!$C$8-'Barème fiscal'!$D$8*2)))))-MIN(MAX(IF(Z17/2<='Barème fiscal'!$B$4,0,IF(Z17/2<='Barème fiscal'!$B$5,Z17*'Barème fiscal'!$C$5-'Barème fiscal'!$D$5*2,IF(Z17/2<='Barème fiscal'!$B$6,Z17*'Barème fiscal'!$C$6-'Barème fiscal'!$D$6*2,IF(Z17/2<='Barème fiscal'!$B$7,Z17*'Barème fiscal'!$C$7-'Barème fiscal'!$D$7*2,Z17*'Barème fiscal'!$C$8-'Barème fiscal'!$D$8*2))))-MAX(0,IF(AA17<='Barème fiscal'!$B$4,0,IF(AA17<='Barème fiscal'!$B$5,Z17*'Barème fiscal'!$C$5-'Barème fiscal'!$D$5*'Hypothèses'!$B$39,IF(AA17<='Barème fiscal'!$B$6,Z17*'Barème fiscal'!$C$6-'Barème fiscal'!$D$6*'Hypothèses'!$B$39,IF(AA17<='Barème fiscal'!$B$7,Z17*'Barème fiscal'!$C$7-'Barème fiscal'!$D$7*'Hypothèses'!$B$39,Z17*'Barème fiscal'!$C$8-'Barème fiscal'!$D$8*'Hypothèses'!$B$39))))),0),MAX('Hypothèses'!$B$39-2,0)*2*'Barème fiscal'!$B$10) -> 10032.542 | AE17: =Y17*'Hypothèses'!$B$40 -> 0 | AF17: =AD17+AE17 -> 10032.542 | AG17: =P17-AF17 -> 2324.4382 | AH17: =H17-G17-AS17 -> 112891.61 | AI17: =(B17-'Tableau dAMT financier'!G29-C17+AG17)/12 -> -481.53796 | AK17: =AK16+AI17*12 -> -84748.667 | AL17: =AL16+F17 -> 101920 | AM17: =MAX(0,A17*'Hypothèses'!$B$31*'Hypothèses'!$B$32-AL17) -> 0 | AN17: =H17-('Hypothèses'!$B$4+MAX('Hypothèses'!$B$4*'Hypothèses'!$B$5,'Hypothèses'!$B$4*'Hypothèses'!$B$43)+IF(A17>5,'Hypothèses'!$B$4*'Hypothèses'!$B$44,0)-AL17) -> 43420 | AO17: =IF(A17<=5,0,IF(A17<=21,(A17-5)*0.06,1)) -> 0.54 | AP17: =MAX(0,AN17*(1-AO17)) -> 19973.2 | AQ17: =IF(A17<=5,0,IF(A17<=21,(A17-5)*0.0165,IF(A17=22,(21-5)*0.0165+0.016,IF(A17<=30,(21-5)*0.0165+0.016+(A17-22)*0.09,1)))) -> 0.1485 | AR17: =MAX(0,AN17*(1-AQ17)) -> 36972.13 | AS17: =IF(AN17<=0,0,AP17*'Hypothèses'!$B$45+AR17*'Hypothèses'!$B$46+IF(AP17<=50000,0,IF(AP17<=60000,AP17*0.02-(60000-AP17)/20,IF(AP17<=100000,AP17*0.02,IF(AP17<=110000,AP17*0.03-(110000-AP17)/10,IF(AP17<=150000,AP17*0.03,IF(AP17<=160000,AP17*0.04-(160000-AP17)*3/20,IF(AP17<=200000,AP17*0.04,IF(AP17<=210000,AP17*0.05-(210000-AP17)/5,IF(AP17<=250000,AP17*0.05,IF(AP17<=260000,AP17*0.06-(260000-AP17)/4,AP17*0.06))))))))))) -> 10154.114 | AT17: =V6 -> 0 | AU17: =IFERROR(IRR(B73:P73),"") -> 0.024371272 | AV17: =MAX(0,I17)*'Barème fiscal'!$B$13 -> 340 | AW17: =Y17*'Barème fiscal'!$B$13 -> 0
A18: 15 | B18: =B17*(1+'Hypothèses'!$B$27) -> 11085.802 | C18: =B18*'Hypothèses'!$B$28 -> 3325.7405 | D18: ='Tableau dAMT financier'!E30 -> 4361.5951 | E18: ='Tableau dAMT financier'!F30 -> 884.8 | F18: =MIN('Hypothèses'!$B$34,MAX(0,'Hypothèses'!$B$31-AL17)) -> 7280 | G18: ='Tableau dAMT financier'!H30 -> 126452.39 | H18: =H17*(1+index) -> 260000 | I18: =I17*(1+index) -> 5000 | J18: ='Hypothèses'!$B$50+I18-AV17 -> 90160 | K18: =J18/'Hypothèses'!$B$39 -> 36064 | L18: =IF(K18<='Barème fiscal'!$B$4,'Barème fiscal'!$C$4,IF(K18<='Barème fiscal'!$B$5,'Barème fiscal'!$C$5,IF(K18<='Barème fiscal'!$B$6,'Barème fiscal'!$C$6,IF(K18<='Barème fiscal'!$B$7,'Barème fiscal'!$C$7,'Barème fiscal'!$C$8)))) -> 0.3 | M18: =IF(J18>0,N18/J18,0) -> 0.12751752 | N18: =MAX(0,IF(J18/2<='Barème fiscal'!$B$4,0,IF(J18/2<='Barème fiscal'!$B$5,J18*'Barème fiscal'!$C$5-'Barème fiscal'!$D$5*2,IF(J18/2<='Barème fiscal'!$B$6,J18*'Barème fiscal'!$C$6-'Barème fiscal'!$D$6*2,IF(J18/2<='Barème fiscal'!$B$7,J18*'Barème fiscal'!$C$7-'Barème fiscal'!$D$7*2,J18*'Barème fiscal'!$C$8-'Barème fiscal'!$D$8*2)))))-MIN(MAX(IF(J18/2<='Barème fiscal'!$B$4,0,IF(J18/2<='Barème fiscal'!$B$5,J18*'Barème fiscal'!$C$5-'Barème fiscal'!$D$5*2,IF(J18/2<='Barème fiscal'!$B$6,J18*'Barème fiscal'!$C$6-'Barème fiscal'!$D$6*2,IF(J18/2<='Barème fiscal'!$B$7,J18*'Barème fiscal'!$C$7-'Barème fiscal'!$D$7*2,J18*'Barème fiscal'!$C$8-'Barème fiscal'!$D$8*2))))-MAX(0,IF(K18<='Barème fiscal'!$B$4,0,IF(K18<='Barème fiscal'!$B$5,J18*'Barème fiscal'!$C$5-'Barème fiscal'!$D$5*'Hypothèses'!$B$39,IF(K18<='Barème fiscal'!$B$6,J18*'Barème fiscal'!$C$6-'Barème fiscal'!$D$6*'Hypothèses'!$B$39,IF(K18<='Barème fiscal'!$B$7,J18*'Barème fiscal'!$C$7-'Barème fiscal'!$D$7*'Hypothèses'!$B$39,J18*'Barème fiscal'!$C$8-'Barème fiscal'!$D$8*'Hypothèses'!$B$39))))),0),MAX('Hypothèses'!$B$39-2,0)*2*'Barème fiscal'!$B$10) -> 11496.98 | O18: =MAX(0,I18)*'Hypothèses'!$B$40 -> 860 | P18: =N18+O18 -> 12356.98 | Q18: =B18+I18 -> 16085.802 | R18: =D18+E18 -> 5246.3951 | S18: =C18+F18 -> 10605.74 | T18: =Q18-R18-S18 -> 233.66597 | U18: =IF(T18>=0,0,IF(Q18>=R18,MAX(T18,-'Barème fiscal'!$B$11),MAX(-S18,-'Barème fiscal'!$B$11))) -> 0 | V18: =IF(T18>=0,0,IF(Q18>=R18,MAX(0,-T18-'Barème fiscal'!$B$11),(R18-Q18)+MAX(0,S18-'Barème fiscal'!$B$11))) -> 0 | W18: =W17+V18-X17-AT18 -> 0 | X18: =IF(T18>0,MIN(W18,T18),0) -> 0 | Y18: =MAX(0,T18-X18) -> 233.66597 | Z18: ='Hypothèses'!$B$50+Y18+U18-AW17 -> 85733.666 | AA18: =Z18/'Hypothèses'!$B$39 -> 34293.466 | AB18: =IF(AA18<='Barème fiscal'!$B$4,'Barème fiscal'!$C$4,IF(AA18<='Barème fiscal'!$B$5,'Barème fiscal'!$C$5,IF(AA18<='Barème fiscal'!$B$6,'Barème fiscal'!$C$6,IF(AA18<='Barème fiscal'!$B$7,'Barème fiscal'!$C$7,'Barème fiscal'!$C$8)))) -> 0.3 | AC18: =IF(Z18>0,AD18/Z18,0) -> 0.11861245 | AD18: =MAX(0,IF(Z18/2<='Barème fiscal'!$B$4,0,IF(Z18/2<='Barème fiscal'!$B$5,Z18*'Barème fiscal'!$C$5-'Barème fiscal'!$D$5*2,IF(Z18/2<='Barème fiscal'!$B$6,Z18*'Barème fiscal'!$C$6-'Barème fiscal'!$D$6*2,IF(Z18/2<='Barème fiscal'!$B$7,Z18*'Barème fiscal'!$C$7-'Barème fiscal'!$D$7*2,Z18*'Barème fiscal'!$C$8-'Barème fiscal'!$D$8*2)))))-MIN(MAX(IF(Z18/2<='Barème fiscal'!$B$4,0,IF(Z18/2<='Barème fiscal'!$B$5,Z18*'Barème fiscal'!$C$5-'Barème fiscal'!$D$5*2,IF(Z18/2<='Barème fiscal'!$B$6,Z18*'Barème fiscal'!$C$6-'Barème fiscal'!$D$6*2,IF(Z18/2<='Barème fiscal'!$B$7,Z18*'Barème fiscal'!$C$7-'Barème fiscal'!$D$7*2,Z18*'Barème fiscal'!$C$8-'Barème fiscal'!$D$8*2))))-MAX(0,IF(AA18<='Barème fiscal'!$B$4,0,IF(AA18<='Barème fiscal'!$B$5,Z18*'Barème fiscal'!$C$5-'Barème fiscal'!$D$5*'Hypothèses'!$B$39,IF(AA18<='Barème fiscal'!$B$6,Z18*'Barème fiscal'!$C$6-'Barème fiscal'!$D$6*'Hypothèses'!$B$39,IF(AA18<='Barème fiscal'!$B$7,Z18*'Barème fiscal'!$C$7-'Barème fiscal'!$D$7*'Hypothèses'!$B$39,Z18*'Barème fiscal'!$C$8-'Barème fiscal'!$D$8*'Hypothèses'!$B$39))))),0),MAX('Hypothèses'!$B$39-2,0)*2*'Barème fiscal'!$B$10) -> 10169.08 | AE18: =Y18*'Hypothèses'!$B$40 -> 40.190546 | AF18: =AD18+AE18 -> 10209.27 | AG18: =P18-AF18 -> 2147.7097 | AH18: =H18-G18-AS18 -> 122412.87 | AI18: =(B18-'Tableau dAMT financier'!G30-C18+AG18)/12 -> -486.70861 | AK18: =AK17+AI18*12 -> -90589.17 | AL18: =AL17+F18 -> 109200 | AM18: =MAX(0,A18*'Hypothèses'!$B$31*'Hypothèses'!$B$32-AL18) -> 0 | AN18: =H18-('Hypothèses'!$B$4+MAX('Hypothèses'!$B$4*'Hypothèses'!$B$5,'Hypothèses'!$B$4*'Hypothèses'!$B$43)+IF(A18>5,'Hypothèses'!$B$4*'Hypothèses'!$B$44,0)-AL18) -> 50700 | AO18: =IF(A18<=5,0,IF(A18<=21,(A18-5)*0.06,1)) -> 0.6 | AP18: =MAX(0,AN18*(1-AO18)) -> 20280 | AQ18: =IF(A18<=5,0,IF(A18<=21,(A18-5)*0.0165,IF(A18=22,(21-5)*0.0165+0.016,IF(A18<=30,(21-5)*0.0165+0.016+(A18-22)*0.09,1)))) -> 0.165 | AR18: =MAX(0,AN18*(1-AQ18)) -> 42334.5 | AS18: =IF(AN18<=0,0,AP18*'Hypothèses'!$B$45+AR18*'Hypothèses'!$B$46+IF(AP18<=50000,0,IF(AP18<=60000,AP18*0.02-(60000-AP18)/20,IF(AP18<=100000,AP18*0.02,IF(AP18<=110000,AP18*0.03-(110000-AP18)/10,IF(AP18<=150000,AP18*0.03,IF(AP18<=160000,AP18*0.04-(160000-AP18)*3/20,IF(AP18<=200000,AP18*0.04,IF(AP18<=210000,AP18*0.05-(210000-AP18)/5,IF(AP18<=250000,AP18*0.05,IF(AP18<=260000,AP18*0.06-(260000-AP18)/4,AP18*0.06))))))))))) -> 11134.734 | AT18: =V7 -> 0 | AU18: =IFERROR(IRR(B74:Q74),"") -> 0.025272211 | AV18: =MAX(0,I18)*'Barème fiscal'!$B$13 -> 340 | AW18: =Y18*'Barème fiscal'!$B$13 -> 15.889286
A19: 16 | B19: =B18*(1+'Hypothèses'!$B$27) -> 11252.089 | C19: =B19*'Hypothèses'!$B$28 -> 3375.6266 | D19: ='Tableau dAMT financier'!E31 -> 4009.743 | E19: ='Tableau dAMT financier'!F31 -> 884.8 | F19: =MIN('Hypothèses'!$B$34,MAX(0,'Hypothèses'!$B$31-AL18)) -> 7280 | G19: ='Tableau dAMT financier'!H31 -> 115598.66 | H19: =H18*(1+index) -> 260000 | I19: =I18*(1+index) -> 5000 | J19: ='Hypothèses'!$B$50+I19-AV18 -> 90160 | K19: =J19/'Hypothèses'!$B$39 -> 36064 | L19: =IF(K19<='Barème fiscal'!$B$4,'Barème fiscal'!$C$4,IF(K19<='Barème fiscal'!$B$5,'Barème fiscal'!$C$5,IF(K19<='Barème fiscal'!$B$6,'Barème fiscal'!$C$6,IF(K19<='Barème fiscal'!$B$7,'Barème fiscal'!$C$7,'Barème fiscal'!$C$8)))) -> 0.3 | M19: =IF(J19>0,N19/J19,0) -> 0.12751752 | N19: =MAX(0,IF(J19/2<='Barème fiscal'!$B$4,0,IF(J19/2<='Barème fiscal'!$B$5,J19*'Barème fiscal'!$C$5-'Barème fiscal'!$D$5*2,IF(J19/2<='Barème fiscal'!$B$6,J19*'Barème fiscal'!$C$6-'Barème fiscal'!$D$6*2,IF(J19/2<='Barème fiscal'!$B$7,J19*'Barème fiscal'!$C$7-'Barème fiscal'!$D$7*2,J19*'Barème fiscal'!$C$8-'Barème fiscal'!$D$8*2)))))-MIN(MAX(IF(J19/2<='Barème fiscal'!$B$4,0,IF(J19/2<='Barème fiscal'!$B$5,J19*'Barème fiscal'!$C$5-'Barème fiscal'!$D$5*2,IF(J19/2<='Barème fiscal'!$B$6,J19*'Barème fiscal'!$C$6-'Barème fiscal'!$D$6*2,IF(J19/2<='Barème fiscal'!$B$7,J19*'Barème fiscal'!$C$7-'Barème fiscal'!$D$7*2,J19*'Barème fiscal'!$C$8-'Barème fiscal'!$D$8*2))))-MAX(0,IF(K19<='Barème fiscal'!$B$4,0,IF(K19<='Barème fiscal'!$B$5,J19*'Barème fiscal'!$C$5-'Barème fiscal'!$D$5*'Hypothèses'!$B$39,IF(K19<='Barème fiscal'!$B$6,J19*'Barème fiscal'!$C$6-'Barème fiscal'!$D$6*'Hypothèses'!$B$39,IF(K19<='Barème fiscal'!$B$7,J19*'Barème fiscal'!$C$7-'Barème fiscal'!$D$7*'Hypothèses'!$B$39,J19*'Barème fiscal'!$C$8-'Barème fiscal'!$D$8*'Hypothèses'!$B$39))))),0),MAX('Hypothèses'!$B$39-2,0)*2*'Barème fiscal'!$B$10) -> 11496.98 | O19: =MAX(0,I19)*'Hypothèses'!$B$40 -> 860 | P19: =N19+O19 -> 12356.98 | Q19: =B19+I19 -> 16252.089 | R19: =D19+E19 -> 4894.543 | S19: =C19+F19 -> 10655.627 | T19: =Q19-R19-S19 -> 701.91899 | U19: =IF(T19>=0,0,IF(Q19>=R19,MAX(T19,-'Barème fiscal'!$B$11),MAX(-S19,-'Barème fiscal'!$B$11))) -> 0 | V19: =IF(T19>=0,0,IF(Q19>=R19,MAX(0,-T19-'Barème fiscal'!$B$11),(R19-Q19)+MAX(0,S19-'Barème fiscal'!$B$11))) -> 0 | W19: =W18+V19-X18-AT19 -> 0 | X19: =IF(T19>0,MIN(W19,T19),0) -> 0 | Y19: =MAX(0,T19-X19) -> 701.91899 | Z19: ='Hypothèses'!$B$50+Y19+U19-AW18 -> 86186.03 | AA19: =Z19/'Hypothèses'!$B$39 -> 34474.412 | AB19: =IF(AA19<='Barème fiscal'!$B$4,'Barème fiscal'!$C$4,IF(AA19<='Barème fiscal'!$B$5,'Barème fiscal'!$C$5,IF(AA19<='Barème fiscal'!$B$6,'Barème fiscal'!$C$6,IF(AA19<='Barème fiscal'!$B$7,'Barème fiscal'!$C$7,'Barème fiscal'!$C$8)))) -> 0.3 | AC19: =IF(Z19>0,AD19/Z19,0) -> 0.11956449 | AD19: =MAX(0,IF(Z19/2<='Barème fiscal'!$B$4,0,IF(Z19/2<='Barème fiscal'!$B$5,Z19*'Barème fiscal'!$C$5-'Barème fiscal'!$D$5*2,IF(Z19/2<='Barème fiscal'!$B$6,Z19*'Barème fiscal'!$C$6-'Barème fiscal'!$D$6*2,IF(Z19/2<='Barème fiscal'!$B$7,Z19*'Barème fiscal'!$C$7-'Barème fiscal'!$D$7*2,Z19*'Barème fiscal'!$C$8-'Barème fiscal'!$D$8*2)))))-MIN(MAX(IF(Z19/2<='Barème fiscal'!$B$4,0,IF(Z19/2<='Barème fiscal'!$B$5,Z19*'Barème fiscal'!$C$5-'Barème fiscal'!$D$5*2,IF(Z19/2<='Barème fiscal'!$B$6,Z19*'Barème fiscal'!$C$6-'Barème fiscal'!$D$6*2,IF(Z19/2<='Barème fiscal'!$B$7,Z19*'Barème fiscal'!$C$7-'Barème fiscal'!$D$7*2,Z19*'Barème fiscal'!$C$8-'Barème fiscal'!$D$8*2))))-MAX(0,IF(AA19<='Barème fiscal'!$B$4,0,IF(AA19<='Barème fiscal'!$B$5,Z19*'Barème fiscal'!$C$5-'Barème fiscal'!$D$5*'Hypothèses'!$B$39,IF(AA19<='Barème fiscal'!$B$6,Z19*'Barème fiscal'!$C$6-'Barème fiscal'!$D$6*'Hypothèses'!$B$39,IF(AA19<='Barème fiscal'!$B$7,Z19*'Barème fiscal'!$C$7-'Barème fiscal'!$D$7*'Hypothèses'!$B$39,Z19*'Barème fiscal'!$C$8-'Barème fiscal'!$D$8*'Hypothèses'!$B$39))))),0),MAX('Hypothèses'!$B$39-2,0)*2*'Barème fiscal'!$B$10) -> 10304.789 | AE19: =Y19*'Hypothèses'!$B$40 -> 120.73007 | AF19: =AD19+AE19 -> 10425.519 | AG19: =P19-AF19 -> 1931.461 | AH19: =H19-G19-AS19 -> 132493.29 | AI19: =(B19-'Tableau dAMT financier'!G31-C19+AG19)/12 -> -495.02925 | AK19: =AK18+AI19*12 -> -96529.521 | AL19: =AL18+F19 -> 116480 | AM19: =MAX(0,A19*'Hypothèses'!$B$31*'Hypothèses'!$B$32-AL19) -> 0 | AN19: =H19-('Hypothèses'!$B$4+MAX('Hypothèses'!$B$4*'Hypothèses'!$B$5,'Hypothèses'!$B$4*'Hypothèses'!$B$43)+IF(A19>5,'Hypothèses'!$B$4*'Hypothèses'!$B$44,0)-AL19) -> 57980 | AO19: =IF(A19<=5,0,IF(A19<=21,(A19-5)*0.06,1)) -> 0.66 | AP19: =MAX(0,AN19*(1-AO19)) -> 19713.2 | AQ19: =IF(A19<=5,0,IF(A19<=21,(A19-5)*0.0165,IF(A19=22,(21-5)*0.0165+0.016,IF(A19<=30,(21-5)*0.0165+0.016+(A19-22)*0.09,1)))) -> 0.1815 | AR19: =MAX(0,AN19*(1-AQ19)) -> 47456.63 | AS19: =IF(AN19<=0,0,AP19*'Hypothèses'!$B$45+AR19*'Hypothèses'!$B$46+IF(AP19<=50000,0,IF(AP19<=60000,AP19*0.02-(60000-AP19)/20,IF(AP19<=100000,AP19*0.02,IF(AP19<=110000,AP19*0.03-(110000-AP19)/10,IF(AP19<=150000,AP19*0.03,IF(AP19<=160000,AP19*0.04-(160000-AP19)*3/20,IF(AP19<=200000,AP19*0.04,IF(AP19<=210000,AP19*0.05-(210000-AP19)/5,IF(AP19<=250000,AP19*0.05,IF(AP19<=260000,AP19*0.06-(260000-AP19)/4,AP19*0.06))))))))))) -> 11908.048 | AT19: =V8 -> 0 | AU19: =IFERROR(IRR(B75:R75),"") -> 0.026151095 | AV19: =MAX(0,I19)*'Barème fiscal'!$B$13 -> 340 | AW19: =Y19*'Barème fiscal'!$B$13 -> 47.730491
A20: 17 | B20: =B19*(1+'Hypothèses'!$B$27) -> 11420.87 | C20: =B20*'Hypothèses'!$B$28 -> 3426.261 | D20: ='Tableau dAMT financier'!E32 -> 3646.1026 | E20: ='Tableau dAMT financier'!F32 -> 884.8 | F20: =MIN('Hypothèses'!$B$34,MAX(0,'Hypothèses'!$B$31-AL19)) -> 7280 | G20: ='Tableau dAMT financier'!H32 -> 104381.29 | H20: =H19*(1+index) -> 260000 | I20: =I19*(1+index) -> 5000 | J20: ='Hypothèses'!$B$50+I20-AV19 -> 90160 | K20: =J20/'Hypothèses'!$B$39 -> 36064 | L20: =IF(K20<='Barème fiscal'!$B$4,'Barème fiscal'!$C$4,IF(K20<='Barème fiscal'!$B$5,'Barème fiscal'!$C$5,IF(K20<='Barème fiscal'!$B$6,'Barème fiscal'!$C$6,IF(K20<='Barème fiscal'!$B$7,'Barème fiscal'!$C$7,'Barème fiscal'!$C$8)))) -> 0.3 | M20: =IF(J20>0,N20/J20,0) -> 0.12751752 | N20: =MAX(0,IF(J20/2<='Barème fiscal'!$B$4,0,IF(J20/2<='Barème fiscal'!$B$5,J20*'Barème fiscal'!$C$5-'Barème fiscal'!$D$5*2,IF(J20/2<='Barème fiscal'!$B$6,J20*'Barème fiscal'!$C$6-'Barème fiscal'!$D$6*2,IF(J20/2<='Barème fiscal'!$B$7,J20*'Barème fiscal'!$C$7-'Barème fiscal'!$D$7*2,J20*'Barème fiscal'!$C$8-'Barème fiscal'!$D$8*2)))))-MIN(MAX(IF(J20/2<='Barème fiscal'!$B$4,0,IF(J20/2<='Barème fiscal'!$B$5,J20*'Barème fiscal'!$C$5-'Barème fiscal'!$D$5*2,IF(J20/2<='Barème fiscal'!$B$6,J20*'Barème fiscal'!$C$6-'Barème fiscal'!$D$6*2,IF(J20/2<='Barème fiscal'!$B$7,J20*'Barème fiscal'!$C$7-'Barème fiscal'!$D$7*2,J20*'Barème fiscal'!$C$8-'Barème fiscal'!$D$8*2))))-MAX(0,IF(K20<='Barème fiscal'!$B$4,0,IF(K20<='Barème fiscal'!$B$5,J20*'Barème fiscal'!$C$5-'Barème fiscal'!$D$5*'Hypothèses'!$B$39,IF(K20<='Barème fiscal'!$B$6,J20*'Barème fiscal'!$C$6-'Barème fiscal'!$D$6*'Hypothèses'!$B$39,IF(K20<='Barème fiscal'!$B$7,J20*'Barème fiscal'!$C$7-'Barème fiscal'!$D$7*'Hypothèses'!$B$39,J20*'Barème fiscal'!$C$8-'Barème fiscal'!$D$8*'Hypothèses'!$B$39))))),0),MAX('Hypothèses'!$B$39-2,0)*2*'Barème fiscal'!$B$10) -> 11496.98 | O20: =MAX(0,I20)*'Hypothèses'!$B$40 -> 860 | P20: =N20+O20 -> 12356.98 | Q20: =B20+I20 -> 16420.87 | R20: =D20+E20 -> 4530.9026 | S20: =C20+F20 -> 10706.261 | T20: =Q20-R20-S20 -> 1183.7064 | U20: =IF(T20>=0,0,IF(Q20>=R20,MAX(T20,-'Barème fiscal'!$B$11),MAX(-S20,-'Barème fiscal'!$B$11))) -> 0 | V20: =IF(T20>=0,0,IF(Q20>=R20,MAX(0,-T20-'Barème fiscal'!$B$11),(R20-Q20)+MAX(0,S20-'Barème fiscal'!$B$11))) -> 0 | W20: =W19+V20-X19-AT20 -> 0 | X20: =IF(T20>0,MIN(W20,T20),0) -> 0 | Y20: =MAX(0,T20-X20) -> 1183.7064 | Z20: ='Hypothèses'!$B$50+Y20+U20-AW19 -> 86635.976 | AA20: =Z20/'Hypothèses'!$B$39 -> 34654.39 | AB20: =IF(AA20<='Barème fiscal'!$B$4,'Barème fiscal'!$C$4,IF(AA20<='Barème fiscal'!$B$5,'Barème fiscal'!$C$5,IF(AA20<='Barème fiscal'!$B$6,'Barème fiscal'!$C$6,IF(AA20<='Barème fiscal'!$B$7,'Barème fiscal'!$C$7,'Barème fiscal'!$C$8)))) -> 0.3 | AC20: =IF(Z20>0,AD20/Z20,0) -> 0.12050159 | AD20: =MAX(0,IF(Z20/2<='Barème fiscal'!$B$4,0,IF(Z20/2<='Barème fiscal'!$B$5,Z20*'Barème fiscal'!$C$5-'Barème fiscal'!$D$5*2,IF(Z20/2<='Barème fiscal'!$B$6,Z20*'Barème fiscal'!$C$6-'Barème fiscal'!$D$6*2,IF(Z20/2<='Barème fiscal'!$B$7,Z20*'Barème fiscal'!$C$7-'Barème fiscal'!$D$7*2,Z20*'Barème fiscal'!$C$8-'Barème fiscal'!$D$8*2)))))-MIN(MAX(IF(Z20/2<='Barème fiscal'!$B$4,0,IF(Z20/2<='Barème fiscal'!$B$5,Z20*'Barème fiscal'!$C$5-'Barème fiscal'!$D$5*2,IF(Z20/2<='Barème fiscal'!$B$6,Z20*'Barème fiscal'!$C$6-'Barème fiscal'!$D$6*2,IF(Z20/2<='Barème fiscal'!$B$7,Z20*'Barème fiscal'!$C$7-'Barème fiscal'!$D$7*2,Z20*'Barème fiscal'!$C$8-'Barème fiscal'!$D$8*2))))-MAX(0,IF(AA20<='Barème fiscal'!$B$4,0,IF(AA20<='Barème fiscal'!$B$5,Z20*'Barème fiscal'!$C$5-'Barème fiscal'!$D$5*'Hypothèses'!$B$39,IF(AA20<='Barème fiscal'!$B$6,Z20*'Barème fiscal'!$C$6-'Barème fiscal'!$D$6*'Hypothèses'!$B$39,IF(AA20<='Barème fiscal'!$B$7,Z20*'Barème fiscal'!$C$7-'Barème fiscal'!$D$7*'Hypothèses'!$B$39,Z20*'Barème fiscal'!$C$8-'Barème fiscal'!$D$8*'Hypothèses'!$B$39))))),0),MAX('Hypothèses'!$B$39-2,0)*2*'Barème fiscal'!$B$10) -> 10439.773 | AE20: =Y20*'Hypothèses'!$B$40 -> 203.5975 | AF20: =AD20+AE20 -> 10643.37 | AG20: =P20-AF20 -> 1713.6097 | AH20: =H20-G20-AS20 -> 143144.65 | AI20: =(B20-'Tableau dAMT financier'!G32-C20+AG20)/12 -> -503.33795 | AK20: =AK19+AI20*12 -> -102569.58 | AL20: =AL19+F20 -> 123760 | AM20: =MAX(0,A20*'Hypothèses'!$B$31*'Hypothèses'!$B$32-AL20) -> 0 | AN20: =H20-('Hypothèses'!$B$4+MAX('Hypothèses'!$B$4*'Hypothèses'!$B$5,'Hypothèses'!$B$4*'Hypothèses'!$B$43)+IF(A20>5,'Hypothèses'!$B$4*'Hypothèses'!$B$44,0)-AL20) -> 65260 | AO20: =IF(A20<=5,0,IF(A20<=21,(A20-5)*0.06,1)) -> 0.72 | AP20: =MAX(0,AN20*(1-AO20)) -> 18272.8 | AQ20: =IF(A20<=5,0,IF(A20<=21,(A20-5)*0.0165,IF(A20=22,(21-5)*0.0165+0.016,IF(A20<=30,(21-5)*0.0165+0.016+(A20-22)*0.09,1)))) -> 0.198 | AR20: =MAX(0,AN20*(1-AQ20)) -> 52338.52 | AS20: =IF(AN20<=0,0,AP20*'Hypothèses'!$B$45+AR20*'Hypothèses'!$B$46+IF(AP20<=50000,0,IF(AP20<=60000,AP20*0.02-(60000-AP20)/20,IF(AP20<=100000,AP20*0.02,IF(AP20<=110000,AP20*0.03-(110000-AP20)/10,IF(AP20<=150000,AP20*0.03,IF(AP20<=160000,AP20*0.04-(160000-AP20)*3/20,IF(AP20<=200000,AP20*0.04,IF(AP20<=210000,AP20*0.05-(210000-AP20)/5,IF(AP20<=250000,AP20*0.05,IF(AP20<=260000,AP20*0.06-(260000-AP20)/4,AP20*0.06))))))))))) -> 12474.057 | AT20: =V9 -> 0 | AU20: =IFERROR(IRR(B76:S76),"") -> 0.026989952 | AV20: =MAX(0,I20)*'Barème fiscal'!$B$13 -> 340 | AW20: =Y20*'Barème fiscal'!$B$13 -> 80.492034
A21: 18 | B21: =B20*(1+'Hypothèses'!$B$27) -> 11592.183 | C21: =B21*'Hypothèses'!$B$28 -> 3477.6549 | D21: ='Tableau dAMT financier'!E33 -> 3270.2788 | E21: ='Tableau dAMT financier'!F33 -> 884.8 | F21: =MIN('Hypothèses'!$B$34,MAX(0,'Hypothèses'!$B$31-AL20)) -> 7280 | G21: ='Tableau dAMT financier'!H33 -> 92788.094 | H21: =H20*(1+index) -> 260000 | I21: =I20*(1+index) -> 5000 | J21: ='Hypothèses'!$B$50+I21-AV20 -> 90160 | K21: =J21/'Hypothèses'!$B$39 -> 36064 | L21: =IF(K21<='Barème fiscal'!$B$4,'Barème fiscal'!$C$4,IF(K21<='Barème fiscal'!$B$5,'Barème fiscal'!$C$5,IF(K21<='Barème fiscal'!$B$6,'Barème fiscal'!$C$6,IF(K21<='Barème fiscal'!$B$7,'Barème fiscal'!$C$7,'Barème fiscal'!$C$8)))) -> 0.3 | M21: =IF(J21>0,N21/J21,0) -> 0.12751752 | N21: =MAX(0,IF(J21/2<='Barème fiscal'!$B$4,0,IF(J21/2<='Barème fiscal'!$B$5,J21*'Barème fiscal'!$C$5-'Barème fiscal'!$D$5*2,IF(J21/2<='Barème fiscal'!$B$6,J21*'Barème fiscal'!$C$6-'Barème fiscal'!$D$6*2,IF(J21/2<='Barème fiscal'!$B$7,J21*'Barème fiscal'!$C$7-'Barème fiscal'!$D$7*2,J21*'Barème fiscal'!$C$8-'Barème fiscal'!$D$8*2)))))-MIN(MAX(IF(J21/2<='Barème fiscal'!$B$4,0,IF(J21/2<='Barème fiscal'!$B$5,J21*'Barème fiscal'!$C$5-'Barème fiscal'!$D$5*2,IF(J21/2<='Barème fiscal'!$B$6,J21*'Barème fiscal'!$C$6-'Barème fiscal'!$D$6*2,IF(J21/2<='Barème fiscal'!$B$7,J21*'Barème fiscal'!$C$7-'Barème fiscal'!$D$7*2,J21*'Barème fiscal'!$C$8-'Barème fiscal'!$D$8*2))))-MAX(0,IF(K21<='Barème fiscal'!$B$4,0,IF(K21<='Barème fiscal'!$B$5,J21*'Barème fiscal'!$C$5-'Barème fiscal'!$D$5*'Hypothèses'!$B$39,IF(K21<='Barème fiscal'!$B$6,J21*'Barème fiscal'!$C$6-'Barème fiscal'!$D$6*'Hypothèses'!$B$39,IF(K21<='Barème fiscal'!$B$7,J21*'Barème fiscal'!$C$7-'Barème fiscal'!$D$7*'Hypothèses'!$B$39,J21*'Barème fiscal'!$C$8-'Barème fiscal'!$D$8*'Hypothèses'!$B$39))))),0),MAX('Hypothèses'!$B$39-2,0)*2*'Barème fiscal'!$B$10) -> 11496.98 | O21: =MAX(0,I21)*'Hypothèses'!$B$40 -> 860 | P21: =N21+O21 -> 12356.98 | Q21: =B21+I21 -> 16592.183 | R21: =D21+E21 -> 4155.0788 | S21: =C21+F21 -> 10757.655 | T21: =Q21-R21-S21 -> 1679.4493 | U21: =IF(T21>=0,0,IF(Q21>=R21,MAX(T21,-'Barème fiscal'!$B$11),MAX(-S21,-'Barème fiscal'!$B$11))) -> 0 | V21: =IF(T21>=0,0,IF(Q21>=R21,MAX(0,-T21-'Barème fiscal'!$B$11),(R21-Q21)+MAX(0,S21-'Barème fiscal'!$B$11))) -> 0 | W21: =W20+V21-X20-AT21 -> 0 | X21: =IF(T21>0,MIN(W21,T21),0) -> 0 | Y21: =MAX(0,T21-X21) -> 1679.4493 | Z21: ='Hypothèses'!$B$50+Y21+U21-AW20 -> 87098.957 | AA21: =Z21/'Hypothèses'!$B$39 -> 34839.583 | AB21: =IF(AA21<='Barème fiscal'!$B$4,'Barème fiscal'!$C$4,IF(AA21<='Barème fiscal'!$B$5,'Barème fiscal'!$C$5,IF(AA21<='Barème fiscal'!$B$6,'Barème fiscal'!$C$6,IF(AA21<='Barème fiscal'!$B$7,'Barème fiscal'!$C$7,'Barème fiscal'!$C$8)))) -> 0.3 | AC21: =IF(Z21>0,AD21/Z21,0) -> 0.12145573 | AD21: =MAX(0,IF(Z21/2<='Barème fiscal'!$B$4,0,IF(Z21/2<='Barème fiscal'!$B$5,Z21*'Barème fiscal'!$C$5-'Barème fiscal'!$D$5*2,IF(Z21/2<='Barème fiscal'!$B$6,Z21*'Barème fiscal'!$C$6-'Barème fiscal'!$D$6*2,IF(Z21/2<='Barème fiscal'!$B$7,Z21*'Barème fiscal'!$C$7-'Barème fiscal'!$D$7*2,Z21*'Barème fiscal'!$C$8-'Barème fiscal'!$D$8*2)))))-MIN(MAX(IF(Z21/2<='Barème fiscal'!$B$4,0,IF(Z21/2<='Barème fiscal'!$B$5,Z21*'Barème fiscal'!$C$5-'Barème fiscal'!$D$5*2,IF(Z21/2<='Barème fiscal'!$B$6,Z21*'Barème fiscal'!$C$6-'Barème fiscal'!$D$6*2,IF(Z21/2<='Barème fiscal'!$B$7,Z21*'Barème fiscal'!$C$7-'Barème fiscal'!$D$7*2,Z21*'Barème fiscal'!$C$8-'Barème fiscal'!$D$8*2))))-MAX(0,IF(AA21<='Barème fiscal'!$B$4,0,IF(AA21<='Barème fiscal'!$B$5,Z21*'Barème fiscal'!$C$5-'Barème fiscal'!$D$5*'Hypothèses'!$B$39,IF(AA21<='Barème fiscal'!$B$6,Z21*'Barème fiscal'!$C$6-'Barème fiscal'!$D$6*'Hypothèses'!$B$39,IF(AA21<='Barème fiscal'!$B$7,Z21*'Barème fiscal'!$C$7-'Barème fiscal'!$D$7*'Hypothèses'!$B$39,Z21*'Barème fiscal'!$C$8-'Barème fiscal'!$D$8*'Hypothèses'!$B$39))))),0),MAX('Hypothèses'!$B$39-2,0)*2*'Barème fiscal'!$B$10) -> 10578.667 | AE21: =Y21*'Hypothèses'!$B$40 -> 288.86528 | AF21: =AD21+AE21 -> 10867.532 | AG21: =P21-AF21 -> 1489.4475 | AH21: =H21-G21-AS21 -> 154379.14 | AI21: =(B21-'Tableau dAMT financier'!G33-C21+AG21)/12 -> -512.02487 | AK21: =AK20+AI21*12 -> -108713.88 | AL21: =AL20+F21 -> 131040 | AM21: =MAX(0,A21*'Hypothèses'!$B$31*'Hypothèses'!$B$32-AL21) -> 0 | AN21: =H21-('Hypothèses'!$B$4+MAX('Hypothèses'!$B$4*'Hypothèses'!$B$5,'Hypothèses'!$B$4*'Hypothèses'!$B$43)+IF(A21>5,'Hypothèses'!$B$4*'Hypothèses'!$B$44,0)-AL21) -> 72540 | AO21: =IF(A21<=5,0,IF(A21<=21,(A21-5)*0.06,1)) -> 0.78 | AP21: =MAX(0,AN21*(1-AO21)) -> 15958.8 | AQ21: =IF(A21<=5,0,IF(A21<=21,(A21-5)*0.0165,IF(A21=22,(21-5)*0.0165+0.016,IF(A21<=30,(21-5)*0.0165+0.016+(A21-22)*0.09,1)))) -> 0.2145 | AR21: =MAX(0,AN21*(1-AQ21)) -> 56980.17 | AS21: =IF(AN21<=0,0,AP21*'Hypothèses'!$B$45+AR21*'Hypothèses'!$B$46+IF(AP21<=50000,0,IF(AP21<=60000,AP21*0.02-(60000-AP21)/20,IF(AP21<=100000,AP21*0.02,IF(AP21<=110000,AP21*0.03-(110000-AP21)/10,IF(AP21<=150000,AP21*0.03,IF(AP21<=160000,AP21*0.04-(160000-AP21)*3/20,IF(AP21<=200000,AP21*0.04,IF(AP21<=210000,AP21*0.05-(210000-AP21)/5,IF(AP21<=250000,AP21*0.05,IF(AP21<=260000,AP21*0.06-(260000-AP21)/4,AP21*0.06))))))))))) -> 12832.761 | AT21: =V10 -> 0 | AU21: =IFERROR(IRR(B77:T77),"") -> 0.02777579 | AV21: =MAX(0,I21)*'Barème fiscal'!$B$13 -> 340 | AW21: =Y21*'Barème fiscal'!$B$13 -> 114.20255
A22: 19 | B22: =B21*(1+'Hypothèses'!$B$27) -> 11766.066 | C22: =B22*'Hypothèses'!$B$28 -> 3529.8197 | D22: ='Tableau dAMT financier'!E34 -> 2881.8635 | E22: ='Tableau dAMT financier'!F34 -> 884.8 | F22: =MIN('Hypothèses'!$B$34,MAX(0,'Hypothèses'!$B$31-AL21)) -> 7280 | G22: ='Tableau dAMT financier'!H34 -> 80806.484 | H22: =H21*(1+index) -> 260000 | I22: =I21*(1+index) -> 5000 | J22: ='Hypothèses'!$B$50+I22-AV21 -> 90160 | K22: =J22/'Hypothèses'!$B$39 -> 36064 | L22: =IF(K22<='Barème fiscal'!$B$4,'Barème fiscal'!$C$4,IF(K22<='Barème fiscal'!$B$5,'Barème fiscal'!$C$5,IF(K22<='Barème fiscal'!$B$6,'Barème fiscal'!$C$6,IF(K22<='Barème fiscal'!$B$7,'Barème fiscal'!$C$7,'Barème fiscal'!$C$8)))) -> 0.3 | M22: =IF(J22>0,N22/J22,0) -> 0.12751752 | N22: =MAX(0,IF(J22/2<='Barème fiscal'!$B$4,0,IF(J22/2<='Barème fiscal'!$B$5,J22*'Barème fiscal'!$C$5-'Barème fiscal'!$D$5*2,IF(J22/2<='Barème fiscal'!$B$6,J22*'Barème fiscal'!$C$6-'Barème fiscal'!$D$6*2,IF(J22/2<='Barème fiscal'!$B$7,J22*'Barème fiscal'!$C$7-'Barème fiscal'!$D$7*2,J22*'Barème fiscal'!$C$8-'Barème fiscal'!$D$8*2)))))-MIN(MAX(IF(J22/2<='Barème fiscal'!$B$4,0,IF(J22/2<='Barème fiscal'!$B$5,J22*'Barème fiscal'!$C$5-'Barème fiscal'!$D$5*2,IF(J22/2<='Barème fiscal'!$B$6,J22*'Barème fiscal'!$C$6-'Barème fiscal'!$D$6*2,IF(J22/2<='Barème fiscal'!$B$7,J22*'Barème fiscal'!$C$7-'Barème fiscal'!$D$7*2,J22*'Barème fiscal'!$C$8-'Barème fiscal'!$D$8*2))))-MAX(0,IF(K22<='Barème fiscal'!$B$4,0,IF(K22<='Barème fiscal'!$B$5,J22*'Barème fiscal'!$C$5-'Barème fiscal'!$D$5*'Hypothèses'!$B$39,IF(K22<='Barème fiscal'!$B$6,J22*'Barème fiscal'!$C$6-'Barème fiscal'!$D$6*'Hypothèses'!$B$39,IF(K22<='Barème fiscal'!$B$7,J22*'Barème fiscal'!$C$7-'Barème fiscal'!$D$7*'Hypothèses'!$B$39,J22*'Barème fiscal'!$C$8-'Barème fiscal'!$D$8*'Hypothèses'!$B$39))))),0),MAX('Hypothèses'!$B$39-2,0)*2*'Barème fiscal'!$B$10) -> 11496.98 | O22: =MAX(0,I22)*'Hypothèses'!$B$40 -> 860 | P22: =N22+O22 -> 12356.98 | Q22: =B22+I22 -> 16766.066 | R22: =D22+E22 -> 3766.6635 | S22: =C22+F22 -> 10809.82 | T22: =Q22-R22-S22 -> 2189.5825 | U22: =IF(T22>=0,0,IF(Q22>=R22,MAX(T22,-'Barème fiscal'!$B$11),MAX(-S22,-'Barème fiscal'!$B$11))) -> 0 | V22: =IF(T22>=0,0,IF(Q22>=R22,MAX(0,-T22-'Barème fiscal'!$B$11),(R22-Q22)+MAX(0,S22-'Barème fiscal'!$B$11))) -> 0 | W22: =W21+V22-X21-AT22 -> 0 | X22: =IF(T22>0,MIN(W22,T22),0) -> 0 | Y22: =MAX(0,T22-X22) -> 2189.5825 | Z22: ='Hypothèses'!$B$50+Y22+U22-AW21 -> 87575.38 | AA22: =Z22/'Hypothèses'!$B$39 -> 35030.152 | AB22: =IF(AA22<='Barème fiscal'!$B$4,'Barème fiscal'!$C$4,IF(AA22<='Barème fiscal'!$B$5,'Barème fiscal'!$C$5,IF(AA22<='Barème fiscal'!$B$6,'Barème fiscal'!$C$6,IF(AA22<='Barème fiscal'!$B$7,'Barème fiscal'!$C$7,'Barème fiscal'!$C$8)))) -> 0.3 | AC22: =IF(Z22>0,AD22/Z22,0) -> 0.12242703 | AD22: =MAX(0,IF(Z22/2<='Barème fiscal'!$B$4,0,IF(Z22/2<='Barème fiscal'!$B$5,Z22*'Barème fiscal'!$C$5-'Barème fiscal'!$D$5*2,IF(Z22/2<='Barème fiscal'!$B$6,Z22*'Barème fiscal'!$C$6-'Barème fiscal'!$D$6*2,IF(Z22/2<='Barème fiscal'!$B$7,Z22*'Barème fiscal'!$C$7-'Barème fiscal'!$D$7*2,Z22*'Barème fiscal'!$C$8-'Barème fiscal'!$D$8*2)))))-MIN(MAX(IF(Z22/2<='Barème fiscal'!$B$4,0,IF(Z22/2<='Barème fiscal'!$B$5,Z22*'Barème fiscal'!$C$5-'Barème fiscal'!$D$5*2,IF(Z22/2<='Barème fiscal'!$B$6,Z22*'Barème fiscal'!$C$6-'Barème fiscal'!$D$6*2,IF(Z22/2<='Barème fiscal'!$B$7,Z22*'Barème fiscal'!$C$7-'Barème fiscal'!$D$7*2,Z22*'Barème fiscal'!$C$8-'Barème fiscal'!$D$8*2))))-MAX(0,IF(AA22<='Barème fiscal'!$B$4,0,IF(AA22<='Barème fiscal'!$B$5,Z22*'Barème fiscal'!$C$5-'Barème fiscal'!$D$5*'Hypothèses'!$B$39,IF(AA22<='Barème fiscal'!$B$6,Z22*'Barème fiscal'!$C$6-'Barème fiscal'!$D$6*'Hypothèses'!$B$39,IF(AA22<='Barème fiscal'!$B$7,Z22*'Barème fiscal'!$C$7-'Barème fiscal'!$D$7*'Hypothèses'!$B$39,Z22*'Barème fiscal'!$C$8-'Barème fiscal'!$D$8*'Hypothèses'!$B$39))))),0),MAX('Hypothèses'!$B$39-2,0)*2*'Barème fiscal'!$B$10) -> 10721.594 | AE22: =Y22*'Hypothèses'!$B$40 -> 376.60819 | AF22: =AD22+AE22 -> 11098.202 | AG22: =P22-AF22 -> 1258.7778 | AH22: =H22-G22-AS22 -> 166209.36 | AI22: =(B22-'Tableau dAMT financier'!G34-C22+AG22)/12 -> -521.10419 | AK22: =AK21+AI22*12 -> -114967.13 | AL22: =AL21+F22 -> 138320 | AM22: =MAX(0,A22*'Hypothèses'!$B$31*'Hypothèses'!$B$32-AL22) -> 0 | AN22: =H22-('Hypothèses'!$B$4+MAX('Hypothèses'!$B$4*'Hypothèses'!$B$5,'Hypothèses'!$B$4*'Hypothèses'!$B$43)+IF(A22>5,'Hypothèses'!$B$4*'Hypothèses'!$B$44,0)-AL22) -> 79820 | AO22: =IF(A22<=5,0,IF(A22<=21,(A22-5)*0.06,1)) -> 0.84 | AP22: =MAX(0,AN22*(1-AO22)) -> 12771.2 | AQ22: =IF(A22<=5,0,IF(A22<=21,(A22-5)*0.0165,IF(A22=22,(21-5)*0.0165+0.016,IF(A22<=30,(21-5)*0.0165+0.016+(A22-22)*0.09,1)))) -> 0.231 | AR22: =MAX(0,AN22*(1-AQ22)) -> 61381.58 | AS22: =IF(AN22<=0,0,AP22*'Hypothèses'!$B$45+AR22*'Hypothèses'!$B$46+IF(AP22<=50000,0,IF(AP22<=60000,AP22*0.02-(60000-AP22)/20,IF(AP22<=100000,AP22*0.02,IF(AP22<=110000,AP22*0.03-(110000-AP22)/10,IF(AP22<=150000,AP22*0.03,IF(AP22<=160000,AP22*0.04-(160000-AP22)*3/20,IF(AP22<=200000,AP22*0.04,IF(AP22<=210000,AP22*0.05-(210000-AP22)/5,IF(AP22<=250000,AP22*0.05,IF(AP22<=260000,AP22*0.06-(260000-AP22)/4,AP22*0.06))))))))))) -> 12984.16 | AT22: =V11 -> 0 | AU22: =IFERROR(IRR(B78:U78),"") -> 0.02850202 | AV22: =MAX(0,I22)*'Barème fiscal'!$B$13 -> 340 | AW22: =Y22*'Barème fiscal'!$B$13 -> 148.89161
A23: 20 | B23: =B22*(1+'Hypothèses'!$B$27) -> 11942.557 | C23: =B23*'Hypothèses'!$B$28 -> 3582.767 | D23: ='Tableau dAMT financier'!E35 -> 2480.4349 | E23: ='Tableau dAMT financier'!F35 -> 884.8 | F23: =MIN('Hypothèses'!$B$34,MAX(0,'Hypothèses'!$B$31-AL22)) -> 7280 | G23: ='Tableau dAMT financier'!H35 -> 68423.445 | H23: =H22*(1+index) -> 260000 | I23: =I22*(1+index) -> 5000 | J23: ='Hypothèses'!$B$50+I23-AV22 -> 90160 | K23: =J23/'Hypothèses'!$B$39 -> 36064 | L23: =IF(K23<='Barème fiscal'!$B$4,'Barème fiscal'!$C$4,IF(K23<='Barème fiscal'!$B$5,'Barème fiscal'!$C$5,IF(K23<='Barème fiscal'!$B$6,'Barème fiscal'!$C$6,IF(K23<='Barème fiscal'!$B$7,'Barème fiscal'!$C$7,'Barème fiscal'!$C$8)))) -> 0.3 | M23: =IF(J23>0,N23/J23,0) -> 0.12751752 | N23: =MAX(0,IF(J23/2<='Barème fiscal'!$B$4,0,IF(J23/2<='Barème fiscal'!$B$5,J23*'Barème fiscal'!$C$5-'Barème fiscal'!$D$5*2,IF(J23/2<='Barème fiscal'!$B$6,J23*'Barème fiscal'!$C$6-'Barème fiscal'!$D$6*2,IF(J23/2<='Barème fiscal'!$B$7,J23*'Barème fiscal'!$C$7-'Barème fiscal'!$D$7*2,J23*'Barème fiscal'!$C$8-'Barème fiscal'!$D$8*2)))))-MIN(MAX(IF(J23/2<='Barème fiscal'!$B$4,0,IF(J23/2<='Barème fiscal'!$B$5,J23*'Barème fiscal'!$C$5-'Barème fiscal'!$D$5*2,IF(J23/2<='Barème fiscal'!$B$6,J23*'Barème fiscal'!$C$6-'Barème fiscal'!$D$6*2,IF(J23/2<='Barème fiscal'!$B$7,J23*'Barème fiscal'!$C$7-'Barème fiscal'!$D$7*2,J23*'Barème fiscal'!$C$8-'Barème fiscal'!$D$8*2))))-MAX(0,IF(K23<='Barème fiscal'!$B$4,0,IF(K23<='Barème fiscal'!$B$5,J23*'Barème fiscal'!$C$5-'Barème fiscal'!$D$5*'Hypothèses'!$B$39,IF(K23<='Barème fiscal'!$B$6,J23*'Barème fiscal'!$C$6-'Barème fiscal'!$D$6*'Hypothèses'!$B$39,IF(K23<='Barème fiscal'!$B$7,J23*'Barème fiscal'!$C$7-'Barème fiscal'!$D$7*'Hypothèses'!$B$39,J23*'Barème fiscal'!$C$8-'Barème fiscal'!$D$8*'Hypothèses'!$B$39))))),0),MAX('Hypothèses'!$B$39-2,0)*2*'Barème fiscal'!$B$10) -> 11496.98 | O23: =MAX(0,I23)*'Hypothèses'!$B$40 -> 860 | P23: =N23+O23 -> 12356.98 | Q23: =B23+I23 -> 16942.557 | R23: =D23+E23 -> 3365.2349 | S23: =C23+F23 -> 10862.767 | T23: =Q23-R23-S23 -> 2714.5548 | U23: =IF(T23>=0,0,IF(Q23>=R23,MAX(T23,-'Barème fiscal'!$B$11),MAX(-S23,-'Barème fiscal'!$B$11))) -> 0 | V23: =IF(T23>=0,0,IF(Q23>=R23,MAX(0,-T23-'Barème fiscal'!$B$11),(R23-Q23)+MAX(0,S23-'Barème fiscal'!$B$11))) -> 0 | W23: =W22+V23-X22-AT23 -> 0 | X23: =IF(T23>0,MIN(W23,T23),0) -> 0 | Y23: =MAX(0,T23-X23) -> 2714.5548 | Z23: ='Hypothèses'!$B$50+Y23+U23-AW22 -> 88065.663 | AA23: =Z23/'Hypothèses'!$B$39 -> 35226.265 | AB23: =IF(AA23<='Barème fiscal'!$B$4,'Barème fiscal'!$C$4,IF(AA23<='Barème fiscal'!$B$5,'Barème fiscal'!$C$5,IF(AA23<='Barème fiscal'!$B$6,'Barème fiscal'!$C$6,IF(AA23<='Barème fiscal'!$B$7,'Barème fiscal'!$C$7,'Barème fiscal'!$C$8)))) -> 0.3 | AC23: =IF(Z23>0,AD23/Z23,0) -> 0.12341563 | AD23: =MAX(0,IF(Z23/2<='Barème fiscal'!$B$4,0,IF(Z23/2<='Barème fiscal'!$B$5,Z23*'Barème fiscal'!$C$5-'Barème fiscal'!$D$5*2,IF(Z23/2<='Barème fiscal'!$B$6,Z23*'Barème fiscal'!$C$6-'Barème fiscal'!$D$6*2,IF(Z23/2<='Barème fiscal'!$B$7,Z23*'Barème fiscal'!$C$7-'Barème fiscal'!$D$7*2,Z23*'Barème fiscal'!$C$8-'Barème fiscal'!$D$8*2)))))-MIN(MAX(IF(Z23/2<='Barème fiscal'!$B$4,0,IF(Z23/2<='Barème fiscal'!$B$5,Z23*'Barème fiscal'!$C$5-'Barème fiscal'!$D$5*2,IF(Z23/2<='Barème fiscal'!$B$6,Z23*'Barème fiscal'!$C$6-'Barème fiscal'!$D$6*2,IF(Z23/2<='Barème fiscal'!$B$7,Z23*'Barème fiscal'!$C$7-'Barème fiscal'!$D$7*2,Z23*'Barème fiscal'!$C$8-'Barème fiscal'!$D$8*2))))-MAX(0,IF(AA23<='Barème fiscal'!$B$4,0,IF(AA23<='Barème fiscal'!$B$5,Z23*'Barème fiscal'!$C$5-'Barème fiscal'!$D$5*'Hypothèses'!$B$39,IF(AA23<='Barème fiscal'!$B$6,Z23*'Barème fiscal'!$C$6-'Barème fiscal'!$D$6*'Hypothèses'!$B$39,IF(AA23<='Barème fiscal'!$B$7,Z23*'Barème fiscal'!$C$7-'Barème fiscal'!$D$7*'Hypothèses'!$B$39,Z23*'Barème fiscal'!$C$8-'Barème fiscal'!$D$8*'Hypothèses'!$B$39))))),0),MAX('Hypothèses'!$B$39-2,0)*2*'Barème fiscal'!$B$10) -> 10868.679 | AE23: =Y23*'Hypothèses'!$B$40 -> 466.90342 | AF23: =AD23+AE23 -> 11335.582 | AG23: =P23-AF23 -> 1021.3976 | AH23: =H23-G23-AS23 -> 178648.3 | AI23: =(B23-'Tableau dAMT financier'!G35-C23+AG23)/12 -> -530.59056 | AK23: =AK22+AI23*12 -> -121334.21 | AL23: =AL22+F23 -> 145600 | AM23: =MAX(0,A23*'Hypothèses'!$B$31*'Hypothèses'!$B$32-AL23) -> 0 | AN23: =H23-('Hypothèses'!$B$4+MAX('Hypothèses'!$B$4*'Hypothèses'!$B$5,'Hypothèses'!$B$4*'Hypothèses'!$B$43)+IF(A23>5,'Hypothèses'!$B$4*'Hypothèses'!$B$44,0)-AL23) -> 87100 | AO23: =IF(A23<=5,0,IF(A23<=21,(A23-5)*0.06,1)) -> 0.9 | AP23: =MAX(0,AN23*(1-AO23)) -> 8710 | AQ23: =IF(A23<=5,0,IF(A23<=21,(A23-5)*0.0165,IF(A23=22,(21-5)*0.0165+0.016,IF(A23<=30,(21-5)*0.0165+0.016+(A23-22)*0.09,1)))) -> 0.2475 | AR23: =MAX(0,AN23*(1-AQ23)) -> 65542.75 | AS23: =IF(AN23<=0,0,AP23*'Hypothèses'!$B$45+AR23*'Hypothèses'!$B$46+IF(AP23<=50000,0,IF(AP23<=60000,AP23*0.02-(60000-AP23)/20,IF(AP23<=100000,AP23*0.02,IF(AP23<=110000,AP23*0.03-(110000-AP23)/10,IF(AP23<=150000,AP23*0.03,IF(AP23<=160000,AP23*0.04-(160000-AP23)*3/20,IF(AP23<=200000,AP23*0.04,IF(AP23<=210000,AP23*0.05-(210000-AP23)/5,IF(AP23<=250000,AP23*0.05,IF(AP23<=260000,AP23*0.06-(260000-AP23)/4,AP23*0.06))))))))))) -> 12928.253 | AT23: =V12 -> 0 | AU23: =IFERROR(IRR(B79:V79),"") -> 0.029166183 | AV23: =MAX(0,I23)*'Barème fiscal'!$B$13 -> 340 | AW23: =Y23*'Barème fiscal'!$B$13 -> 184.58973
A24: 21 | B24: =B23*(1+'Hypothèses'!$B$27) -> 12121.695 | C24: =B24*'Hypothèses'!$B$28 -> 3636.5085 | D24: ='Tableau dAMT financier'!E36 -> 2065.5569 | E24: ='Tableau dAMT financier'!F36 -> 884.8 | F24: =MIN('Hypothèses'!$B$34,MAX(0,'Hypothèses'!$B$31-AL23)) -> 7280 | G24: ='Tableau dAMT financier'!H36 -> 55625.527 | H24: =H23*(1+index) -> 260000 | I24: =I23*(1+index) -> 5000 | J24: ='Hypothèses'!$B$50+I24-AV23 -> 90160 | K24: =J24/'Hypothèses'!$B$39 -> 36064 | L24: =IF(K24<='Barème fiscal'!$B$4,'Barème fiscal'!$C$4,IF(K24<='Barème fiscal'!$B$5,'Barème fiscal'!$C$5,IF(K24<='Barème fiscal'!$B$6,'Barème fiscal'!$C$6,IF(K24<='Barème fiscal'!$B$7,'Barème fiscal'!$C$7,'Barème fiscal'!$C$8)))) -> 0.3 | M24: =IF(J24>0,N24/J24,0) -> 0.12751752 | N24: =MAX(0,IF(J24/2<='Barème fiscal'!$B$4,0,IF(J24/2<='Barème fiscal'!$B$5,J24*'Barème fiscal'!$C$5-'Barème fiscal'!$D$5*2,IF(J24/2<='Barème fiscal'!$B$6,J24*'Barème fiscal'!$C$6-'Barème fiscal'!$D$6*2,IF(J24/2<='Barème fiscal'!$B$7,J24*'Barème fiscal'!$C$7-'Barème fiscal'!$D$7*2,J24*'Barème fiscal'!$C$8-'Barème fiscal'!$D$8*2)))))-MIN(MAX(IF(J24/2<='Barème fiscal'!$B$4,0,IF(J24/2<='Barème fiscal'!$B$5,J24*'Barème fiscal'!$C$5-'Barème fiscal'!$D$5*2,IF(J24/2<='Barème fiscal'!$B$6,J24*'Barème fiscal'!$C$6-'Barème fiscal'!$D$6*2,IF(J24/2<='Barème fiscal'!$B$7,J24*'Barème fiscal'!$C$7-'Barème fiscal'!$D$7*2,J24*'Barème fiscal'!$C$8-'Barème fiscal'!$D$8*2))))-MAX(0,IF(K24<='Barème fiscal'!$B$4,0,IF(K24<='Barème fiscal'!$B$5,J24*'Barème fiscal'!$C$5-'Barème fiscal'!$D$5*'Hypothèses'!$B$39,IF(K24<='Barème fiscal'!$B$6,J24*'Barème fiscal'!$C$6-'Barème fiscal'!$D$6*'Hypothèses'!$B$39,IF(K24<='Barème fiscal'!$B$7,J24*'Barème fiscal'!$C$7-'Barème fiscal'!$D$7*'Hypothèses'!$B$39,J24*'Barème fiscal'!$C$8-'Barème fiscal'!$D$8*'Hypothèses'!$B$39))))),0),MAX('Hypothèses'!$B$39-2,0)*2*'Barème fiscal'!$B$10) -> 11496.98 | O24: =MAX(0,I24)*'Hypothèses'!$B$40 -> 860 | P24: =N24+O24 -> 12356.98 | Q24: =B24+I24 -> 17121.695 | R24: =D24+E24 -> 2950.3569 | S24: =C24+F24 -> 10916.509 | T24: =Q24-R24-S24 -> 3254.8296 | U24: =IF(T24>=0,0,IF(Q24>=R24,MAX(T24,-'Barème fiscal'!$B$11),MAX(-S24,-'Barème fiscal'!$B$11))) -> 0 | V24: =IF(T24>=0,0,IF(Q24>=R24,MAX(0,-T24-'Barème fiscal'!$B$11),(R24-Q24)+MAX(0,S24-'Barème fiscal'!$B$11))) -> 0 | W24: =W23+V24-X23-AT24 -> 0 | X24: =IF(T24>0,MIN(W24,T24),0) -> 0 | Y24: =MAX(0,T24-X24) -> 3254.8296 | Z24: ='Hypothèses'!$B$50+Y24+U24-AW23 -> 88570.24 | AA24: =Z24/'Hypothèses'!$B$39 -> 35428.096 | AB24: =IF(AA24<='Barème fiscal'!$B$4,'Barème fiscal'!$C$4,IF(AA24<='Barème fiscal'!$B$5,'Barème fiscal'!$C$5,IF(AA24<='Barème fiscal'!$B$6,'Barème fiscal'!$C$6,IF(AA24<='Barème fiscal'!$B$7,'Barème fiscal'!$C$7,'Barème fiscal'!$C$8)))) -> 0.3 | AC24: =IF(Z24>0,AD24/Z24,0) -> 0.12442161 | AD24: =MAX(0,IF(Z24/2<='Barème fiscal'!$B$4,0,IF(Z24/2<='Barème fiscal'!$B$5,Z24*'Barème fiscal'!$C$5-'Barème fiscal'!$D$5*2,IF(Z24/2<='Barème fiscal'!$B$6,Z24*'Barème fiscal'!$C$6-'Barème fiscal'!$D$6*2,IF(Z24/2<='Barème fiscal'!$B$7,Z24*'Barème fiscal'!$C$7-'Barème fiscal'!$D$7*2,Z24*'Barème fiscal'!$C$8-'Barème fiscal'!$D$8*2)))))-MIN(MAX(IF(Z24/2<='Barème fiscal'!$B$4,0,IF(Z24/2<='Barème fiscal'!$B$5,Z24*'Barème fiscal'!$C$5-'Barème fiscal'!$D$5*2,IF(Z24/2<='Barème fiscal'!$B$6,Z24*'Barème fiscal'!$C$6-'Barème fiscal'!$D$6*2,IF(Z24/2<='Barème fiscal'!$B$7,Z24*'Barème fiscal'!$C$7-'Barème fiscal'!$D$7*2,Z24*'Barème fiscal'!$C$8-'Barème fiscal'!$D$8*2))))-MAX(0,IF(AA24<='Barème fiscal'!$B$4,0,IF(AA24<='Barème fiscal'!$B$5,Z24*'Barème fiscal'!$C$5-'Barème fiscal'!$D$5*'Hypothèses'!$B$39,IF(AA24<='Barème fiscal'!$B$6,Z24*'Barème fiscal'!$C$6-'Barème fiscal'!$D$6*'Hypothèses'!$B$39,IF(AA24<='Barème fiscal'!$B$7,Z24*'Barème fiscal'!$C$7-'Barème fiscal'!$D$7*'Hypothèses'!$B$39,Z24*'Barème fiscal'!$C$8-'Barème fiscal'!$D$8*'Hypothèses'!$B$39))))),0),MAX('Hypothèses'!$B$39-2,0)*2*'Barème fiscal'!$B$10) -> 11020.052 | AE24: =Y24*'Hypothèses'!$B$40 -> 559.8307 | AF24: =AD24+AE24 -> 11579.883 | AG24: =P24-AF24 -> 777.09733 | AH24: =H24-G24-AS24 -> 191709.43 | AI24: =(B24-'Tableau dAMT financier'!G36-C24+AG24)/12 -> -540.49918 | AK24: =AK23+AI24*12 -> -127820.2 | AL24: =AL23+F24 -> 152880 | AM24: =MAX(0,A24*'Hypothèses'!$B$31*'Hypothèses'!$B$32-AL24) -> 0 | AN24: =H24-('Hypothèses'!$B$4+MAX('Hypothèses'!$B$4*'Hypothèses'!$B$5,'Hypothèses'!$B$4*'Hypothèses'!$B$43)+IF(A24>5,'Hypothèses'!$B$4*'Hypothèses'!$B$44,0)-AL24) -> 94380 | AO24: =IF(A24<=5,0,IF(A24<=21,(A24-5)*0.06,1)) -> 0.96 | AP24: =MAX(0,AN24*(1-AO24)) -> 3775.2 | AQ24: =IF(A24<=5,0,IF(A24<=21,(A24-5)*0.0165,IF(A24=22,(21-5)*0.0165+0.016,IF(A24<=30,(21-5)*0.0165+0.016+(A24-22)*0.09,1)))) -> 0.264 | AR24: =MAX(0,AN24*(1-AQ24)) -> 69463.68 | AS24: =IF(AN24<=0,0,AP24*'Hypothèses'!$B$45+AR24*'Hypothèses'!$B$46+IF(AP24<=50000,0,IF(AP24<=60000,AP24*0.02-(60000-AP24)/20,IF(AP24<=100000,AP24*0.02,IF(AP24<=110000,AP24*0.03-(110000-AP24)/10,IF(AP24<=150000,AP24*0.03,IF(AP24<=160000,AP24*0.04-(160000-AP24)*3/20,IF(AP24<=200000,AP24*0.04,IF(AP24<=210000,AP24*0.05-(210000-AP24)/5,IF(AP24<=250000,AP24*0.05,IF(AP24<=260000,AP24*0.06-(260000-AP24)/4,AP24*0.06))))))))))) -> 12665.041 | AT24: =V13 -> 0 | AU24: =IFERROR(IRR(B80:W80),"") -> 0.029768453 | AV24: =MAX(0,I24)*'Barème fiscal'!$B$13 -> 340 | AW24: =Y24*'Barème fiscal'!$B$13 -> 221.32841
A25: 22 | B25: =B24*(1+'Hypothèses'!$B$27) -> 12303.52 | C25: =B25*'Hypothèses'!$B$28 -> 3691.0561 | D25: ='Tableau dAMT financier'!E37 -> 1636.779 | E25: ='Tableau dAMT financier'!F37 -> 884.8 | F25: =MIN('Hypothèses'!$B$34,MAX(0,'Hypothèses'!$B$31-AL24)) -> 7280 | G25: ='Tableau dAMT financier'!H37 -> 42398.832 | H25: =H24*(1+index) -> 260000 | I25: =I24*(1+index) -> 5000 | J25: ='Hypothèses'!$B$50+I25-AV24 -> 90160 | K25: =J25/'Hypothèses'!$B$39 -> 36064 | L25: =IF(K25<='Barème fiscal'!$B$4,'Barème fiscal'!$C$4,IF(K25<='Barème fiscal'!$B$5,'Barème fiscal'!$C$5,IF(K25<='Barème fiscal'!$B$6,'Barème fiscal'!$C$6,IF(K25<='Barème fiscal'!$B$7,'Barème fiscal'!$C$7,'Barème fiscal'!$C$8)))) -> 0.3 | M25: =IF(J25>0,N25/J25,0) -> 0.12751752 | N25: =MAX(0,IF(J25/2<='Barème fiscal'!$B$4,0,IF(J25/2<='Barème fiscal'!$B$5,J25*'Barème fiscal'!$C$5-'Barème fiscal'!$D$5*2,IF(J25/2<='Barème fiscal'!$B$6,J25*'Barème fiscal'!$C$6-'Barème fiscal'!$D$6*2,IF(J25/2<='Barème fiscal'!$B$7,J25*'Barème fiscal'!$C$7-'Barème fiscal'!$D$7*2,J25*'Barème fiscal'!$C$8-'Barème fiscal'!$D$8*2)))))-MIN(MAX(IF(J25/2<='Barème fiscal'!$B$4,0,IF(J25/2<='Barème fiscal'!$B$5,J25*'Barème fiscal'!$C$5-'Barème fiscal'!$D$5*2,IF(J25/2<='Barème fiscal'!$B$6,J25*'Barème fiscal'!$C$6-'Barème fiscal'!$D$6*2,IF(J25/2<='Barème fiscal'!$B$7,J25*'Barème fiscal'!$C$7-'Barème fiscal'!$D$7*2,J25*'Barème fiscal'!$C$8-'Barème fiscal'!$D$8*2))))-MAX(0,IF(K25<='Barème fiscal'!$B$4,0,IF(K25<='Barème fiscal'!$B$5,J25*'Barème fiscal'!$C$5-'Barème fiscal'!$D$5*'Hypothèses'!$B$39,IF(K25<='Barème fiscal'!$B$6,J25*'Barème fiscal'!$C$6-'Barème fiscal'!$D$6*'Hypothèses'!$B$39,IF(K25<='Barème fiscal'!$B$7,J25*'Barème fiscal'!$C$7-'Barème fiscal'!$D$7*'Hypothèses'!$B$39,J25*'Barème fiscal'!$C$8-'Barème fiscal'!$D$8*'Hypothèses'!$B$39))))),0),MAX('Hypothèses'!$B$39-2,0)*2*'Barème fiscal'!$B$10) -> 11496.98 | O25: =MAX(0,I25)*'Hypothèses'!$B$40 -> 860 | P25: =N25+O25 -> 12356.98 | Q25: =B25+I25 -> 17303.52 | R25: =D25+E25 -> 2521.579 | S25: =C25+F25 -> 10971.056 | T25: =Q25-R25-S25 -> 3810.8854 | U25: =IF(T25>=0,0,IF(Q25>=R25,MAX(T25,-'Barème fiscal'!$B$11),MAX(-S25,-'Barème fiscal'!$B$11))) -> 0 | V25: =IF(T25>=0,0,IF(Q25>=R25,MAX(0,-T25-'Barème fiscal'!$B$11),(R25-Q25)+MAX(0,S25-'Barème fiscal'!$B$11))) -> 0 | W25: =W24+V25-X24-AT25 -> 0 | X25: =IF(T25>0,MIN(W25,T25),0) -> 0 | Y25: =MAX(0,T25-X25) -> 3810.8854 | Z25: ='Hypothèses'!$B$50+Y25+U25-AW24 -> 89089.557 | AA25: =Z25/'Hypothèses'!$B$39 -> 35635.823 | AB25: =IF(AA25<='Barème fiscal'!$B$4,'Barème fiscal'!$C$4,IF(AA25<='Barème fiscal'!$B$5,'Barème fiscal'!$C$5,IF(AA25<='Barème fiscal'!$B$6,'Barème fiscal'!$C$6,IF(AA25<='Barème fiscal'!$B$7,'Barème fiscal'!$C$7,'Barème fiscal'!$C$8)))) -> 0.3 | AC25: =IF(Z25>0,AD25/Z25,0) -> 0.12544509 | AD25: =MAX(0,IF(Z25/2<='Barème fiscal'!$B$4,0,IF(Z25/2<='Barème fiscal'!$B$5,Z25*'Barème fiscal'!$C$5-'Barème fiscal'!$D$5*2,IF(Z25/2<='Barème fiscal'!$B$6,Z25*'Barème fiscal'!$C$6-'Barème fiscal'!$D$6*2,IF(Z25/2<='Barème fiscal'!$B$7,Z25*'Barème fiscal'!$C$7-'Barème fiscal'!$D$7*2,Z25*'Barème fiscal'!$C$8-'Barème fiscal'!$D$8*2)))))-MIN(MAX(IF(Z25/2<='Barème fiscal'!$B$4,0,IF(Z25/2<='Barème fiscal'!$B$5,Z25*'Barème fiscal'!$C$5-'Barème fiscal'!$D$5*2,IF(Z25/2<='Barème fiscal'!$B$6,Z25*'Barème fiscal'!$C$6-'Barème fiscal'!$D$6*2,IF(Z25/2<='Barème fiscal'!$B$7,Z25*'Barème fiscal'!$C$7-'Barème fiscal'!$D$7*2,Z25*'Barème fiscal'!$C$8-'Barème fiscal'!$D$8*2))))-MAX(0,IF(AA25<='Barème fiscal'!$B$4,0,IF(AA25<='Barème fiscal'!$B$5,Z25*'Barème fiscal'!$C$5-'Barème fiscal'!$D$5*'Hypothèses'!$B$39,IF(AA25<='Barème fiscal'!$B$6,Z25*'Barème fiscal'!$C$6-'Barème fiscal'!$D$6*'Hypothèses'!$B$39,IF(AA25<='Barème fiscal'!$B$7,Z25*'Barème fiscal'!$C$7-'Barème fiscal'!$D$7*'Hypothèses'!$B$39,Z25*'Barème fiscal'!$C$8-'Barème fiscal'!$D$8*'Hypothèses'!$B$39))))),0),MAX('Hypothèses'!$B$39-2,0)*2*'Barème fiscal'!$B$10) -> 11175.847 | AE25: =Y25*'Hypothèses'!$B$40 -> 655.47228 | AF25: =AD25+AE25 -> 11831.319 | AG25: =P25-AF25 -> 525.66063 | AH25: =H25-G25-AS25 -> 205011.59 | AI25: =(B25-'Tableau dAMT financier'!G37-C25+AG25)/12 -> -550.84576 | AK25: =AK24+AI25*12 -> -134430.35 | AL25: =AL24+F25 -> 160160 | AM25: =MAX(0,A25*'Hypothèses'!$B$31*'Hypothèses'!$B$32-AL25) -> 0 | AN25: =H25-('Hypothèses'!$B$4+MAX('Hypothèses'!$B$4*'Hypothèses'!$B$5,'Hypothèses'!$B$4*'Hypothèses'!$B$43)+IF(A25>5,'Hypothèses'!$B$4*'Hypothèses'!$B$44,0)-AL25) -> 101660 | AO25: =IF(A25<=5,0,IF(A25<=21,(A25-5)*0.06,1)) -> 1 | AP25: =MAX(0,AN25*(1-AO25)) -> 0 | AQ25: =IF(A25<=5,0,IF(A25<=21,(A25-5)*0.0165,IF(A25=22,(21-5)*0.0165+0.016,IF(A25<=30,(21-5)*0.0165+0.016+(A25-22)*0.09,1)))) -> 0.28 | AR25: =MAX(0,AN25*(1-AQ25)) -> 73195.2 | AS25: =IF(AN25<=0,0,AP25*'Hypothèses'!$B$45+AR25*'Hypothèses'!$B$46+IF(AP25<=50000,0,IF(AP25<=60000,AP25*0.02-(60000-AP25)/20,IF(AP25<=100000,AP25*0.02,IF(AP25<=110000,AP25*0.03-(110000-AP25)/10,IF(AP25<=150000,AP25*0.03,IF(AP25<=160000,AP25*0.04-(160000-AP25)*3/20,IF(AP25<=200000,AP25*0.04,IF(AP25<=210000,AP25*0.05-(210000-AP25)/5,IF(AP25<=250000,AP25*0.05,IF(AP25<=260000,AP25*0.06-(260000-AP25)/4,AP25*0.06))))))))))) -> 12589.574 | AT25: =V14 -> 0 | AU25: =IFERROR(IRR(B81:X81),"") -> 0.030155905 | AV25: =MAX(0,I25)*'Barème fiscal'!$B$13 -> 340 | AW25: =Y25*'Barème fiscal'!$B$13 -> 259.14021
A26: 23 | B26: =B25*(1+'Hypothèses'!$B$27) -> 12488.073 | C26: =B26*'Hypothèses'!$B$28 -> 3746.422 | D26: ='Tableau dAMT financier'!E38 -> 1193.6354 | E26: ='Tableau dAMT financier'!F38 -> 884.8 | F26: =MIN('Hypothèses'!$B$34,MAX(0,'Hypothèses'!$B$31-AL25)) -> 7280 | G26: ='Tableau dAMT financier'!H38 -> 28728.994 | H26: =H25*(1+index) -> 260000 | I26: =I25*(1+index) -> 5000 | J26: ='Hypothèses'!$B$50+I26-AV25 -> 90160 | K26: =J26/'Hypothèses'!$B$39 -> 36064 | L26: =IF(K26<='Barème fiscal'!$B$4,'Barème fiscal'!$C$4,IF(K26<='Barème fiscal'!$B$5,'Barème fiscal'!$C$5,IF(K26<='Barème fiscal'!$B$6,'Barème fiscal'!$C$6,IF(K26<='Barème fiscal'!$B$7,'Barème fiscal'!$C$7,'Barème fiscal'!$C$8)))) -> 0.3 | M26: =IF(J26>0,N26/J26,0) -> 0.12751752 | N26: =MAX(0,IF(J26/2<='Barème fiscal'!$B$4,0,IF(J26/2<='Barème fiscal'!$B$5,J26*'Barème fiscal'!$C$5-'Barème fiscal'!$D$5*2,IF(J26/2<='Barème fiscal'!$B$6,J26*'Barème fiscal'!$C$6-'Barème fiscal'!$D$6*2,IF(J26/2<='Barème fiscal'!$B$7,J26*'Barème fiscal'!$C$7-'Barème fiscal'!$D$7*2,J26*'Barème fiscal'!$C$8-'Barème fiscal'!$D$8*2)))))-MIN(MAX(IF(J26/2<='Barème fiscal'!$B$4,0,IF(J26/2<='Barème fiscal'!$B$5,J26*'Barème fiscal'!$C$5-'Barème fiscal'!$D$5*2,IF(J26/2<='Barème fiscal'!$B$6,J26*'Barème fiscal'!$C$6-'Barème fiscal'!$D$6*2,IF(J26/2<='Barème fiscal'!$B$7,J26*'Barème fiscal'!$C$7-'Barème fiscal'!$D$7*2,J26*'Barème fiscal'!$C$8-'Barème fiscal'!$D$8*2))))-MAX(0,IF(K26<='Barème fiscal'!$B$4,0,IF(K26<='Barème fiscal'!$B$5,J26*'Barème fiscal'!$C$5-'Barème fiscal'!$D$5*'Hypothèses'!$B$39,IF(K26<='Barème fiscal'!$B$6,J26*'Barème fiscal'!$C$6-'Barème fiscal'!$D$6*'Hypothèses'!$B$39,IF(K26<='Barème fiscal'!$B$7,J26*'Barème fiscal'!$C$7-'Barème fiscal'!$D$7*'Hypothèses'!$B$39,J26*'Barème fiscal'!$C$8-'Barème fiscal'!$D$8*'Hypothèses'!$B$39))))),0),MAX('Hypothèses'!$B$39-2,0)*2*'Barème fiscal'!$B$10) -> 11496.98 | O26: =MAX(0,I26)*'Hypothèses'!$B$40 -> 860 | P26: =N26+O26 -> 12356.98 | Q26: =B26+I26 -> 17488.073 | R26: =D26+E26 -> 2078.4354 | S26: =C26+F26 -> 11026.422 | T26: =Q26-R26-S26 -> 4383.2159 | U26: =IF(T26>=0,0,IF(Q26>=R26,MAX(T26,-'Barème fiscal'!$B$11),MAX(-S26,-'Barème fiscal'!$B$11))) -> 0 | V26: =IF(T26>=0,0,IF(Q26>=R26,MAX(0,-T26-'Barème fiscal'!$B$11),(R26-Q26)+MAX(0,S26-'Barème fiscal'!$B$11))) -> 0 | W26: =W25+V26-X25-AT26 -> 0 | X26: =IF(T26>0,MIN(W26,T26),0) -> 0 | Y26: =MAX(0,T26-X26) -> 4383.2159 | Z26: ='Hypothèses'!$B$50+Y26+U26-AW25 -> 89624.076 | AA26: =Z26/'Hypothèses'!$B$39 -> 35849.63 | AB26: =IF(AA26<='Barème fiscal'!$B$4,'Barème fiscal'!$C$4,IF(AA26<='Barème fiscal'!$B$5,'Barème fiscal'!$C$5,IF(AA26<='Barème fiscal'!$B$6,'Barème fiscal'!$C$6,IF(AA26<='Barème fiscal'!$B$7,'Barème fiscal'!$C$7,'Barème fiscal'!$C$8)))) -> 0.3 | AC26: =IF(Z26>0,AD26/Z26,0) -> 0.12648613 | AD26: =MAX(0,IF(Z26/2<='Barème fiscal'!$B$4,0,IF(Z26/2<='Barème fiscal'!$B$5,Z26*'Barème fiscal'!$C$5-'Barème fiscal'!$D$5*2,IF(Z26/2<='Barème fiscal'!$B$6,Z26*'Barème fiscal'!$C$6-'Barème fiscal'!$D$6*2,IF(Z26/2<='Barème fiscal'!$B$7,Z26*'Barème fiscal'!$C$7-'Barème fiscal'!$D$7*2,Z26*'Barème fiscal'!$C$8-'Barème fiscal'!$D$8*2)))))-MIN(MAX(IF(Z26/2<='Barème fiscal'!$B$4,0,IF(Z26/2<='Barème fiscal'!$B$5,Z26*'Barème fiscal'!$C$5-'Barème fiscal'!$D$5*2,IF(Z26/2<='Barème fiscal'!$B$6,Z26*'Barème fiscal'!$C$6-'Barème fiscal'!$D$6*2,IF(Z26/2<='Barème fiscal'!$B$7,Z26*'Barème fiscal'!$C$7-'Barème fiscal'!$D$7*2,Z26*'Barème fiscal'!$C$8-'Barème fiscal'!$D$8*2))))-MAX(0,IF(AA26<='Barème fiscal'!$B$4,0,IF(AA26<='Barème fiscal'!$B$5,Z26*'Barème fiscal'!$C$5-'Barème fiscal'!$D$5*'Hypothèses'!$B$39,IF(AA26<='Barème fiscal'!$B$6,Z26*'Barème fiscal'!$C$6-'Barème fiscal'!$D$6*'Hypothèses'!$B$39,IF(AA26<='Barème fiscal'!$B$7,Z26*'Barème fiscal'!$C$7-'Barème fiscal'!$D$7*'Hypothèses'!$B$39,Z26*'Barème fiscal'!$C$8-'Barème fiscal'!$D$8*'Hypothèses'!$B$39))))),0),MAX('Hypothèses'!$B$39-2,0)*2*'Barème fiscal'!$B$10) -> 11336.203 | AE26: =Y26*'Hypothèses'!$B$40 -> 753.91314 | AF26: =AD26+AE26 -> 12090.116 | AG26: =P26-AF26 -> 266.86414 | AH26: =H26-G26-AS26 -> 219466.27 | AI26: =(B26-'Tableau dAMT financier'!G38-C26+AG26)/12 -> -561.64655 | AK26: =AK25+AI26*12 -> -141170.11 | AL26: =AL25+F26 -> 167440 | AM26: =MAX(0,A26*'Hypothèses'!$B$31*'Hypothèses'!$B$32-AL26) -> 0 | AN26: =H26-('Hypothèses'!$B$4+MAX('Hypothèses'!$B$4*'Hypothèses'!$B$5,'Hypothèses'!$B$4*'Hypothèses'!$B$43)+IF(A26>5,'Hypothèses'!$B$4*'Hypothèses'!$B$44,0)-AL26) -> 108940 | AO26: =IF(A26<=5,0,IF(A26<=21,(A26-5)*0.06,1)) -> 1 | AP26: =MAX(0,AN26*(1-AO26)) -> 0 | AQ26: =IF(A26<=5,0,IF(A26<=21,(A26-5)*0.0165,IF(A26=22,(21-5)*0.0165+0.016,IF(A26<=30,(21-5)*0.0165+0.016+(A26-22)*0.09,1)))) -> 0.37 | AR26: =MAX(0,AN26*(1-AQ26)) -> 68632.2 | AS26: =IF(AN26<=0,0,AP26*'Hypothèses'!$B$45+AR26*'Hypothèses'!$B$46+IF(AP26<=50000,0,IF(AP26<=60000,AP26*0.02-(60000-AP26)/20,IF(AP26<=100000,AP26*0.02,IF(AP26<=110000,AP26*0.03-(110000-AP26)/10,IF(AP26<=150000,AP26*0.03,IF(AP26<=160000,AP26*0.04-(160000-AP26)*3/20,IF(AP26<=200000,AP26*0.04,IF(AP26<=210000,AP26*0.05-(210000-AP26)/5,IF(AP26<=250000,AP26*0.05,IF(AP26<=260000,AP26*0.06-(260000-AP26)/4,AP26*0.06))))))))))) -> 11804.738 | AT26: =V15 -> 0 | AU26: =IFERROR(IRR(B82:Y82),"") -> 0.030694793 | AV26: =MAX(0,I26)*'Barème fiscal'!$B$13 -> 340 | AW26: =Y26*'Barème fiscal'!$B$13 -> 298.05868
A27: 24 | B27: =B26*(1+'Hypothèses'!$B$27) -> 12675.394 | C27: =B27*'Hypothèses'!$B$28 -> 3802.6183 | D27: ='Tableau dAMT financier'!E39 -> 735.6448 | E27: ='Tableau dAMT financier'!F39 -> 884.8 | F27: =MIN('Hypothèses'!$B$34,MAX(0,'Hypothèses'!$B$31-AL26)) -> 7280 | G27: ='Tableau dAMT financier'!H39 -> 14601.164 | H27: =H26*(1+index) -> 260000 | I27: =I26*(1+index) -> 5000 | J27: ='Hypothèses'!$B$50+I27-AV26 -> 90160 | K27: =J27/'Hypothèses'!$B$39 -> 36064 | L27: =IF(K27<='Barème fiscal'!$B$4,'Barème fiscal'!$C$4,IF(K27<='Barème fiscal'!$B$5,'Barème fiscal'!$C$5,IF(K27<='Barème fiscal'!$B$6,'Barème fiscal'!$C$6,IF(K27<='Barème fiscal'!$B$7,'Barème fiscal'!$C$7,'Barème fiscal'!$C$8)))) -> 0.3 | M27: =IF(J27>0,N27/J27,0) -> 0.12751752 | N27: =MAX(0,IF(J27/2<='Barème fiscal'!$B$4,0,IF(J27/2<='Barème fiscal'!$B$5,J27*'Barème fiscal'!$C$5-'Barème fiscal'!$D$5*2,IF(J27/2<='Barème fiscal'!$B$6,J27*'Barème fiscal'!$C$6-'Barème fiscal'!$D$6*2,IF(J27/2<='Barème fiscal'!$B$7,J27*'Barème fiscal'!$C$7-'Barème fiscal'!$D$7*2,J27*'Barème fiscal'!$C$8-'Barème fiscal'!$D$8*2)))))-MIN(MAX(IF(J27/2<='Barème fiscal'!$B$4,0,IF(J27/2<='Barème fiscal'!$B$5,J27*'Barème fiscal'!$C$5-'Barème fiscal'!$D$5*2,IF(J27/2<='Barème fiscal'!$B$6,J27*'Barème fiscal'!$C$6-'Barème fiscal'!$D$6*2,IF(J27/2<='Barème fiscal'!$B$7,J27*'Barème fiscal'!$C$7-'Barème fiscal'!$D$7*2,J27*'Barème fiscal'!$C$8-'Barème fiscal'!$D$8*2))))-MAX(0,IF(K27<='Barème fiscal'!$B$4,0,IF(K27<='Barème fiscal'!$B$5,J27*'Barème fiscal'!$C$5-'Barème fiscal'!$D$5*'Hypothèses'!$B$39,IF(K27<='Barème fiscal'!$B$6,J27*'Barème fiscal'!$C$6-'Barème fiscal'!$D$6*'Hypothèses'!$B$39,IF(K27<='Barème fiscal'!$B$7,J27*'Barème fiscal'!$C$7-'Barème fiscal'!$D$7*'Hypothèses'!$B$39,J27*'Barème fiscal'!$C$8-'Barème fiscal'!$D$8*'Hypothèses'!$B$39))))),0),MAX('Hypothèses'!$B$39-2,0)*2*'Barème fiscal'!$B$10) -> 11496.98 | O27: =MAX(0,I27)*'Hypothèses'!$B$40 -> 860 | P27: =N27+O27 -> 12356.98 | Q27: =B27+I27 -> 17675.394 | R27: =D27+E27 -> 1620.4448 | S27: =C27+F27 -> 11082.618 | T27: =Q27-R27-S27 -> 4972.3313 | U27: =IF(T27>=0,0,IF(Q27>=R27,MAX(T27,-'Barème fiscal'!$B$11),MAX(-S27,-'Barème fiscal'!$B$11))) -> 0 | V27: =IF(T27>=0,0,IF(Q27>=R27,MAX(0,-T27-'Barème fiscal'!$B$11),(R27-Q27)+MAX(0,S27-'Barème fiscal'!$B$11))) -> 0 | W27: =W26+V27-X26-AT27 -> 0 | X27: =IF(T27>0,MIN(W27,T27),0) -> 0 | Y27: =MAX(0,T27-X27) -> 4972.3313 | Z27: ='Hypothèses'!$B$50+Y27+U27-AW26 -> 90174.273 | AA27: =Z27/'Hypothèses'!$B$39 -> 36069.709 | AB27: =IF(AA27<='Barème fiscal'!$B$4,'Barème fiscal'!$C$4,IF(AA27<='Barème fiscal'!$B$5,'Barème fiscal'!$C$5,IF(AA27<='Barème fiscal'!$B$6,'Barème fiscal'!$C$6,IF(AA27<='Barème fiscal'!$B$7,'Barème fiscal'!$C$7,'Barème fiscal'!$C$8)))) -> 0.3 | AC27: =IF(Z27>0,AD27/Z27,0) -> 0.12754482 | AD27: =MAX(0,IF(Z27/2<='Barème fiscal'!$B$4,0,IF(Z27/2<='Barème fiscal'!$B$5,Z27*'Barème fiscal'!$C$5-'Barème fiscal'!$D$5*2,IF(Z27/2<='Barème fiscal'!$B$6,Z27*'Barème fiscal'!$C$6-'Barème fiscal'!$D$6*2,IF(Z27/2<='Barème fiscal'!$B$7,Z27*'Barème fiscal'!$C$7-'Barème fiscal'!$D$7*2,Z27*'Barème fiscal'!$C$8-'Barème fiscal'!$D$8*2)))))-MIN(MAX(IF(Z27/2<='Barème fiscal'!$B$4,0,IF(Z27/2<='Barème fiscal'!$B$5,Z27*'Barème fiscal'!$C$5-'Barème fiscal'!$D$5*2,IF(Z27/2<='Barème fiscal'!$B$6,Z27*'Barème fiscal'!$C$6-'Barème fiscal'!$D$6*2,IF(Z27/2<='Barème fiscal'!$B$7,Z27*'Barème fiscal'!$C$7-'Barème fiscal'!$D$7*2,Z27*'Barème fiscal'!$C$8-'Barème fiscal'!$D$8*2))))-MAX(0,IF(AA27<='Barème fiscal'!$B$4,0,IF(AA27<='Barème fiscal'!$B$5,Z27*'Barème fiscal'!$C$5-'Barème fiscal'!$D$5*'Hypothèses'!$B$39,IF(AA27<='Barème fiscal'!$B$6,Z27*'Barème fiscal'!$C$6-'Barème fiscal'!$D$6*'Hypothèses'!$B$39,IF(AA27<='Barème fiscal'!$B$7,Z27*'Barème fiscal'!$C$7-'Barème fiscal'!$D$7*'Hypothèses'!$B$39,Z27*'Barème fiscal'!$C$8-'Barème fiscal'!$D$8*'Hypothèses'!$B$39))))),0),MAX('Hypothèses'!$B$39-2,0)*2*'Barème fiscal'!$B$10) -> 11501.262 | AE27: =Y27*'Hypothèses'!$B$40 -> 855.24098 | AF27: =AD27+AE27 -> 12356.503 | AG27: =P27-AF27 -> 0.47724157 | AH27: =H27-G27-AS27 -> 234604.32 | AI27: =(B27-'Tableau dAMT financier'!G39-C27+AG27)/12 -> -572.9184 | AK27: =AK26+AI27*12 -> -148045.13 | AL27: =AL26+F27 -> 174720 | AM27: =MAX(0,A27*'Hypothèses'!$B$31*'Hypothèses'!$B$32-AL27) -> 0 | AN27: =H27-('Hypothèses'!$B$4+MAX('Hypothèses'!$B$4*'Hypothèses'!$B$5,'Hypothèses'!$B$4*'Hypothèses'!$B$43)+IF(A27>5,'Hypothèses'!$B$4*'Hypothèses'!$B$44,0)-AL27) -> 116220 | AO27: =IF(A27<=5,0,IF(A27<=21,(A27-5)*0.06,1)) -> 1 | AP27: =MAX(0,AN27*(1-AO27)) -> 0 | AQ27: =IF(A27<=5,0,IF(A27<=21,(A27-5)*0.0165,IF(A27=22,(21-5)*0.0165+0.016,IF(A27<=30,(21-5)*0.0165+0.016+(A27-22)*0.09,1)))) -> 0.46 | AR27: =MAX(0,AN27*(1-AQ27)) -> 62758.8 | AS27: =IF(AN27<=0,0,AP27*'Hypothèses'!$B$45+AR27*'Hypothèses'!$B$46+IF(AP27<=50000,0,IF(AP27<=60000,AP27*0.02-(60000-AP27)/20,IF(AP27<=100000,AP27*0.02,IF(AP27<=110000,AP27*0.03-(110000-AP27)/10,IF(AP27<=150000,AP27*0.03,IF(AP27<=160000,AP27*0.04-(160000-AP27)*3/20,IF(AP27<=200000,AP27*0.04,IF(AP27<=210000,AP27*0.05-(210000-AP27)/5,IF(AP27<=250000,AP27*0.05,IF(AP27<=260000,AP27*0.06-(260000-AP27)/4,AP27*0.06))))))))))) -> 10794.514 | AT27: =V16 -> 0 | AU27: =IFERROR(IRR(B83:Z83),"") -> 0.031175466 | AV27: =MAX(0,I27)*'Barème fiscal'!$B$13 -> 340 | AW27: =Y27*'Barème fiscal'!$B$13 -> 338.11853
A28: 25 | B28: =B27*(1+'Hypothèses'!$B$27) -> 12865.525 | C28: =B28*'Hypothèses'!$B$28 -> 3859.6576 | D28: ='Tableau dAMT financier'!E40 -> 262.30983 | E28: ='Tableau dAMT financier'!F40 -> 884.8 | F28: =MIN('Hypothèses'!$B$34,MAX(0,'Hypothèses'!$B$31-AL27)) -> 7280 | G28: ='Tableau dAMT financier'!H40 -> 2.8521754e-09 | H28: =H27*(1+index) -> 260000 | I28: =I27*(1+index) -> 5000 | J28: ='Hypothèses'!$B$50+I28-AV27 -> 90160 | K28: =J28/'Hypothèses'!$B$39 -> 36064 | L28: =IF(K28<='Barème fiscal'!$B$4,'Barème fiscal'!$C$4,IF(K28<='Barème fiscal'!$B$5,'Barème fiscal'!$C$5,IF(K28<='Barème fiscal'!$B$6,'Barème fiscal'!$C$6,IF(K28<='Barème fiscal'!$B$7,'Barème fiscal'!$C$7,'Barème fiscal'!$C$8)))) -> 0.3 | M28: =IF(J28>0,N28/J28,0) -> 0.12751752 | N28: =MAX(0,IF(J28/2<='Barème fiscal'!$B$4,0,IF(J28/2<='Barème fiscal'!$B$5,J28*'Barème fiscal'!$C$5-'Barème fiscal'!$D$5*2,IF(J28/2<='Barème fiscal'!$B$6,J28*'Barème fiscal'!$C$6-'Barème fiscal'!$D$6*2,IF(J28/2<='Barème fiscal'!$B$7,J28*'Barème fiscal'!$C$7-'Barème fiscal'!$D$7*2,J28*'Barème fiscal'!$C$8-'Barème fiscal'!$D$8*2)))))-MIN(MAX(IF(J28/2<='Barème fiscal'!$B$4,0,IF(J28/2<='Barème fiscal'!$B$5,J28*'Barème fiscal'!$C$5-'Barème fiscal'!$D$5*2,IF(J28/2<='Barème fiscal'!$B$6,J28*'Barème fiscal'!$C$6-'Barème fiscal'!$D$6*2,IF(J28/2<='Barème fiscal'!$B$7,J28*'Barème fiscal'!$C$7-'Barème fiscal'!$D$7*2,J28*'Barème fiscal'!$C$8-'Barème fiscal'!$D$8*2))))-MAX(0,IF(K28<='Barème fiscal'!$B$4,0,IF(K28<='Barème fiscal'!$B$5,J28*'Barème fiscal'!$C$5-'Barème fiscal'!$D$5*'Hypothèses'!$B$39,IF(K28<='Barème fiscal'!$B$6,J28*'Barème fiscal'!$C$6-'Barème fiscal'!$D$6*'Hypothèses'!$B$39,IF(K28<='Barème fiscal'!$B$7,J28*'Barème fiscal'!$C$7-'Barème fiscal'!$D$7*'Hypothèses'!$B$39,J28*'Barème fiscal'!$C$8-'Barème fiscal'!$D$8*'Hypothèses'!$B$39))))),0),MAX('Hypothèses'!$B$39-2,0)*2*'Barème fiscal'!$B$10) -> 11496.98 | O28: =MAX(0,I28)*'Hypothèses'!$B$40 -> 860 | P28: =N28+O28 -> 12356.98 | Q28: =B28+I28 -> 17865.525 | R28: =D28+E28 -> 1147.1098 | S28: =C28+F28 -> 11139.658 | T28: =Q28-R28-S28 -> 5578.7579 | U28: =IF(T28>=0,0,IF(Q28>=R28,MAX(T28,-'Barème fiscal'!$B$11),MAX(-S28,-'Barème fiscal'!$B$11))) -> 0 | V28: =IF(T28>=0,0,IF(Q28>=R28,MAX(0,-T28-'Barème fiscal'!$B$11),(R28-Q28)+MAX(0,S28-'Barème fiscal'!$B$11))) -> 0 | W28: =W27+V28-X27-AT28 -> 0 | X28: =IF(T28>0,MIN(W28,T28),0) -> 0 | Y28: =MAX(0,T28-X28) -> 5578.7579 | Z28: ='Hypothèses'!$B$50+Y28+U28-AW27 -> 90740.639 | AA28: =Z28/'Hypothèses'!$B$39 -> 36296.256 | AB28: =IF(AA28<='Barème fiscal'!$B$4,'Barème fiscal'!$C$4,IF(AA28<='Barème fiscal'!$B$5,'Barème fiscal'!$C$5,IF(AA28<='Barème fiscal'!$B$6,'Barème fiscal'!$C$6,IF(AA28<='Barème fiscal'!$B$7,'Barème fiscal'!$C$7,'Barème fiscal'!$C$8)))) -> 0.3 | AC28: =IF(Z28>0,AD28/Z28,0) -> 0.12862122 | AD28: =MAX(0,IF(Z28/2<='Barème fiscal'!$B$4,0,IF(Z28/2<='Barème fiscal'!$B$5,Z28*'Barème fiscal'!$C$5-'Barème fiscal'!$D$5*2,IF(Z28/2<='Barème fiscal'!$B$6,Z28*'Barème fiscal'!$C$6-'Barème fiscal'!$D$6*2,IF(Z28/2<='Barème fiscal'!$B$7,Z28*'Barème fiscal'!$C$7-'Barème fiscal'!$D$7*2,Z28*'Barème fiscal'!$C$8-'Barème fiscal'!$D$8*2)))))-MIN(MAX(IF(Z28/2<='Barème fiscal'!$B$4,0,IF(Z28/2<='Barème fiscal'!$B$5,Z28*'Barème fiscal'!$C$5-'Barème fiscal'!$D$5*2,IF(Z28/2<='Barème fiscal'!$B$6,Z28*'Barème fiscal'!$C$6-'Barème fiscal'!$D$6*2,IF(Z28/2<='Barème fiscal'!$B$7,Z28*'Barème fiscal'!$C$7-'Barème fiscal'!$D$7*2,Z28*'Barème fiscal'!$C$8-'Barème fiscal'!$D$8*2))))-MAX(0,IF(AA28<='Barème fiscal'!$B$4,0,IF(AA28<='Barème fiscal'!$B$5,Z28*'Barème fiscal'!$C$5-'Barème fiscal'!$D$5*'Hypothèses'!$B$39,IF(AA28<='Barème fiscal'!$B$6,Z28*'Barème fiscal'!$C$6-'Barème fiscal'!$D$6*'Hypothèses'!$B$39,IF(AA28<='Barème fiscal'!$B$7,Z28*'Barème fiscal'!$C$7-'Barème fiscal'!$D$7*'Hypothèses'!$B$39,Z28*'Barème fiscal'!$C$8-'Barème fiscal'!$D$8*'Hypothèses'!$B$39))))),0),MAX('Hypothèses'!$B$39-2,0)*2*'Barème fiscal'!$B$10) -> 11671.172 | AE28: =Y28*'Hypothèses'!$B$40 -> 959.54636 | AF28: =AD28+AE28 -> 12630.718 | AG28: =P28-AF28 -> -273.73816 | AH28: =H28-G28-AS28 -> 250441.1 | AI28: =(B28-'Tableau dAMT financier'!G40-C28+AG28)/12 -> -584.67871 | AK28: =AK27+AI28*12 -> -155061.28 | AL28: =AL27+F28 -> 182000 | AM28: =MAX(0,A28*'Hypothèses'!$B$31*'Hypothèses'!$B$32-AL28) -> 0 | AN28: =H28-('Hypothèses'!$B$4+MAX('Hypothèses'!$B$4*'Hypothèses'!$B$5,'Hypothèses'!$B$4*'Hypothèses'!$B$43)+IF(A28>5,'Hypothèses'!$B$4*'Hypothèses'!$B$44,0)-AL28) -> 123500 | AO28: =IF(A28<=5,0,IF(A28<=21,(A28-5)*0.06,1)) -> 1 | AP28: =MAX(0,AN28*(1-AO28)) -> 0 | AQ28: =IF(A28<=5,0,IF(A28<=21,(A28-5)*0.0165,IF(A28=22,(21-5)*0.0165+0.016,IF(A28<=30,(21-5)*0.0165+0.016+(A28-22)*0.09,1)))) -> 0.55 | AR28: =MAX(0,AN28*(1-AQ28)) -> 55575 | AS28: =IF(AN28<=0,0,AP28*'Hypothèses'!$B$45+AR28*'Hypothèses'!$B$46+IF(AP28<=50000,0,IF(AP28<=60000,AP28*0.02-(60000-AP28)/20,IF(AP28<=100000,AP28*0.02,IF(AP28<=110000,AP28*0.03-(110000-AP28)/10,IF(AP28<=150000,AP28*0.03,IF(AP28<=160000,AP28*0.04-(160000-AP28)*3/20,IF(AP28<=200000,AP28*0.04,IF(AP28<=210000,AP28*0.05-(210000-AP28)/5,IF(AP28<=250000,AP28*0.05,IF(AP28<=260000,AP28*0.06-(260000-AP28)/4,AP28*0.06))))))))))) -> 9558.9 | AT28: =V17 -> 0 | AU28: =IFERROR(IRR(B84:AA84),"") -> 0.031601639 | AV28: =MAX(0,I28)*'Barème fiscal'!$B$13 -> 340 | AW28: =Y28*'Barème fiscal'!$B$13 -> 379.35554
A29: TOTAL | B29: =SUM(B4:B28) -> 270567.21 | C29: =SUM(C4:C28) -> 81170.164 | D29: =SUM(D4:D28) -> 118786.85 | E29: =SUM(E4:E28) -> 22120 | F29: =SUM(F4:F28) -> 182000 | N29: =SUM(N4:N28) -> 287526.5 | O29: =SUM(O4:O28) -> 21500 | P29: =SUM(P4:P28) -> 309026.5 | U29: =SUM(U4:U28) -> -43212.701 | V29: =SUM(V4:V28) -> 0 | AD29: =SUM(AD4:AD28) -> 248209.03 | AE29: =SUM(AE4:AE28) -> 5280.8985 | AF29: =SUM(AF4:AF28) -> 253489.92 | AG29: =SUM(AG4:AG28) -> 55536.575 | AI29: =SUM(AI4:AI28) -> -12397.769 | AL29: =AL28 -> 182000 | AT29: =SUM(AT4:AT28) -> 0
A32: SYNTHÈSE GLOBALE
A34: Apport personnel | D34: ='Hypothèses'!B14 -> 15000
A35: Montant emprunté | D35: ='Hypothèses'!B15 -> 252800
A37: Total loyers perçus | D37: =B29 -> 270567.21
A38: Total charges | D38: =C29 -> 81170.164
A39: Total intérêts | D39: =D29 -> 118786.85
A40: Total assurances | D40: =E29 -> 22120
A41: Total amort. Jeanbrun | D41: =F29 -> 182000
A43: Économie fiscale totale | D43: =AG29 -> 55536.575
A44: dont économie IR | D44: =N29-AD29 -> 39317.473
A45: dont économie PS | D45: =O29-AE29 -> 16219.102
A47: Cash-flow cumulé | D47: =AK29
A48: Enrichissement final | D48: =AH29
A49: Valeur bien finale
A50: CRD final
A52: Stock déficit reportable
A53: Total déficits imputés
A58: ZONE AUXILIAIRE — CALCUL TRI (ne pas modifier)
A59: Scénario | B59: An 0 | C59: An 1 | D59: An 2 | E59: An 3 | F59: An 4 | G59: An 5 | H59: An 6 | I59: An 7 | J59: An 8 | K59: An 9 | L59: An 10 | M59: An 11 | N59: An 12 | O59: An 13 | P59: An 14 | Q59: An 15 | R59: An 16 | S59: An 17 | T59: An 18 | U59: An 19 | V59: An 20 | W59: An 21 | X59: An 22 | Y59: An 23 | Z59: An 24 | AA59: An 25
A60: Sortie an 1 | B60: =-'Hypothèses'!$B$14 -> -15000 | C60: =B4-'Tableau dAMT financier'!G16-C4+AG4+H4-G4-AS4 -> 9464.6387
A61: Sortie an 2 | B61: =-'Hypothèses'!$B$14 -> -15000 | C61: =B4-'Tableau dAMT financier'!G16-C4+AG4 -> -4355.9764 | D61: =B5-'Tableau dAMT financier'!G17-C5+AG5+H5-G5-AS5 -> 15004.674
A62: Sortie an 3 | B62: =-'Hypothèses'!$B$14 -> -15000 | C62: =B4-'Tableau dAMT financier'!G16-C4+AG4 -> -4355.9764 | D62: =B5-'Tableau dAMT financier'!G17-C5+AG5 -> -5658.371 | E62: =B6-'Tableau dAMT financier'!G18-C6+AG6+H6-G6-AS6 -> 21227.64
A63: Sortie an 4 | B63: =-'Hypothèses'!$B$14 -> -15000 | C63: =B4-'Tableau dAMT financier'!G16-C4+AG4 -> -4355.9764 | D63: =B5-'Tableau dAMT financier'!G17-C5+AG5 -> -5658.371 | E63: =B6-'Tableau dAMT financier'!G18-C6+AG6 -> -5660.0028 | F63: =B7-'Tableau dAMT financier'!G19-C7+AG7+H7-G7-AS7 -> 25897.956
A64: Sortie an 5 | B64: =-'Hypothèses'!$B$14 -> -15000 | C64: =B4-'Tableau dAMT financier'!G16-C4+AG4 -> -4355.9764 | D64: =B5-'Tableau dAMT financier'!G17-C5+AG5 -> -5658.371 | E64: =B6-'Tableau dAMT financier'!G18-C6+AG6 -> -5660.0028 | F64: =B7-'Tableau dAMT financier'!G19-C7+AG7 -> -5662.9317 | G64: =B8-'Tableau dAMT financier'!G20-C8+AG8+H8-G8-AS8 -> 30811.778
A65: Sortie an 6 | B65: =-'Hypothèses'!$B$14 -> -15000 | C65: =B4-'Tableau dAMT financier'!G16-C4+AG4 -> -4355.9764 | D65: =B5-'Tableau dAMT financier'!G17-C5+AG5 -> -5658.371 | E65: =B6-'Tableau dAMT financier'!G18-C6+AG6 -> -5660.0028 | F65: =B7-'Tableau dAMT financier'!G19-C7+AG7 -> -5662.9317 | G65: =B8-'Tableau dAMT financier'!G20-C8+AG8 -> -5667.2197 | H65: =B9-'Tableau dAMT financier'!G21-C9+AG9+H9-G9-AS9 -> 44730.406
A66: Sortie an 7 | B66: =-'Hypothèses'!$B$14 -> -15000 | C66: =B4-'Tableau dAMT financier'!G16-C4+AG4 -> -4355.9764 | D66: =B5-'Tableau dAMT financier'!G17-C5+AG5 -> -5658.371 | E66: =B6-'Tableau dAMT financier'!G18-C6+AG6 -> -5660.0028 | F66: =B7-'Tableau dAMT financier'!G19-C7+AG7 -> -5662.9317 | G66: =B8-'Tableau dAMT financier'!G20-C8+AG8 -> -5667.2197 | H66: =B9-'Tableau dAMT financier'!G21-C9+AG9 -> -5672.9313 | I66: =B10-'Tableau dAMT financier'!G22-C10+AG10+H10-G10-AS10 -> 52791.292
A67: Sortie an 8 | B67: =-'Hypothèses'!$B$14 -> -15000 | C67: =B4-'Tableau dAMT financier'!G16-C4+AG4 -> -4355.9764 | D67: =B5-'Tableau dAMT financier'!G17-C5+AG5 -> -5658.371 | E67: =B6-'Tableau dAMT financier'!G18-C6+AG6 -> -5660.0028 | F67: =B7-'Tableau dAMT financier'!G19-C7+AG7 -> -5662.9317 | G67: =B8-'Tableau dAMT financier'!G20-C8+AG8 -> -5667.2197 | H67: =B9-'Tableau dAMT financier'!G21-C9+AG9 -> -5672.9313 | I67: =B10-'Tableau dAMT financier'!G22-C10+AG10 -> -5680.1335 | J67: =B11-'Tableau dAMT financier'!G23-C11+AG11+H11-G11-AS11 -> 61120.929
A68: Sortie an 9 | B68: =-'Hypothèses'!$B$14 -> -15000 | C68: =B4-'Tableau dAMT financier'!G16-C4+AG4 -> -4355.9764 | D68: =B5-'Tableau dAMT financier'!G17-C5+AG5 -> -5658.371 | E68: =B6-'Tableau dAMT financier'!G18-C6+AG6 -> -5660.0028 | F68: =B7-'Tableau dAMT financier'!G19-C7+AG7 -> -5662.9317 | G68: =B8-'Tableau dAMT financier'!G20-C8+AG8 -> -5667.2197 | H68: =B9-'Tableau dAMT financier'!G21-C9+AG9 -> -5672.9313 | I68: =B10-'Tableau dAMT financier'!G22-C10+AG10 -> -5680.1335 | J68: =B11-'Tableau dAMT financier'!G23-C11+AG11 -> -5688.8955 | K68: =B12-'Tableau dAMT financier'!G24-C12+AG12+H12-G12-AS12 -> 67586.865
A69: Sortie an 10 | B69: =-'Hypothèses'!$B$14 -> -15000 | C69: =B4-'Tableau dAMT financier'!G16-C4+AG4 -> -4355.9764 | D69: =B5-'Tableau dAMT financier'!G17-C5+AG5 -> -5658.371 | E69: =B6-'Tableau dAMT financier'!G18-C6+AG6 -> -5660.0028 | F69: =B7-'Tableau dAMT financier'!G19-C7+AG7 -> -5662.9317 | G69: =B8-'Tableau dAMT financier'!G20-C8+AG8 -> -5667.2197 | H69: =B9-'Tableau dAMT financier'!G21-C9+AG9 -> -5672.9313 | I69: =B10-'Tableau dAMT financier'!G22-C10+AG10 -> -5680.1335 | J69: =B11-'Tableau dAMT financier'!G23-C11+AG11 -> -5688.8955 | K69: =B12-'Tableau dAMT financier'!G24-C12+AG12 -> -5699.2895 | L69: =B13-'Tableau dAMT financier'!G25-C13+AG13+H13-G13-AS13 -> 74464.112
A70: Sortie an 11 | B70: =-'Hypothèses'!$B$14 -> -15000 | C70: =B4-'Tableau dAMT financier'!G16-C4+AG4 -> -4355.9764 | D70: =B5-'Tableau dAMT financier'!G17-C5+AG5 -> -5658.371 | E70: =B6-'Tableau dAMT financier'!G18-C6+AG6 -> -5660.0028 | F70: =B7-'Tableau dAMT financier'!G19-C7+AG7 -> -5662.9317 | G70: =B8-'Tableau dAMT financier'!G20-C8+AG8 -> -5667.2197 | H70: =B9-'Tableau dAMT financier'!G21-C9+AG9 -> -5672.9313 | I70: =B10-'Tableau dAMT financier'!G22-C10+AG10 -> -5680.1335 | J70: =B11-'Tableau dAMT financier'!G23-C11+AG11 -> -5688.8955 | K70: =B12-'Tableau dAMT financier'!G24-C12+AG12 -> -5699.2895 | L70: =B13-'Tableau dAMT financier'!G25-C13+AG13 -> -5711.3902 | M70: =B14-'Tableau dAMT financier'!G26-C14+AG14+H14-G14-AS14 -> 81845.281
A71: Sortie an 12 | B71: =-'Hypothèses'!$B$14 -> -15000 | C71: =B4-'Tableau dAMT financier'!G16-C4+AG4 -> -4355.9764 | D71: =B5-'Tableau dAMT financier'!G17-C5+AG5 -> -5658.371 | E71: =B6-'Tableau dAMT financier'!G18-C6+AG6 -> -5660.0028 | F71: =B7-'Tableau dAMT financier'!G19-C7+AG7 -> -5662.9317 | G71: =B8-'Tableau dAMT financier'!G20-C8+AG8 -> -5667.2197 | H71: =B9-'Tableau dAMT financier'!G21-C9+AG9 -> -5672.9313 | I71: =B10-'Tableau dAMT financier'!G22-C10+AG10 -> -5680.1335 | J71: =B11-'Tableau dAMT financier'!G23-C11+AG11 -> -5688.8955 | K71: =B12-'Tableau dAMT financier'!G24-C12+AG12 -> -5699.2895 | L71: =B13-'Tableau dAMT financier'!G25-C13+AG13 -> -5711.3902 | M71: =B14-'Tableau dAMT financier'!G26-C14+AG14 -> -5725.2752 | N71: =B15-'Tableau dAMT financier'!G27-C15+AG15+H15-G15-AS15 -> 89740.288
A72: Sortie an 13 | B72: =-'Hypothèses'!$B$14 -> -15000 | C72: =B4-'Tableau dAMT financier'!G16-C4+AG4 -> -4355.9764 | D72: =B5-'Tableau dAMT financier'!G17-C5+AG5 -> -5658.371 | E72: =B6-'Tableau dAMT financier'!G18-C6+AG6 -> -5660.0028 | F72: =B7-'Tableau dAMT financier'!G19-C7+AG7 -> -5662.9317 | G72: =B8-'Tableau dAMT financier'!G20-C8+AG8 -> -5667.2197 | H72: =B9-'Tableau dAMT financier'!G21-C9+AG9 -> -5672.9313 | I72: =B10-'Tableau dAMT financier'!G22-C10+AG10 -> -5680.1335 | J72: =B11-'Tableau dAMT financier'!G23-C11+AG11 -> -5688.8955 | K72: =B12-'Tableau dAMT financier'!G24-C12+AG12 -> -5699.2895 | L72: =B13-'Tableau dAMT financier'!G25-C13+AG13 -> -5711.3902 | M72: =B14-'Tableau dAMT financier'!G26-C14+AG14 -> -5725.2752 | N72: =B15-'Tableau dAMT financier'!G27-C15+AG15 -> -5741.0249 | O72: =B16-'Tableau dAMT financier'!G28-C16+AG16+H16-G16-AS16 -> 98159.384
A73: Sortie an 14 | B73: =-'Hypothèses'!$B$14 -> -15000 | C73: =B4-'Tableau dAMT financier'!G16-C4+AG4 -> -4355.9764 | D73: =B5-'Tableau dAMT financier'!G17-C5+AG5 -> -5658.371 | E73: =B6-'Tableau dAMT financier'!G18-C6+AG6 -> -5660.0028 | F73: =B7-'Tableau dAMT financier'!G19-C7+AG7 -> -5662.9317 | G73: =B8-'Tableau dAMT financier'!G20-C8+AG8 -> -5667.2197 | H73: =B9-'Tableau dAMT financier'!G21-C9+AG9 -> -5672.9313 | I73: =B10-'Tableau dAMT financier'!G22-C10+AG10 -> -5680.1335 | J73: =B11-'Tableau dAMT financier'!G23-C11+AG11 -> -5688.8955 | K73: =B12-'Tableau dAMT financier'!G24-C12+AG12 -> -5699.2895 | L73: =B13-'Tableau dAMT financier'!G25-C13+AG13 -> -5711.3902 | M73: =B14-'Tableau dAMT financier'!G26-C14+AG14 -> -5725.2752 | N73: =B15-'Tableau dAMT financier'!G27-C15+AG15 -> -5741.0249 | O73: =B16-'Tableau dAMT financier'!G28-C16+AG16 -> -5758.7228 | P73: =B17-'Tableau dAMT financier'!G29-C17+AG17+H17-G17-AS17 -> 107113.16
A74: Sortie an 15 | B74: =-'Hypothèses'!$B$14 -> -15000 | C74: =B4-'Tableau dAMT financier'!G16-C4+AG4 -> -4355.9764 | D74: =B5-'Tableau dAMT financier'!G17-C5+AG5 -> -5658.371 | E74: =B6-'Tableau dAMT financier'!G18-C6+AG6 -> -5660.0028 | F74: =B7-'Tableau dAMT financier'!G19-C7+AG7 -> -5662.9317 | G74: =B8-'Tableau dAMT financier'!G20-C8+AG8 -> -5667.2197 | H74: =B9-'Tableau dAMT financier'!G21-C9+AG9 -> -5672.9313 | I74: =B10-'Tableau dAMT financier'!G22-C10+AG10 -> -5680.1335 | J74: =B11-'Tableau dAMT financier'!G23-C11+AG11 -> -5688.8955 | K74: =B12-'Tableau dAMT financier'!G24-C12+AG12 -> -5699.2895 | L74: =B13-'Tableau dAMT financier'!G25-C13+AG13 -> -5711.3902 | M74: =B14-'Tableau dAMT financier'!G26-C14+AG14 -> -5725.2752 | N74: =B15-'Tableau dAMT financier'!G27-C15+AG15 -> -5741.0249 | O74: =B16-'Tableau dAMT financier'!G28-C16+AG16 -> -5758.7228 | P74: =B17-'Tableau dAMT financier'!G29-C17+AG17 -> -5778.4555 | Q74: =B18-'Tableau dAMT financier'!G30-C18+AG18+H18-G18-AS18 -> 116572.37
A75: Sortie an 16 | B75: =-'Hypothèses'!$B$14 -> -15000 | C75: =B4-'Tableau dAMT financier'!G16-C4+AG4 -> -4355.9764 | D75: =B5-'Tableau dAMT financier'!G17-C5+AG5 -> -5658.371 | E75: =B6-'Tableau dAMT financier'!G18-C6+AG6 -> -5660.0028 | F75: =B7-'Tableau dAMT financier'!G19-C7+AG7 -> -5662.9317 | G75: =B8-'Tableau dAMT financier'!G20-C8+AG8 -> -5667.2197 | H75: =B9-'Tableau dAMT financier'!G21-C9+AG9 -> -5672.9313 | I75: =B10-'Tableau dAMT financier'!G22-C10+AG10 -> -5680.1335 | J75: =B11-'Tableau dAMT financier'!G23-C11+AG11 -> -5688.8955 | K75: =B12-'Tableau dAMT financier'!G24-C12+AG12 -> -5699.2895 | L75: =B13-'Tableau dAMT financier'!G25-C13+AG13 -> -5711.3902 | M75: =B14-'Tableau dAMT financier'!G26-C14+AG14 -> -5725.2752 | N75: =B15-'Tableau dAMT financier'!G27-C15+AG15 -> -5741.0249 | O75: =B16-'Tableau dAMT financier'!G28-C16+AG16 -> -5758.7228 | P75: =B17-'Tableau dAMT financier'!G29-C17+AG17 -> -5778.4555 | Q75: =B18-'Tableau dAMT financier'!G30-C18+AG18 -> -5840.5033 | R75: =B19-'Tableau dAMT financier'!G31-C19+AG19+H19-G19-AS19 -> 126552.94
A76: Sortie an 17 | B76: =-'Hypothèses'!$B$14 -> -15000 | C76: =B4-'Tableau dAMT financier'!G16-C4+AG4 -> -4355.9764 | D76: =B5-'Tableau dAMT financier'!G17-C5+AG5 -> -5658.371 | E76: =B6-'Tableau dAMT financier'!G18-C6+AG6 -> -5660.0028 | F76: =B7-'Tableau dAMT financier'!G19-C7+AG7 -> -5662.9317 | G76: =B8-'Tableau dAMT financier'!G20-C8+AG8 -> -5667.2197 | H76: =B9-'Tableau dAMT financier'!G21-C9+AG9 -> -5672.9313 | I76: =B10-'Tableau dAMT financier'!G22-C10+AG10 -> -5680.1335 | J76: =B11-'Tableau dAMT financier'!G23-C11+AG11 -> -5688.8955 | K76: =B12-'Tableau dAMT financier'!G24-C12+AG12 -> -5699.2895 | L76: =B13-'Tableau dAMT financier'!G25-C13+AG13 -> -5711.3902 | M76: =B14-'Tableau dAMT financier'!G26-C14+AG14 -> -5725.2752 | N76: =B15-'Tableau dAMT financier'!G27-C15+AG15 -> -5741.0249 | O76: =B16-'Tableau dAMT financier'!G28-C16+AG16 -> -5758.7228 | P76: =B17-'Tableau dAMT financier'!G29-C17+AG17 -> -5778.4555 | Q76: =B18-'Tableau dAMT financier'!G30-C18+AG18 -> -5840.5033 | R76: =B19-'Tableau dAMT financier'!G31-C19+AG19 -> -5940.351 | S76: =B20-'Tableau dAMT financier'!G32-C20+AG20+H20-G20-AS20 -> 137104.6
A77: Sortie an 18 | B77: =-'Hypothèses'!$B$14 -> -15000 | C77: =B4-'Tableau dAMT financier'!G16-C4+AG4 -> -4355.9764 | D77: =B5-'Tableau dAMT financier'!G17-C5+AG5 -> -5658.371 | E77: =B6-'Tableau dAMT financier'!G18-C6+AG6 -> -5660.0028 | F77: =B7-'Tableau dAMT financier'!G19-C7+AG7 -> -5662.9317 | G77: =B8-'Tableau dAMT financier'!G20-C8+AG8 -> -5667.2197 | H77: =B9-'Tableau dAMT financier'!G21-C9+AG9 -> -5672.9313 | I77: =B10-'Tableau dAMT financier'!G22-C10+AG10 -> -5680.1335 | J77: =B11-'Tableau dAMT financier'!G23-C11+AG11 -> -5688.8955 | K77: =B12-'Tableau dAMT financier'!G24-C12+AG12 -> -5699.2895 | L77: =B13-'Tableau dAMT financier'!G25-C13+AG13 -> -5711.3902 | M77: =B14-'Tableau dAMT financier'!G26-C14+AG14 -> -5725.2752 | N77: =B15-'Tableau dAMT financier'!G27-C15+AG15 -> -5741.0249 | O77: =B16-'Tableau dAMT financier'!G28-C16+AG16 -> -5758.7228 | P77: =B17-'Tableau dAMT financier'!G29-C17+AG17 -> -5778.4555 | Q77: =B18-'Tableau dAMT financier'!G30-C18+AG18 -> -5840.5033 | R77: =B19-'Tableau dAMT financier'!G31-C19+AG19 -> -5940.351 | S77: =B20-'Tableau dAMT financier'!G32-C20+AG20 -> -6040.0554 | T77: =B21-'Tableau dAMT financier'!G33-C21+AG21+H21-G21-AS21 -> 148234.85
A78: Sortie an 19 | B78: =-'Hypothèses'!$B$14 -> -15000 | C78: =B4-'Tableau dAMT financier'!G16-C4+AG4 -> -4355.9764 | D78: =B5-'Tableau dAMT financier'!G17-C5+AG5 -> -5658.371 | E78: =B6-'Tableau dAMT financier'!G18-C6+AG6 -> -5660.0028 | F78: =B7-'Tableau dAMT financier'!G19-C7+AG7 -> -5662.9317 | G78: =B8-'Tableau dAMT financier'!G20-C8+AG8 -> -5667.2197 | H78: =B9-'Tableau dAMT financier'!G21-C9+AG9 -> -5672.9313 | I78: =B10-'Tableau dAMT financier'!G22-C10+AG10 -> -5680.1335 | J78: =B11-'Tableau dAMT financier'!G23-C11+AG11 -> -5688.8955 | K78: =B12-'Tableau dAMT financier'!G24-C12+AG12 -> -5699.2895 | L78: =B13-'Tableau dAMT financier'!G25-C13+AG13 -> -5711.3902 | M78: =B14-'Tableau dAMT financier'!G26-C14+AG14 -> -5725.2752 | N78: =B15-'Tableau dAMT financier'!G27-C15+AG15 -> -5741.0249 | O78: =B16-'Tableau dAMT financier'!G28-C16+AG16 -> -5758.7228 | P78: =B17-'Tableau dAMT financier'!G29-C17+AG17 -> -5778.4555 | Q78: =B18-'Tableau dAMT financier'!G30-C18+AG18 -> -5840.5033 | R78: =B19-'Tableau dAMT financier'!G31-C19+AG19 -> -5940.351 | S78: =B20-'Tableau dAMT financier'!G32-C20+AG20 -> -6040.0554 | T78: =B21-'Tableau dAMT financier'!G33-C21+AG21 -> -6144.2985 | U78: =B22-'Tableau dAMT financier'!G34-C22+AG22+H22-G22-AS22 -> 159956.11
A79: Sortie an 20 | B79: =-'Hypothèses'!$B$14 -> -15000 | C79: =B4-'Tableau dAMT financier'!G16-C4+AG4 -> -4355.9764 | D79: =B5-'Tableau dAMT financier'!G17-C5+AG5 -> -5658.371 | E79: =B6-'Tableau dAMT financier'!G18-C6+AG6 -> -5660.0028 | F79: =B7-'Tableau dAMT financier'!G19-C7+AG7 -> -5662.9317 | G79: =B8-'Tableau dAMT financier'!G20-C8+AG8 -> -5667.2197 | H79: =B9-'Tableau dAMT financier'!G21-C9+AG9 -> -5672.9313 | I79: =B10-'Tableau dAMT financier'!G22-C10+AG10 -> -5680.1335 | J79: =B11-'Tableau dAMT financier'!G23-C11+AG11 -> -5688.8955 | K79: =B12-'Tableau dAMT financier'!G24-C12+AG12 -> -5699.2895 | L79: =B13-'Tableau dAMT financier'!G25-C13+AG13 -> -5711.3902 | M79: =B14-'Tableau dAMT financier'!G26-C14+AG14 -> -5725.2752 | N79: =B15-'Tableau dAMT financier'!G27-C15+AG15 -> -5741.0249 | O79: =B16-'Tableau dAMT financier'!G28-C16+AG16 -> -5758.7228 | P79: =B17-'Tableau dAMT financier'!G29-C17+AG17 -> -5778.4555 | Q79: =B18-'Tableau dAMT financier'!G30-C18+AG18 -> -5840.5033 | R79: =B19-'Tableau dAMT financier'!G31-C19+AG19 -> -5940.351 | S79: =B20-'Tableau dAMT financier'!G32-C20+AG20 -> -6040.0554 | T79: =B21-'Tableau dAMT financier'!G33-C21+AG21 -> -6144.2985 | U79: =B22-'Tableau dAMT financier'!G34-C22+AG22 -> -6253.2502 | V79: =B23-'Tableau dAMT financier'!G35-C23+AG23+H23-G23-AS23 -> 172281.22
A80: Sortie an 21 | B80: =-'Hypothèses'!$B$14 -> -15000 | C80: =B4-'Tableau dAMT financier'!G16-C4+AG4 -> -4355.9764 | D80: =B5-'Tableau dAMT financier'!G17-C5+AG5 -> -5658.371 | E80: =B6-'Tableau dAMT financier'!G18-C6+AG6 -> -5660.0028 | F80: =B7-'Tableau dAMT financier'!G19-C7+AG7 -> -5662.9317 | G80: =B8-'Tableau dAMT financier'!G20-C8+AG8 -> -5667.2197 | H80: =B9-'Tableau dAMT financier'!G21-C9+AG9 -> -5672.9313 | I80: =B10-'Tableau dAMT financier'!G22-C10+AG10 -> -5680.1335 | J80: =B11-'Tableau dAMT financier'!G23-C11+AG11 -> -5688.8955 | K80: =B12-'Tableau dAMT financier'!G24-C12+AG12 -> -5699.2895 | L80: =B13-'Tableau dAMT financier'!G25-C13+AG13 -> -5711.3902 | M80: =B14-'Tableau dAMT financier'!G26-C14+AG14 -> -5725.2752 | N80: =B15-'Tableau dAMT financier'!G27-C15+AG15 -> -5741.0249 | O80: =B16-'Tableau dAMT financier'!G28-C16+AG16 -> -5758.7228 | P80: =B17-'Tableau dAMT financier'!G29-C17+AG17 -> -5778.4555 | Q80: =B18-'Tableau dAMT financier'!G30-C18+AG18 -> -5840.5033 | R80: =B19-'Tableau dAMT financier'!G31-C19+AG19 -> -5940.351 | S80: =B20-'Tableau dAMT financier'!G32-C20+AG20 -> -6040.0554 | T80: =B21-'Tableau dAMT financier'!G33-C21+AG21 -> -6144.2985 | U80: =B22-'Tableau dAMT financier'!G34-C22+AG22 -> -6253.2502 | V80: =B23-'Tableau dAMT financier'!G35-C23+AG23 -> -6367.0868 | W80: =B24-'Tableau dAMT financier'!G36-C24+AG24+H24-G24-AS24 -> 185223.44
A81: Sortie an 22 | B81: =-'Hypothèses'!$B$14 -> -15000 | C81: =B4-'Tableau dAMT financier'!G16-C4+AG4 -> -4355.9764 | D81: =B5-'Tableau dAMT financier'!G17-C5+AG5 -> -5658.371 | E81: =B6-'Tableau dAMT financier'!G18-C6+AG6 -> -5660.0028 | F81: =B7-'Tableau dAMT financier'!G19-C7+AG7 -> -5662.9317 | G81: =B8-'Tableau dAMT financier'!G20-C8+AG8 -> -5667.2197 | H81: =B9-'Tableau dAMT financier'!G21-C9+AG9 -> -5672.9313 | I81: =B10-'Tableau dAMT financier'!G22-C10+AG10 -> -5680.1335 | J81: =B11-'Tableau dAMT financier'!G23-C11+AG11 -> -5688.8955 | K81: =B12-'Tableau dAMT financier'!G24-C12+AG12 -> -5699.2895 | L81: =B13-'Tableau dAMT financier'!G25-C13+AG13 -> -5711.3902 | M81: =B14-'Tableau dAMT financier'!G26-C14+AG14 -> -5725.2752 | N81: =B15-'Tableau dAMT financier'!G27-C15+AG15 -> -5741.0249 | O81: =B16-'Tableau dAMT financier'!G28-C16+AG16 -> -5758.7228 | P81: =B17-'Tableau dAMT financier'!G29-C17+AG17 -> -5778.4555 | Q81: =B18-'Tableau dAMT financier'!G30-C18+AG18 -> -5840.5033 | R81: =B19-'Tableau dAMT financier'!G31-C19+AG19 -> -5940.351 | S81: =B20-'Tableau dAMT financier'!G32-C20+AG20 -> -6040.0554 | T81: =B21-'Tableau dAMT financier'!G33-C21+AG21 -> -6144.2985 | U81: =B22-'Tableau dAMT financier'!G34-C22+AG22 -> -6253.2502 | V81: =B23-'Tableau dAMT financier'!G35-C23+AG23 -> -6367.0868 | W81: =B24-'Tableau dAMT financier'!G36-C24+AG24 -> -6485.9902 | X81: =B25-'Tableau dAMT financier'!G37-C25+AG25+H25-G25-AS25 -> 198401.44
A82: Sortie an 23 | B82: =-'Hypothèses'!$B$14 -> -15000 | C82: =B4-'Tableau dAMT financier'!G16-C4+AG4 -> -4355.9764 | D82: =B5-'Tableau dAMT financier'!G17-C5+AG5 -> -5658.371 | E82: =B6-'Tableau dAMT financier'!G18-C6+AG6 -> -5660.0028 | F82: =B7-'Tableau dAMT financier'!G19-C7+AG7 -> -5662.9317 | G82: =B8-'Tableau dAMT financier'!G20-C8+AG8 -> -5667.2197 | H82: =B9-'Tableau dAMT financier'!G21-C9+AG9 -> -5672.9313 | I82: =B10-'Tableau dAMT financier'!G22-C10+AG10 -> -5680.1335 | J82: =B11-'Tableau dAMT financier'!G23-C11+AG11 -> -5688.8955 | K82: =B12-'Tableau dAMT financier'!G24-C12+AG12 -> -5699.2895 | L82: =B13-'Tableau dAMT financier'!G25-C13+AG13 -> -5711.3902 | M82: =B14-'Tableau dAMT financier'!G26-C14+AG14 -> -5725.2752 | N82: =B15-'Tableau dAMT financier'!G27-C15+AG15 -> -5741.0249 | O82: =B16-'Tableau dAMT financier'!G28-C16+AG16 -> -5758.7228 | P82: =B17-'Tableau dAMT financier'!G29-C17+AG17 -> -5778.4555 | Q82: =B18-'Tableau dAMT financier'!G30-C18+AG18 -> -5840.5033 | R82: =B19-'Tableau dAMT financier'!G31-C19+AG19 -> -5940.351 | S82: =B20-'Tableau dAMT financier'!G32-C20+AG20 -> -6040.0554 | T82: =B21-'Tableau dAMT financier'!G33-C21+AG21 -> -6144.2985 | U82: =B22-'Tableau dAMT financier'!G34-C22+AG22 -> -6253.2502 | V82: =B23-'Tableau dAMT financier'!G35-C23+AG23 -> -6367.0868 | W82: =B24-'Tableau dAMT financier'!G36-C24+AG24 -> -6485.9902 | X82: =B25-'Tableau dAMT financier'!G37-C25+AG25 -> -6610.1491 | Y82: =B26-'Tableau dAMT financier'!G38-C26+AG26+H26-G26-AS26 -> 212726.51
A83: Sortie an 24 | B83: =-'Hypothèses'!$B$14 -> -15000 | C83: =B4-'Tableau dAMT financier'!G16-C4+AG4 -> -4355.9764 | D83: =B5-'Tableau dAMT financier'!G17-C5+AG5 -> -5658.371 | E83: =B6-'Tableau dAMT financier'!G18-C6+AG6 -> -5660.0028 | F83: =B7-'Tableau dAMT financier'!G19-C7+AG7 -> -5662.9317 | G83: =B8-'Tableau dAMT financier'!G20-C8+AG8 -> -5667.2197 | H83: =B9-'Tableau dAMT financier'!G21-C9+AG9 -> -5672.9313 | I83: =B10-'Tableau dAMT financier'!G22-C10+AG10 -> -5680.1335 | J83: =B11-'Tableau dAMT financier'!G23-C11+AG11 -> -5688.8955 | K83: =B12-'Tableau dAMT financier'!G24-C12+AG12 -> -5699.2895 | L83: =B13-'Tableau dAMT financier'!G25-C13+AG13 -> -5711.3902 | M83: =B14-'Tableau dAMT financier'!G26-C14+AG14 -> -5725.2752 | N83: =B15-'Tableau dAMT financier'!G27-C15+AG15 -> -5741.0249 | O83: =B16-'Tableau dAMT financier'!G28-C16+AG16 -> -5758.7228 | P83: =B17-'Tableau dAMT financier'!G29-C17+AG17 -> -5778.4555 | Q83: =B18-'Tableau dAMT financier'!G30-C18+AG18 -> -5840.5033 | R83: =B19-'Tableau dAMT financier'!G31-C19+AG19 -> -5940.351 | S83: =B20-'Tableau dAMT financier'!G32-C20+AG20 -> -6040.0554 | T83: =B21-'Tableau dAMT financier'!G33-C21+AG21 -> -6144.2985 | U83: =B22-'Tableau dAMT financier'!G34-C22+AG22 -> -6253.2502 | V83: =B23-'Tableau dAMT financier'!G35-C23+AG23 -> -6367.0868 | W83: =B24-'Tableau dAMT financier'!G36-C24+AG24 -> -6485.9902 | X83: =B25-'Tableau dAMT financier'!G37-C25+AG25 -> -6610.1491 | Y83: =B26-'Tableau dAMT financier'!G38-C26+AG26 -> -6739.7586 | Z83: =B27-'Tableau dAMT financier'!G39-C27+AG27+H27-G27-AS27 -> 227729.3
A84: Sortie an 25 | B84: =-'Hypothèses'!$B$14 -> -15000 | C84: =B4-'Tableau dAMT financier'!G16-C4+AG4 -> -4355.9764 | D84: =B5-'Tableau dAMT financier'!G17-C5+AG5 -> -5658.371 | E84: =B6-'Tableau dAMT financier'!G18-C6+AG6 -> -5660.0028 | F84: =B7-'Tableau dAMT financier'!G19-C7+AG7 -> -5662.9317 | G84: =B8-'Tableau dAMT financier'!G20-C8+AG8 -> -5667.2197 | H84: =B9-'Tableau dAMT financier'!G21-C9+AG9 -> -5672.9313 | I84: =B10-'Tableau dAMT financier'!G22-C10+AG10 -> -5680.1335 | J84: =B11-'Tableau dAMT financier'!G23-C11+AG11 -> -5688.8955 | K84: =B12-'Tableau dAMT financier'!G24-C12+AG12 -> -5699.2895 | L84: =B13-'Tableau dAMT financier'!G25-C13+AG13 -> -5711.3902 | M84: =B14-'Tableau dAMT financier'!G26-C14+AG14 -> -5725.2752 | N84: =B15-'Tableau dAMT financier'!G27-C15+AG15 -> -5741.0249 | O84: =B16-'Tableau dAMT financier'!G28-C16+AG16 -> -5758.7228 | P84: =B17-'Tableau dAMT financier'!G29-C17+AG17 -> -5778.4555 | Q84: =B18-'Tableau dAMT financier'!G30-C18+AG18 -> -5840.5033 | R84: =B19-'Tableau dAMT financier'!G31-C19+AG19 -> -5940.351 | S84: =B20-'Tableau dAMT financier'!G32-C20+AG20 -> -6040.0554 | T84: =B21-'Tableau dAMT financier'!G33-C21+AG21 -> -6144.2985 | U84: =B22-'Tableau dAMT financier'!G34-C22+AG22 -> -6253.2502 | V84: =B23-'Tableau dAMT financier'!G35-C23+AG23 -> -6367.0868 | W84: =B24-'Tableau dAMT financier'!G36-C24+AG24 -> -6485.9902 | X84: =B25-'Tableau dAMT financier'!G37-C25+AG25 -> -6610.1491 | Y84: =B26-'Tableau dAMT financier'!G38-C26+AG26 -> -6739.7586 | Z84: =B27-'Tableau dAMT financier'!G39-C27+AG27 -> -6875.0208 | AA84: =B28-'Tableau dAMT financier'!G40-C28+AG28+H28-G28-AS28 -> 243424.96
A90: DONNÉES GRAPHIQUES ENRICHISSEMENT (ne pas modifier)
A91: Année | B91: 1 | C91: 2 | D91: 3 | E91: 4 | F91: 5 | G91: 6 | H91: 7 | I91: 8 | J91: 9 | K91: 10 | L91: 11 | M91: 12 | N91: 13 | O91: 14 | P91: 15 | Q91: 16 | R91: 17 | S91: 18 | T91: 19 | U91: 20 | V91: 21 | W91: 22 | X91: 23 | Y91: 24 | Z91: 25
A92: Prix vente 0% | B92: ='Hypothèses'!$B$4 -> 260000 | C92: ='Hypothèses'!$B$4 -> 260000 | D92: ='Hypothèses'!$B$4 -> 260000 | E92: ='Hypothèses'!$B$4 -> 260000 | F92: ='Hypothèses'!$B$4 -> 260000 | G92: ='Hypothèses'!$B$4 -> 260000 | H92: ='Hypothèses'!$B$4 -> 260000 | I92: ='Hypothèses'!$B$4 -> 260000 | ... Z92: ='Hypothèses'!$B$4 -> 260000
A93: Prix vente 1.5%/an | B93: ='Hypothèses'!$B$4*(1.015^1) -> 263900 | C93: ='Hypothèses'!$B$4*(1.015^2) -> 267858.5 | D93: ='Hypothèses'!$B$4*(1.015^3) -> 271876.38 | E93: ='Hypothèses'!$B$4*(1.015^4) -> 275954.52 | F93: ='Hypothèses'!$B$4*(1.015^5) -> 280093.84 | G93: ='Hypothèses'!$B$4*(1.015^6) -> 284295.25 | H93: ='Hypothèses'!$B$4*(1.015^7) -> 288559.68 | I93: ='Hypothèses'!$B$4*(1.015^8) -> 292888.07 | J93: ='Hypothèses'!$B$4*(1.015^9) -> 297281.39 | K93: ='Hypothèses'!$B$4*(1.015^10) -> 301740.61 | L93: ='Hypothèses'!$B$4*(1.015^11) -> 306266.72 | M93: ='Hypothèses'!$B$4*(1.015^12) -> 310860.72 | N93: ='Hypothèses'!$B$4*(1.015^13) -> 315523.64 | O93: ='Hypothèses'!$B$4*(1.015^14) -> 320256.49 | P93: ='Hypothèses'!$B$4*(1.015^15) -> 325060.34 | Q93: ='Hypothèses'!$B$4*(1.015^16) -> 329936.24 | R93: ='Hypothèses'!$B$4*(1.015^17) -> 334885.29 | S93: ='Hypothèses'!$B$4*(1.015^18) -> 339908.57 | T93: ='Hypothèses'!$B$4*(1.015^19) -> 345007.19 | U93: ='Hypothèses'!$B$4*(1.015^20) -> 350182.3 | V93: ='Hypothèses'!$B$4*(1.015^21) -> 355435.04 | W93: ='Hypothèses'!$B$4*(1.015^22) -> 360766.56 | X93: ='Hypothèses'!$B$4*(1.015^23) -> 366178.06 | Y93: ='Hypothèses'!$B$4*(1.015^24) -> 371670.73 | Z93: ='Hypothèses'!$B$4*(1.015^25) -> 377245.79
